Workbook

Sheet TEAM
A1: Position | B1: Player | C1: Team | D1: Price (m) | E1: Expected Points
A2: =IFERROR(INDEX(TEAM_BUILDER!$A$6:$A$201,MATCH(1,INDEX((TEAM_BUILDER!$G$6:$G$201=1)*(COUNTIF($B$1:B1,TEAM_BUILDER!$C$6:$C$201)=0),0),0)),"") -> GK | B2: =IFERROR(INDEX(TEAM_BUILDER!$C$6:$C$201,MATCH(ROWS($B$2:B2),TEAM_BUILDER!$I$6:$I$201,0)),"") -> Konstantinos Tzolakis | C2: =IFERROR(INDEX(TEAM_BUILDER!$D$6:$D$201,MATCH($B2,TEAM_BUILDER!$C$6:$C$201,0)),"") -> HUL | D2: =IFERROR(INDEX(TEAM_BUILDER!$E$6:$E$201,MATCH($B2,TEAM_BUILDER!$C$6:$C$201,0)),"") -> 4.6 | E2: =IFERROR(INDEX(TEAM_BUILDER!$H$6:$H$201,MATCH($B2,TEAM_BUILDER!$C$6:$C$201,0)),"") -> 8.4
A3: =IFERROR(INDEX(TEAM_BUILDER!$A$6:$A$201,MATCH(1,INDEX((TEAM_BUILDER!$G$6:$G$201=1)*(COUNTIF($B$1:B2,TEAM_BUILDER!$C$6:$C$201)=0),0),0)),"") -> GK | B3: =IFERROR(INDEX(TEAM_BUILDER!$C$6:$C$201,MATCH(ROWS($B$2:B3),TEAM_BUILDER!$I$6:$I$201,0)),"") -> David Raya Martín | C3: =IFERROR(INDEX(TEAM_BUILDER!$D$6:$D$201,MATCH($B3,TEAM_BUILDER!$C$6:$C$201,0)),"") -> ARS | D3: =IFERROR(INDEX(TEAM_BUILDER!$E$6:$E$201,MATCH($B3,TEAM_BUILDER!$C$6:$C$201,0)),"") -> 6 | E3: =IFERROR(INDEX(TEAM_BUILDER!$H$6:$H$201,MATCH($B3,TEAM_BUILDER!$C$6:$C$201,0)),"") -> 6.1779862
A4: =IFERROR(INDEX(TEAM_BUILDER!$A$6:$A$201,MATCH(1,INDEX((TEAM_BUILDER!$G$6:$G$201=1)*(COUNTIF($B$1:B3,TEAM_BUILDER!$C$6:$C$201)=0),0),0)),"") -> DEF | B4: =IFERROR(INDEX(TEAM_BUILDER!$C$6:$C$201,MATCH(ROWS($B$2:B4),TEAM_BUILDER!$I$6:$I$201,0)),"") -> John Egan | C4: =IFERROR(INDEX(TEAM_BUILDER!$D$6:$D$201,MATCH($B4,TEAM_BUILDER!$C$6:$C$201,0)),"") -> HUL | D4: =IFERROR(INDEX(TEAM_BUILDER!$E$6:$E$201,MATCH($B4,TEAM_BUILDER!$C$6:$C$201,0)),"") -> 4.1 | E4: =IFERROR(INDEX(TEAM_BUILDER!$H$6:$H$201,MATCH($B4,TEAM_BUILDER!$C$6:$C$201,0)),"") -> 10.502855
A5: =IFERROR(INDEX(TEAM_BUILDER!$A$6:$A$201,MATCH(1,INDEX((TEAM_BUILDER!$G$6:$G$201=1)*(COUNTIF($B$1:B4,TEAM_BUILDER!$C$6:$C$201)=0),0),0)),"") -> DEF | B5: =IFERROR(INDEX(TEAM_BUILDER!$C$6:$C$201,MATCH(ROWS($B$2:B5),TEAM_BUILDER!$I$6:$I$201,0)),"") -> Semi Ajayi | C5: =IFERROR(INDEX(TEAM_BUILDER!$D$6:$D$201,MATCH($B5,TEAM_BUILDER!$C$6:$C$201,0)),"") -> HUL | D5: =IFERROR(INDEX(TEAM_BUILDER!$E$6:$E$201,MATCH($B5,TEAM_BUILDER!$C$6:$C$201,0)),"") -> 4.1 | E5: =IFERROR(INDEX(TEAM_BUILDER!$H$6:$H$201,MATCH($B5,TEAM_BUILDER!$C$6:$C$201,0)),"") -> 10.364444
A6: =IFERROR(INDEX(TEAM_BUILDER!$A$6:$A$201,MATCH(1,INDEX((TEAM_BUILDER!$G$6:$G$201=1)*(COUNTIF($B$1:B5,TEAM_BUILDER!$C$6:$C$201)=0),0),0)),"") -> DEF | B6: =IFERROR(INDEX(TEAM_BUILDER!$C$6:$C$201,MATCH(ROWS($B$2:B6),TEAM_BUILDER!$I$6:$I$201,0)),"") -> Gabriel dos Santos Magalhães | C6: =IFERROR(INDEX(TEAM_BUILDER!$D$6:$D$201,MATCH($B6,TEAM_BUILDER!$C$6:$C$201,0)),"") -> ARS | D6: =IFERROR(INDEX(TEAM_BUILDER!$E$6:$E$201,MATCH($B6,TEAM_BUILDER!$C$6:$C$201,0)),"") -> 8 | E6: =IFERROR(INDEX(TEAM_BUILDER!$H$6:$H$201,MATCH($B6,TEAM_BUILDER!$C$6:$C$201,0)),"") -> 8.1528293 | H6: =IF(G6=1,COUNTIF($G$6:G6,1),"")
A7: =IFERROR(INDEX(TEAM_BUILDER!$A$6:$A$201,MATCH(1,INDEX((TEAM_BUILDER!$G$6:$G$201=1)*(COUNTIF($B$1:B6,TEAM_BUILDER!$C$6:$C$201)=0),0),0)),"") -> DEF | B7: =IFERROR(INDEX(TEAM_BUILDER!$C$6:$C$201,MATCH(ROWS($B$2:B7),TEAM_BUILDER!$I$6:$I$201,0)),"") -> Jayden Bogle | C7: =IFERROR(INDEX(TEAM_BUILDER!$D$6:$D$201,MATCH($B7,TEAM_BUILDER!$C$6:$C$201,0)),"") -> LEE | D7: =IFERROR(INDEX(TEAM_BUILDER!$E$6:$E$201,MATCH($B7,TEAM_BUILDER!$C$6:$C$201,0)),"") -> 4.5 | E7: =IFERROR(INDEX(TEAM_BUILDER!$H$6:$H$201,MATCH($B7,TEAM_BUILDER!$C$6:$C$201,0)),"") -> 8.1476383
A8: =IFERROR(INDEX(TEAM_BUILDER!$A$6:$A$201,MATCH(1,INDEX((TEAM_BUILDER!$G$6:$G$201=1)*(COUNTIF($B$1:B7,TEAM_BUILDER!$C$6:$C$201)=0),0),0)),"") -> DEF | B8: =IFERROR(INDEX(TEAM_BUILDER!$C$6:$C$201,MATCH(ROWS($B$2:B8),TEAM_BUILDER!$I$6:$I$201,0)),"") -> Riccardo Calafiori | C8: =IFERROR(INDEX(TEAM_BUILDER!$D$6:$D$201,MATCH($B8,TEAM_BUILDER!$C$6:$C$201,0)),"") -> ARS | D8: =IFERROR(INDEX(TEAM_BUILDER!$E$6:$E$201,MATCH($B8,TEAM_BUILDER!$C$6:$C$201,0)),"") -> 5.7 | E8: =IFERROR(INDEX(TEAM_BUILDER!$H$6:$H$201,MATCH($B8,TEAM_BUILDER!$C$6:$C$201,0)),"") -> 8.1388646
A9: =IFERROR(INDEX(TEAM_BUILDER!$A$6:$A$201,MATCH(1,INDEX((TEAM_BUILDER!$G$6:$G$201=1)*(COUNTIF($B$1:B8,TEAM_BUILDER!$C$6:$C$201)=0),0),0)),"") -> MID | B9: =IFERROR(INDEX(TEAM_BUILDER!$C$6:$C$201,MATCH(ROWS($B$2:B9),TEAM_BUILDER!$I$6:$I$201,0)),"") -> Bryan Mbeumo | C9: =IFERROR(INDEX(TEAM_BUILDER!$D$6:$D$201,MATCH($B9,TEAM_BUILDER!$C$6:$C$201,0)),"") -> MUN | D9: =IFERROR(INDEX(TEAM_BUILDER!$E$6:$E$201,MATCH($B9,TEAM_BUILDER!$C$6:$C$201,0)),"") -> 7.9 | E9: =IFERROR(INDEX(TEAM_BUILDER!$H$6:$H$201,MATCH($B9,TEAM_BUILDER!$C$6:$C$201,0)),"") -> 7.787795
A10: =IFERROR(INDEX(TEAM_BUILDER!$A$6:$A$201,MATCH(1,INDEX((TEAM_BUILDER!$G$6:$G$201=1)*(COUNTIF($B$1:B9,TEAM_BUILDER!$C$6:$C$201)=0),0),0)),"") -> MID | B10: =IFERROR(INDEX(TEAM_BUILDER!$C$6:$C$201,MATCH(ROWS($B$2:B10),TEAM_BUILDER!$I$6:$I$201,0)),"") -> Phil Foden | C10: =IFERROR(INDEX(TEAM_BUILDER!$D$6:$D$201,MATCH($B10,TEAM_BUILDER!$C$6:$C$201,0)),"") -> MCI | D10: =IFERROR(INDEX(TEAM_BUILDER!$E$6:$E$201,MATCH($B10,TEAM_BUILDER!$C$6:$C$201,0)),"") -> 7 | E10: =IFERROR(INDEX(TEAM_BUILDER!$H$6:$H$201,MATCH($B10,TEAM_BUILDER!$C$6:$C$201,0)),"") -> 7.6213819
A11: =IFERROR(INDEX(TEAM_BUILDER!$A$6:$A$201,MATCH(1,INDEX((TEAM_BUILDER!$G$6:$G$201=1)*(COUNTIF($B$1:B10,TEAM_BUILDER!$C$6:$C$201)=0),0),0)),"") -> MID | B11: =IFERROR(INDEX(TEAM_BUILDER!$C$6:$C$201,MATCH(ROWS($B$2:B11),TEAM_BUILDER!$I$6:$I$201,0)),"") -> Dango Ouattara | C11: =IFERROR(INDEX(TEAM_BUILDER!$D$6:$D$201,MATCH($B11,TEAM_BUILDER!$C$6:$C$201,0)),"") -> BRE | D11: =IFERROR(INDEX(TEAM_BUILDER!$E$6:$E$201,MATCH($B11,TEAM_BUILDER!$C$6:$C$201,0)),"") -> 6.4 | E11: =IFERROR(INDEX(TEAM_BUILDER!$H$6:$H$201,MATCH($B11,TEAM_BUILDER!$C$6:$C$201,0)),"") -> 7.4311304
A12: =IFERROR(INDEX(TEAM_BUILDER!$A$6:$A$201,MATCH(1,INDEX((TEAM_BUILDER!$G$6:$G$201=1)*(COUNTIF($B$1:B11,TEAM_BUILDER!$C$6:$C$201)=0),0),0)),"") -> MID | B12: =IFERROR(INDEX(TEAM_BUILDER!$C$6:$C$201,MATCH(ROWS($B$2:B12),TEAM_BUILDER!$I$6:$I$201,0)),"") -> Rayan Cherki | C12: =IFERROR(INDEX(TEAM_BUILDER!$D$6:$D$201,MATCH($B12,TEAM_BUILDER!$C$6:$C$201,0)),"") -> MCI | D12: =IFERROR(INDEX(TEAM_BUILDER!$E$6:$E$201,MATCH($B12,TEAM_BUILDER!$C$6:$C$201,0)),"") -> 7.8 | E12: =IFERROR(INDEX(TEAM_BUILDER!$H$6:$H$201,MATCH($B12,TEAM_BUILDER!$C$6:$C$201,0)),"") -> 7.2204286
A13: =IFERROR(INDEX(TEAM_BUILDER!$A$6:$A$201,MATCH(1,INDEX((TEAM_BUILDER!$G$6:$G$201=1)*(COUNTIF($B$1:B12,TEAM_BUILDER!$C$6:$C$201)=0),0),0)),"") -> MID | B13: =IFERROR(INDEX(TEAM_BUILDER!$C$6:$C$201,MATCH(ROWS($B$2:B13),TEAM_BUILDER!$I$6:$I$201,0)),"") -> Andrey Nascimento dos Santos | C13: =IFERROR(INDEX(TEAM_BUILDER!$D$6:$D$201,MATCH($B13,TEAM_BUILDER!$C$6:$C$201,0)),"") -> MUN | D13: =IFERROR(INDEX(TEAM_BUILDER!$E$6:$E$201,MATCH($B13,TEAM_BUILDER!$C$6:$C$201,0)),"") -> 4.9 | E13: =IFERROR(INDEX(TEAM_BUILDER!$H$6:$H$201,MATCH($B13,TEAM_BUILDER!$C$6:$C$201,0)),"") -> 7.0275502
A14: =IFERROR(INDEX(TEAM_BUILDER!$A$6:$A$201,MATCH(1,INDEX((TEAM_BUILDER!$G$6:$G$201=1)*(COUNTIF($B$1:B13,TEAM_BUILDER!$C$6:$C$201)=0),0),0)),"") -> FWD | B14: =IFERROR(INDEX(TEAM_BUILDER!$C$6:$C$201,MATCH(ROWS($B$2:B14),TEAM_BUILDER!$I$6:$I$201,0)),"") -> Erling Haaland | C14: =IFERROR(INDEX(TEAM_BUILDER!$D$6:$D$201,MATCH($B14,TEAM_BUILDER!$C$6:$C$201,0)),"") -> MCI | D14: =IFERROR(INDEX(TEAM_BUILDER!$E$6:$E$201,MATCH($B14,TEAM_BUILDER!$C$6:$C$201,0)),"") -> 15.5 | E14: =IFERROR(INDEX(TEAM_BUILDER!$H$6:$H$201,MATCH($B14,TEAM_BUILDER!$C$6:$C$201,0)),"") -> 7.7831264
A15: =IFERROR(INDEX(TEAM_BUILDER!$A$6:$A$201,MATCH(1,INDEX((TEAM_BUILDER!$G$6:$G$201=1)*(COUNTIF($B$1:B14,TEAM_BUILDER!$C$6:$C$201)=0),0),0)),"") -> FWD | B15: =IFERROR(INDEX(TEAM_BUILDER!$C$6:$C$201,MATCH(ROWS($B$2:B15),TEAM_BUILDER!$I$6:$I$201,0)),"") -> Igor Thiago Nascimento Rodrigues | C15: =IFERROR(INDEX(TEAM_BUILDER!$D$6:$D$201,MATCH($B15,TEAM_BUILDER!$C$6:$C$201,0)),"") -> BRE | D15: =IFERROR(INDEX(TEAM_BUILDER!$E$6:$E$201,MATCH($B15,TEAM_BUILDER!$C$6:$C$201,0)),"") -> 7.9 | E15: =IFERROR(INDEX(TEAM_BUILDER!$H$6:$H$201,MATCH($B15,TEAM_BUILDER!$C$6:$C$201,0)),"") -> 6.688367
A16: =IFERROR(INDEX(TEAM_BUILDER!$A$6:$A$201,MATCH(1,INDEX((TEAM_BUILDER!$G$6:$G$201=1)*(COUNTIF($B$1:B15,TEAM_BUILDER!$C$6:$C$201)=0),0),0)),"") -> FWD | B16: =IFERROR(INDEX(TEAM_BUILDER!$C$6:$C$201,MATCH(ROWS($B$2:B16),TEAM_BUILDER!$I$6:$I$201,0)),"") -> Thierno Barry | C16: =IFERROR(INDEX(TEAM_BUILDER!$D$6:$D$201,MATCH($B16,TEAM_BUILDER!$C$6:$C$201,0)),"") -> EVE | D16: =IFERROR(INDEX(TEAM_BUILDER!$E$6:$E$201,MATCH($B16,TEAM_BUILDER!$C$6:$C$201,0)),"") -> 5.6 | E16: =IFERROR(INDEX(TEAM_BUILDER!$H$6:$H$201,MATCH($B16,TEAM_BUILDER!$C$6:$C$201,0)),"") -> 6.2822815
D18: =SUM(D2:D16) -> 100

Sheet TEAM_BUILDER
A1: FPL TEAM BUILDER
N2: Club | O2: Players
A3: Budget | B3: 100 | N3: ARS | O3: =SUMPRODUCT((D9:D598=N3)*G9:G598) -> 3 | P3: =IF(O3>3,"TOO MANY","OK") -> OK
A4: Squad Cost | N4: AVL | O4: =SUMPRODUCT((D9:D598=N4)*G9:G598) -> 0 | P4: =IF(O4>3,"TOO MANY","OK") -> OK
A5: Remaining Budget | L5: Metric | M5: Value | N5: BHA | O5: =SUMPRODUCT((D9:D598=N5)*G9:G598) -> 0 | P5: =IF(O5>3,"TOO MANY","OK") -> OK
A6: Squad Players | L6: Squad Cost | M6: =SUMPRODUCT($E$9:$E$160,$G$9:$G$160) -> 100 | N6: BOU | O6: =SUMPRODUCT((D9:D598=N6)*G9:G598) -> 0 | P6: =IF(O6>3,"TOO MANY","OK") -> OK
L7: Expected Points | M7: =SUMPRODUCT($H$9:$H$160,$G$9:$G$160) -> 117.72668 | N7: BRE | O7: =SUMPRODUCT((D9:D598=N7)*G9:G598) -> 2 | P7: =IF(O7>3,"TOO MANY","OK") -> OK
A8: Position | B8: rank | C8: Player | D8: Team | E8: Price | F8: Model Score | G8: selected | H8: Expected Points | I8: Selection Order | J8: Eligible | L8: Remaining Budget | M8: =$B$3-$M$6 -> 0 | N8: COV | O8: =SUMPRODUCT((D9:D598=N8)*G9:G598) -> 0 | P8: =IF(O8>3,"TOO MANY","OK") -> OK
A9: GK | B9: 1 | C9: {=INDEX(Player_Analysis!$A$2:$A$700,MATCH(1,(Player_Analysis!$B$2:$B$700=A9)*(Player_Analysis!$BB$2:$BB$700=B9),0))} -> Konstantinos Tzolakis | D9: =INDEX(Player_Analysis!$D$2:$D$700,MATCH(C9,Player_Analysis!$A$2:$A$700,0)) -> HUL | E9: =INDEX(Player_Analysis!$E$2:$E$700,MATCH(C9,Player_Analysis!$A$2:$A$700,0)) -> 4.6 | F9: =INDEX(Player_Analysis!$BA$2:$BA$700,MATCH(C9,Player_Analysis!$A$2:$A$700,0)) -> 8.4 | G9: 1 | H9: =INDEX(Player_Analysis!$AT$2:$AT$700,MATCH(C9,Player_Analysis!$A$2:$A$700,0)) -> 8.4 | I9: =IF($G9=1,COUNTIF($G$9:G9,1),"") -> 1 | J9: =IFERROR(INDEX(Player_Analysis!$H$2:$H$596,MATCH($C9,Player_Analysis!$A$2:$A$596,0)),0) -> 1 | L9: Players | M9: =SUM($G$9:$G$160) -> 15 | N9: CHE | O9: =SUMPRODUCT((D9:D598=N9)*G9:G598) -> 0 | P9: =IF(O9>3,"TOO MANY","OK") -> OK
A10: GK | B10: 2 | C10: {=INDEX(Player_Analysis!$A$2:$A$700,MATCH(1,(Player_Analysis!$B$2:$B$700=A10)*(Player_Analysis!$BB$2:$BB$700=B10),0))} -> David Raya Martín | D10: =INDEX(Player_Analysis!$D$2:$D$700,MATCH(C10,Player_Analysis!$A$2:$A$700,0)) -> ARS | E10: =INDEX(Player_Analysis!$E$2:$E$700,MATCH(C10,Player_Analysis!$A$2:$A$700,0)) -> 6 | F10: =INDEX(Player_Analysis!$BA$2:$BA$700,MATCH(C10,Player_Analysis!$A$2:$A$700,0)) -> 6.1779862 | G10: 1 | H10: =INDEX(Player_Analysis!$AT$2:$AT$700,MATCH(C10,Player_Analysis!$A$2:$A$700,0)) -> 6.1779862 | I10: =IF(G10=1,COUNTIF($G$9:G10,1),"") -> 2 | J10: =IFERROR(INDEX(Player_Analysis!$H$2:$H$596,MATCH($C10,Player_Analysis!$A$2:$A$596,0)),0) -> 1 | L10: GK | M10: =SUMPRODUCT((A9:A598="GK")*G9:G598) -> 2 | N10: CRY | O10: =SUMPRODUCT((D9:D598=N10)*G9:G598) -> 0 | P10: =IF(O10>3,"TOO MANY","OK") -> OK
A11: GK | B11: 3 | C11: {=INDEX(Player_Analysis!$A$2:$A$700,MATCH(1,(Player_Analysis!$B$2:$B$700=A11)*(Player_Analysis!$BB$2:$BB$700=B11),0))} -> Lukás Hornícek | D11: =INDEX(Player_Analysis!$D$2:$D$700,MATCH(C11,Player_Analysis!$A$2:$A$700,0)) -> NEW | E11: =INDEX(Player_Analysis!$E$2:$E$700,MATCH(C11,Player_Analysis!$A$2:$A$700,0)) -> 5 | F11: =INDEX(Player_Analysis!$BA$2:$BA$700,MATCH(C11,Player_Analysis!$A$2:$A$700,0)) -> 5.6671727 | G11: 0 | H11: =INDEX(Player_Analysis!$AT$2:$AT$700,MATCH(C11,Player_Analysis!$A$2:$A$700,0)) -> 5.6671727 | I11: =IF(G11=1,COUNTIF($G$9:G11,1),"") | J11: =IFERROR(INDEX(Player_Analysis!$H$2:$H$596,MATCH($C11,Player_Analysis!$A$2:$A$596,0)),0) -> 1 | L11: DEF | M11: =SUMPRODUCT((A9:A605="DEF")*G9:G605) -> 5 | N11: EVE | O11: =SUMPRODUCT((D9:D598=N11)*G9:G598) -> 1 | P11: =IF(O11>3,"TOO MANY","OK") -> OK
A12: GK | B12: 4 | C12: {=INDEX(Player_Analysis!$A$2:$A$700,MATCH(1,(Player_Analysis!$B$2:$B$700=A12)*(Player_Analysis!$BB$2:$BB$700=B12),0))} -> James Trafford | D12: =INDEX(Player_Analysis!$D$2:$D$700,MATCH(C12,Player_Analysis!$A$2:$A$700,0)) -> LEE | E12: =INDEX(Player_Analysis!$E$2:$E$700,MATCH(C12,Player_Analysis!$A$2:$A$700,0)) -> 5 | F12: =INDEX(Player_Analysis!$BA$2:$BA$700,MATCH(C12,Player_Analysis!$A$2:$A$700,0)) -> 5.1845245 | G12: 0 | H12: =INDEX(Player_Analysis!$AT$2:$AT$700,MATCH(C12,Player_Analysis!$A$2:$A$700,0)) -> 5.1845245 | I12: =IF(G12=1,COUNTIF($G$9:G12,1),"") | J12: =IFERROR(INDEX(Player_Analysis!$H$2:$H$596,MATCH($C12,Player_Analysis!$A$2:$A$596,0)),0) -> 1 | L12: MID | M12: =SUMPRODUCT((A9:A605="MID")*G9:G605) -> 5 | N12: FUL | O12: =SUMPRODUCT((D9:D598=N12)*G9:G598) -> 0 | P12: =IF(O12>3,"TOO MANY","OK") -> OK
A13: GK | B13: 5 | C13: {=INDEX(Player_Analysis!$A$2:$A$700,MATCH(1,(Player_Analysis!$B$2:$B$700=A13)*(Player_Analysis!$BB$2:$BB$700=B13),0))} -> Zion Suzuki | D13: =INDEX(Player_Analysis!$D$2:$D$700,MATCH(C13,Player_Analysis!$A$2:$A$700,0)) -> AVL | E13: =INDEX(Player_Analysis!$E$2:$E$700,MATCH(C13,Player_Analysis!$A$2:$A$700,0)) -> 5 | F13: =INDEX(Player_Analysis!$BA$2:$BA$700,MATCH(C13,Player_Analysis!$A$2:$A$700,0)) -> 4.9729316 | G13: 0 | H13: =INDEX(Player_Analysis!$AT$2:$AT$700,MATCH(C13,Player_Analysis!$A$2:$A$700,0)) -> 4.9729316 | I13: =IF(G13=1,COUNTIF($G$9:G13,1),"") | J13: =IFERROR(INDEX(Player_Analysis!$H$2:$H$596,MATCH($C13,Player_Analysis!$A$2:$A$596,0)),0) -> 1 | L13: FWD | M13: =SUMPRODUCT((A9:A605="FWD")*G9:G605) -> 3 | N13: HUL | O13: =SUMPRODUCT((D9:D598=N13)*G9:G598) -> 3 | P13: =IF(O13>3,"TOO MANY","OK") -> OK
A14: GK | B14: 6 | C14: {=INDEX(Player_Analysis!$A$2:$A$700,MATCH(1,(Player_Analysis!$B$2:$B$700=A14)*(Player_Analysis!$BB$2:$BB$700=B14),0))} -> Jordan Pickford | D14: =INDEX(Player_Analysis!$D$2:$D$700,MATCH(C14,Player_Analysis!$A$2:$A$700,0)) -> EVE | E14: =INDEX(Player_Analysis!$E$2:$E$700,MATCH(C14,Player_Analysis!$A$2:$A$700,0)) -> 5.5 | F14: =INDEX(Player_Analysis!$BA$2:$BA$700,MATCH(C14,Player_Analysis!$A$2:$A$700,0)) -> 4.8725152 | G14: 0 | H14: =INDEX(Player_Analysis!$AT$2:$AT$700,MATCH(C14,Player_Analysis!$A$2:$A$700,0)) -> 4.8725152 | I14: =IF(G14=1,COUNTIF($G$9:G14,1),"") | J14: =IFERROR(INDEX(Player_Analysis!$H$2:$H$596,MATCH($C14,Player_Analysis!$A$2:$A$596,0)),0) -> 1 | N14: IPS | O14: =SUMPRODUCT((D9:D598=N14)*G9:G598) -> 0 | P14: =IF(O14>3,"TOO MANY","OK") -> OK
A15: GK | B15: 7 | C15: {=INDEX(Player_Analysis!$A$2:$A$700,MATCH(1,(Player_Analysis!$B$2:$B$700=A15)*(Player_Analysis!$BB$2:$BB$700=B15),0))} -> Gianluigi Donnarumma | D15: =INDEX(Player_Analysis!$D$2:$D$700,MATCH(C15,Player_Analysis!$A$2:$A$700,0)) -> MCI | E15: =INDEX(Player_Analysis!$E$2:$E$700,MATCH(C15,Player_Analysis!$A$2:$A$700,0)) -> 5.5 | F15: =INDEX(Player_Analysis!$BA$2:$BA$700,MATCH(C15,Player_Analysis!$A$2:$A$700,0)) -> 4.662592 | G15: 0 | H15: =INDEX(Player_Analysis!$AT$2:$AT$700,MATCH(C15,Player_Analysis!$A$2:$A$700,0)) -> 4.662592 | I15: =IF(G15=1,COUNTIF($G$9:G15,1),"") | J15: =IFERROR(INDEX(Player_Analysis!$H$2:$H$596,MATCH($C15,Player_Analysis!$A$2:$A$596,0)),0) -> 1 | L15: Eligibility check | M15: =SUMPRODUCT(($G$9:$G$160)*(1-$J$9:$J$160)) -> 0 | N15: LEE | O15: =SUMPRODUCT((D9:D598=N15)*G9:G598) -> 1 | P15: =IF(O15>3,"TOO MANY","OK") -> OK
A16: GK | B16: 8 | C16: {=INDEX(Player_Analysis!$A$2:$A$700,MATCH(1,(Player_Analysis!$B$2:$B$700=A16)*(Player_Analysis!$BB$2:$BB$700=B16),0))} -> Caoimhín Kelleher | D16: =INDEX(Player_Analysis!$D$2:$D$700,MATCH(C16,Player_Analysis!$A$2:$A$700,0)) -> BRE | E16: =INDEX(Player_Analysis!$E$2:$E$700,MATCH(C16,Player_Analysis!$A$2:$A$700,0)) -> 5 | F16: =INDEX(Player_Analysis!$BA$2:$BA$700,MATCH(C16,Player_Analysis!$A$2:$A$700,0)) -> 4.637499 | G16: 0 | H16: =INDEX(Player_Analysis!$AT$2:$AT$700,MATCH(C16,Player_Analysis!$A$2:$A$700,0)) -> 4.637499 | I16: =IF(G16=1,COUNTIF($G$9:G16,1),"") | J16: =IFERROR(INDEX(Player_Analysis!$H$2:$H$596,MATCH($C16,Player_Analysis!$A$2:$A$596,0)),0) -> 1 | N16: LIV | O16: =SUMPRODUCT((D9:D598=N16)*G9:G598) -> 0 | P16: =IF(O16>3,"TOO MANY","OK") -> OK
A17: GK | B17: 9 | C17: {=INDEX(Player_Analysis!$A$2:$A$700,MATCH(1,(Player_Analysis!$B$2:$B$700=A17)*(Player_Analysis!$BB$2:$BB$700=B17),0))} -> Matz Sels | D17: =INDEX(Player_Analysis!$D$2:$D$700,MATCH(C17,Player_Analysis!$A$2:$A$700,0)) -> NFO | E17: =INDEX(Player_Analysis!$E$2:$E$700,MATCH(C17,Player_Analysis!$A$2:$A$700,0)) -> 5 | F17: =INDEX(Player_Analysis!$BA$2:$BA$700,MATCH(C17,Player_Analysis!$A$2:$A$700,0)) -> 4.4162305 | G17: 0 | H17: =INDEX(Player_Analysis!$AT$2:$AT$700,MATCH(C17,Player_Analysis!$A$2:$A$700,0)) -> 4.4162305 | I17: =IF(G17=1,COUNTIF($G$9:G17,1),"") | J17: =IFERROR(INDEX(Player_Analysis!$H$2:$H$596,MATCH($C17,Player_Analysis!$A$2:$A$596,0)),0) -> 1 | L17: Squad Valid | M17: =IF(AND(M9=15,M10=2,M11=5,M12=5,M13=3,M6<=B3,M15=0,MAX(O3:O23)<=3),"YES","NO") -> YES | N17: MCI | O17: =SUMPRODUCT((D9:D598=N17)*G9:G598) -> 3 | P17: =IF(O17>3,"TOO MANY","OK") -> OK
A18: GK | B18: 10 | C18: {=INDEX(Player_Analysis!$A$2:$A$700,MATCH(1,(Player_Analysis!$B$2:$B$700=A18)*(Player_Analysis!$BB$2:$BB$700=B18),0))} -> Alisson Becker | D18: =INDEX(Player_Analysis!$D$2:$D$700,MATCH(C18,Player_Analysis!$A$2:$A$700,0)) -> LIV | E18: =INDEX(Player_Analysis!$E$2:$E$700,MATCH(C18,Player_Analysis!$A$2:$A$700,0)) -> 5.5 | F18: =INDEX(Player_Analysis!$BA$2:$BA$700,MATCH(C18,Player_Analysis!$A$2:$A$700,0)) -> 4.1856979 | G18: 0 | H18: =INDEX(Player_Analysis!$AT$2:$AT$700,MATCH(C18,Player_Analysis!$A$2:$A$700,0)) -> 4.1856979 | I18: =IF(G18=1,COUNTIF($G$9:G18,1),"") | J18: =IFERROR(INDEX(Player_Analysis!$H$2:$H$596,MATCH($C18,Player_Analysis!$A$2:$A$596,0)),0) -> 1 | N18: MUN | O18: =SUMPRODUCT((D9:D598=N18)*G9:G598) -> 2 | P18: =IF(O18>3,"TOO MANY","OK") -> OK
A19: GK | B19: 11 | C19: {=INDEX(Player_Analysis!$A$2:$A$700,MATCH(1,(Player_Analysis!$B$2:$B$700=A19)*(Player_Analysis!$BB$2:$BB$700=B19),0))} -> Bart Verbruggen | D19: =INDEX(Player_Analysis!$D$2:$D$700,MATCH(C19,Player_Analysis!$A$2:$A$700,0)) -> BHA | E19: =INDEX(Player_Analysis!$E$2:$E$700,MATCH(C19,Player_Analysis!$A$2:$A$700,0)) -> 4.5 | F19: =INDEX(Player_Analysis!$BA$2:$BA$700,MATCH(C19,Player_Analysis!$A$2:$A$700,0)) -> 3.9480867 | G19: 0 | H19: =INDEX(Player_Analysis!$AT$2:$AT$700,MATCH(C19,Player_Analysis!$A$2:$A$700,0)) -> 3.9480867 | I19: =IF(G19=1,COUNTIF($G$9:G19,1),"") | J19: =IFERROR(INDEX(Player_Analysis!$H$2:$H$596,MATCH($C19,Player_Analysis!$A$2:$A$596,0)),0) -> 1 | N19: NEW | O19: =SUMPRODUCT((D9:D598=N19)*G9:G598) -> 0 | P19: =IF(O19>3,"TOO MANY","OK") -> OK
A20: GK | B20: 12 | C20: {=INDEX(Player_Analysis!$A$2:$A$700,MATCH(1,(Player_Analysis!$B$2:$B$700=A20)*(Player_Analysis!$BB$2:$BB$700=B20),0))} -> Antonín Kinský | D20: =INDEX(Player_Analysis!$D$2:$D$700,MATCH(C20,Player_Analysis!$A$2:$A$700,0)) -> TOT | E20: =INDEX(Player_Analysis!$E$2:$E$700,MATCH(C20,Player_Analysis!$A$2:$A$700,0)) -> 4.5 | F20: =INDEX(Player_Analysis!$BA$2:$BA$700,MATCH(C20,Player_Analysis!$A$2:$A$700,0)) -> 3.8932944 | G20: 0 | H20: =INDEX(Player_Analysis!$AT$2:$AT$700,MATCH(C20,Player_Analysis!$A$2:$A$700,0)) -> 3.8932944 | I20: =IF(G20=1,COUNTIF($G$9:G20,1),"") | J20: =IFERROR(INDEX(Player_Analysis!$H$2:$H$596,MATCH($C20,Player_Analysis!$A$2:$A$596,0)),0) -> 1 | N20: NFO | O20: =SUMPRODUCT((D9:D598=N20)*G9:G598) -> 0 | P20: =IF(O20>3,"TOO MANY","OK") -> OK
A21: GK | B21: 13 | C21: {=INDEX(Player_Analysis!$A$2:$A$700,MATCH(1,(Player_Analysis!$B$2:$B$700=A21)*(Player_Analysis!$BB$2:$BB$700=B21),0))} -> Emiliano Martínez Romero | D21: =INDEX(Player_Analysis!$D$2:$D$700,MATCH(C21,Player_Analysis!$A$2:$A$700,0)) -> CHE | E21: =INDEX(Player_Analysis!$E$2:$E$700,MATCH(C21,Player_Analysis!$A$2:$A$700,0)) -> 5 | F21: =INDEX(Player_Analysis!$BA$2:$BA$700,MATCH(C21,Player_Analysis!$A$2:$A$700,0)) -> 3.4723371 | G21: 0 | H21: =INDEX(Player_Analysis!$AT$2:$AT$700,MATCH(C21,Player_Analysis!$A$2:$A$700,0)) -> 3.4723371 | I21: =IF(G21=1,COUNTIF($G$9:G21,1),"") | J21: =IFERROR(INDEX(Player_Analysis!$H$2:$H$596,MATCH($C21,Player_Analysis!$A$2:$A$596,0)),0) -> 1 | N21: SUN | O21: =SUMPRODUCT((D9:D598=N21)*G9:G598) -> 0 | P21: =IF(O21>3,"TOO MANY","OK") -> OK
A22: GK | B22: 14 | C22: {=INDEX(Player_Analysis!$A$2:$A$700,MATCH(1,(Player_Analysis!$B$2:$B$700=A22)*(Player_Analysis!$BB$2:$BB$700=B22),0))} -> Marco Bizot | D22: =INDEX(Player_Analysis!$D$2:$D$700,MATCH(C22,Player_Analysis!$A$2:$A$700,0)) -> AVL | E22: =INDEX(Player_Analysis!$E$2:$E$700,MATCH(C22,Player_Analysis!$A$2:$A$700,0)) -> 4.5 | F22: =INDEX(Player_Analysis!$BA$2:$BA$700,MATCH(C22,Player_Analysis!$A$2:$A$700,0)) -> 3.0866472 | G22: 0 | H22: =INDEX(Player_Analysis!$AT$2:$AT$700,MATCH(C22,Player_Analysis!$A$2:$A$700,0)) -> 3.0866472 | I22: =IF(G22=1,COUNTIF($G$9:G22,1),"") | J22: =IFERROR(INDEX(Player_Analysis!$H$2:$H$596,MATCH($C22,Player_Analysis!$A$2:$A$596,0)),0) -> 1 | N22: TOT | O22: =SUMPRODUCT((D9:D598=N22)*G9:G598) -> 0 | P22: =IF(O22>3,"TOO MANY","OK") -> OK
A23: GK | B23: 15 | C23: {=INDEX(Player_Analysis!$A$2:$A$700,MATCH(1,(Player_Analysis!$B$2:$B$700=A23)*(Player_Analysis!$BB$2:$BB$700=B23),0))} -> Robert Lynch Sánchez | D23: =INDEX(Player_Analysis!$D$2:$D$700,MATCH(C23,Player_Analysis!$A$2:$A$700,0)) -> CHE | E23: =INDEX(Player_Analysis!$E$2:$E$700,MATCH(C23,Player_Analysis!$A$2:$A$700,0)) -> 4.9 | F23: =INDEX(Player_Analysis!$BA$2:$BA$700,MATCH(C23,Player_Analysis!$A$2:$A$700,0)) -> 2.8957685 | G23: 0 | H23: =INDEX(Player_Analysis!$AT$2:$AT$700,MATCH(C23,Player_Analysis!$A$2:$A$700,0)) -> 2.8957685 | I23: =IF(G23=1,COUNTIF($G$9:G23,1),"") | J23: =IFERROR(INDEX(Player_Analysis!$H$2:$H$596,MATCH($C23,Player_Analysis!$A$2:$A$596,0)),0) -> 0
A24: GK | B24: 16 | C24: {=INDEX(Player_Analysis!$A$2:$A$700,MATCH(1,(Player_Analysis!$B$2:$B$700=A24)*(Player_Analysis!$BB$2:$BB$700=B24),0))} -> Kjell Scherpen | D24: =INDEX(Player_Analysis!$D$2:$D$700,MATCH(C24,Player_Analysis!$A$2:$A$700,0)) -> IPS | E24: =INDEX(Player_Analysis!$E$2:$E$700,MATCH(C24,Player_Analysis!$A$2:$A$700,0)) -> 4.5 | F24: =INDEX(Player_Analysis!$BA$2:$BA$700,MATCH(C24,Player_Analysis!$A$2:$A$700,0)) -> 2.8123724 | G24: 0 | H24: =INDEX(Player_Analysis!$AT$2:$AT$700,MATCH(C24,Player_Analysis!$A$2:$A$700,0)) -> 2.8123724 | I24: =IF(G24=1,COUNTIF($G$9:G24,1),"") | J24: =IFERROR(INDEX(Player_Analysis!$H$2:$H$596,MATCH($C24,Player_Analysis!$A$2:$A$596,0)),0) -> 1
A25: GK | B25: 17 | C25: {=INDEX(Player_Analysis!$A$2:$A$700,MATCH(1,(Player_Analysis!$B$2:$B$700=A25)*(Player_Analysis!$BB$2:$BB$700=B25),0))} -> Senne Lammens | D25: =INDEX(Player_Analysis!$D$2:$D$700,MATCH(C25,Player_Analysis!$A$2:$A$700,0)) -> MUN | E25: =INDEX(Player_Analysis!$E$2:$E$700,MATCH(C25,Player_Analysis!$A$2:$A$700,0)) -> 5 | F25: =INDEX(Player_Analysis!$BA$2:$BA$700,MATCH(C25,Player_Analysis!$A$2:$A$700,0)) -> 2.774628 | G25: 0 | H25: =INDEX(Player_Analysis!$AT$2:$AT$700,MATCH(C25,Player_Analysis!$A$2:$A$700,0)) -> 2.774628 | I25: =IF(G25=1,COUNTIF($G$9:G25,1),"") | J25: =IFERROR(INDEX(Player_Analysis!$H$2:$H$596,MATCH($C25,Player_Analysis!$A$2:$A$596,0)),0) -> 1
A26: GK | B26: 18 | C26: {=INDEX(Player_Analysis!$A$2:$A$700,MATCH(1,(Player_Analysis!$B$2:$B$700=A26)*(Player_Analysis!$BB$2:$BB$700=B26),0))} -> Dean Henderson | D26: =INDEX(Player_Analysis!$D$2:$D$700,MATCH(C26,Player_Analysis!$A$2:$A$700,0)) -> CRY | E26: =INDEX(Player_Analysis!$E$2:$E$700,MATCH(C26,Player_Analysis!$A$2:$A$700,0)) -> 5 | F26: =INDEX(Player_Analysis!$BA$2:$BA$700,MATCH(C26,Player_Analysis!$A$2:$A$700,0)) -> 2.7741732 | G26: 0 | H26: =INDEX(Player_Analysis!$AT$2:$AT$700,MATCH(C26,Player_Analysis!$A$2:$A$700,0)) -> 2.7741732 | J26: =IFERROR(INDEX(Player_Analysis!$H$2:$H$596,MATCH($C26,Player_Analysis!$A$2:$A$596,0)),0) -> 1
A27: GK | B27: 19 | C27: {=INDEX(Player_Analysis!$A$2:$A$700,MATCH(1,(Player_Analysis!$B$2:$B$700=A27)*(Player_Analysis!$BB$2:$BB$700=B27),0))} -> Đorđe Petrović | D27: =INDEX(Player_Analysis!$D$2:$D$700,MATCH(C27,Player_Analysis!$A$2:$A$700,0)) -> BOU | E27: =INDEX(Player_Analysis!$E$2:$E$700,MATCH(C27,Player_Analysis!$A$2:$A$700,0)) -> 4.5 | F27: =INDEX(Player_Analysis!$BA$2:$BA$700,MATCH(C27,Player_Analysis!$A$2:$A$700,0)) -> 2.5647797 | G27: 0 | H27: =INDEX(Player_Analysis!$AT$2:$AT$700,MATCH(C27,Player_Analysis!$A$2:$A$700,0)) -> 2.5647797 | J27: =IFERROR(INDEX(Player_Analysis!$H$2:$H$596,MATCH($C27,Player_Analysis!$A$2:$A$596,0)),0) -> 1
A28: GK | B28: 20 | C28: {=INDEX(Player_Analysis!$A$2:$A$700,MATCH(1,(Player_Analysis!$B$2:$B$700=A28)*(Player_Analysis!$BB$2:$BB$700=B28),0))} -> Carl Rushworth | D28: =INDEX(Player_Analysis!$D$2:$D$700,MATCH(C28,Player_Analysis!$A$2:$A$700,0)) -> COV | E28: =INDEX(Player_Analysis!$E$2:$E$700,MATCH(C28,Player_Analysis!$A$2:$A$700,0)) -> 4.5 | F28: =INDEX(Player_Analysis!$BA$2:$BA$700,MATCH(C28,Player_Analysis!$A$2:$A$700,0)) -> 2.499612 | G28: 0 | H28: =INDEX(Player_Analysis!$AT$2:$AT$700,MATCH(C28,Player_Analysis!$A$2:$A$700,0)) -> 2.499612 | J28: =IFERROR(INDEX(Player_Analysis!$H$2:$H$596,MATCH($C28,Player_Analysis!$A$2:$A$596,0)),0) -> 1
A29: GK | B29: 21 | C29: {=INDEX(Player_Analysis!$A$2:$A$700,MATCH(1,(Player_Analysis!$B$2:$B$700=A29)*(Player_Analysis!$BB$2:$BB$700=B29),0))} -> Bernd Leno | D29: =INDEX(Player_Analysis!$D$2:$D$700,MATCH(C29,Player_Analysis!$A$2:$A$700,0)) -> FUL | E29: =INDEX(Player_Analysis!$E$2:$E$700,MATCH(C29,Player_Analysis!$A$2:$A$700,0)) -> 4.5 | F29: =INDEX(Player_Analysis!$BA$2:$BA$700,MATCH(C29,Player_Analysis!$A$2:$A$700,0)) -> 2.4639849 | G29: 0 | H29: =INDEX(Player_Analysis!$AT$2:$AT$700,MATCH(C29,Player_Analysis!$A$2:$A$700,0)) -> 2.4639849 | J29: =IFERROR(INDEX(Player_Analysis!$H$2:$H$596,MATCH($C29,Player_Analysis!$A$2:$A$596,0)),0) -> 1
A30: GK | B30: 22 | C30: {=INDEX(Player_Analysis!$A$2:$A$700,MATCH(1,(Player_Analysis!$B$2:$B$700=A30)*(Player_Analysis!$BB$2:$BB$700=B30),0))} -> Kepa Arrizabalaga Revuelta | D30: =INDEX(Player_Analysis!$D$2:$D$700,MATCH(C30,Player_Analysis!$A$2:$A$700,0)) -> ARS | E30: =INDEX(Player_Analysis!$E$2:$E$700,MATCH(C30,Player_Analysis!$A$2:$A$700,0)) -> 4.9 | F30: =INDEX(Player_Analysis!$BA$2:$BA$700,MATCH(C30,Player_Analysis!$A$2:$A$700,0)) -> 0 | G30: 0 | H30: =INDEX(Player_Analysis!$AT$2:$AT$700,MATCH(C30,Player_Analysis!$A$2:$A$700,0)) -> 0 | J30: =IFERROR(INDEX(Player_Analysis!$H$2:$H$596,MATCH($C30,Player_Analysis!$A$2:$A$596,0)),0) -> 1
A31: GK | B31: 23 | C31: {=INDEX(Player_Analysis!$A$2:$A$700,MATCH(1,(Player_Analysis!$B$2:$B$700=A31)*(Player_Analysis!$BB$2:$BB$700=B31),0))} -> Illan Meslier | D31: =INDEX(Player_Analysis!$D$2:$D$700,MATCH(C31,Player_Analysis!$A$2:$A$700,0)) -> ARS | E31: =INDEX(Player_Analysis!$E$2:$E$700,MATCH(C31,Player_Analysis!$A$2:$A$700,0)) -> 4.9 | F31: =INDEX(Player_Analysis!$BA$2:$BA$700,MATCH(C31,Player_Analysis!$A$2:$A$700,0)) -> 0 | G31: 0 | H31: =INDEX(Player_Analysis!$AT$2:$AT$700,MATCH(C31,Player_Analysis!$A$2:$A$700,0)) -> 0 | J31: =IFERROR(INDEX(Player_Analysis!$H$2:$H$596,MATCH($C31,Player_Analysis!$A$2:$A$596,0)),0) -> 1
A32: GK | B32: 24 | C32: {=INDEX(Player_Analysis!$A$2:$A$700,MATCH(1,(Player_Analysis!$B$2:$B$700=A32)*(Player_Analysis!$BB$2:$BB$700=B32),0))} -> Fraser Forster | D32: =INDEX(Player_Analysis!$D$2:$D$700,MATCH(C32,Player_Analysis!$A$2:$A$700,0)) -> BOU | E32: =INDEX(Player_Analysis!$E$2:$E$700,MATCH(C32,Player_Analysis!$A$2:$A$700,0)) -> 4 | F32: =INDEX(Player_Analysis!$BA$2:$BA$700,MATCH(C32,Player_Analysis!$A$2:$A$700,0)) -> 0 | G32: 0 | H32: =INDEX(Player_Analysis!$AT$2:$AT$700,MATCH(C32,Player_Analysis!$A$2:$A$700,0)) -> 0 | J32: =IFERROR(INDEX(Player_Analysis!$H$2:$H$596,MATCH($C32,Player_Analysis!$A$2:$A$596,0)),0) -> 1
A33: GK | B33: 25 | C33: {=INDEX(Player_Analysis!$A$2:$A$700,MATCH(1,(Player_Analysis!$B$2:$B$700=A33)*(Player_Analysis!$BB$2:$BB$700=B33),0))} -> Will Dennis | D33: =INDEX(Player_Analysis!$D$2:$D$700,MATCH(C33,Player_Analysis!$A$2:$A$700,0)) -> BOU | E33: =INDEX(Player_Analysis!$E$2:$E$700,MATCH(C33,Player_Analysis!$A$2:$A$700,0)) -> 4 | F33: =INDEX(Player_Analysis!$BA$2:$BA$700,MATCH(C33,Player_Analysis!$A$2:$A$700,0)) -> 0 | G33: 0 | H33: =INDEX(Player_Analysis!$AT$2:$AT$700,MATCH(C33,Player_Analysis!$A$2:$A$700,0)) -> 0 | J33: =IFERROR(INDEX(Player_Analysis!$H$2:$H$596,MATCH($C33,Player_Analysis!$A$2:$A$596,0)),0) -> 0
A34: GK | B34: 26 | C34: {=INDEX(Player_Analysis!$A$2:$A$700,MATCH(1,(Player_Analysis!$B$2:$B$700=A34)*(Player_Analysis!$BB$2:$BB$700=B34),0))} -> Michele Di Gregorio | D34: =INDEX(Player_Analysis!$D$2:$D$700,MATCH(C34,Player_Analysis!$A$2:$A$700,0)) -> BOU | E34: =INDEX(Player_Analysis!$E$2:$E$700,MATCH(C34,Player_Analysis!$A$2:$A$700,0)) -> 4.5 | F34: =INDEX(Player_Analysis!$BA$2:$BA$700,MATCH(C34,Player_Analysis!$A$2:$A$700,0)) -> 0 | G34: 0 | H34: =INDEX(Player_Analysis!$AT$2:$AT$700,MATCH(C34,Player_Analysis!$A$2:$A$700,0)) -> 0 | J34: =IFERROR(INDEX(Player_Analysis!$H$2:$H$596,MATCH($C34,Player_Analysis!$A$2:$A$596,0)),0) -> 1
A35: GK | B35: 27 | C35: {=INDEX(Player_Analysis!$A$2:$A$700,MATCH(1,(Player_Analysis!$B$2:$B$700=A35)*(Player_Analysis!$BB$2:$BB$700=B35),0))} -> Hákon Rafn Valdimarsson | D35: =INDEX(Player_Analysis!$D$2:$D$700,MATCH(C35,Player_Analysis!$A$2:$A$700,0)) -> BRE | E35: =INDEX(Player_Analysis!$E$2:$E$700,MATCH(C35,Player_Analysis!$A$2:$A$700,0)) -> 4.5 | F35: =INDEX(Player_Analysis!$BA$2:$BA$700,MATCH(C35,Player_Analysis!$A$2:$A$700,0)) -> 0 | G35: 0 | H35: =INDEX(Player_Analysis!$AT$2:$AT$700,MATCH(C35,Player_Analysis!$A$2:$A$700,0)) -> 0 | J35: =IFERROR(INDEX(Player_Analysis!$H$2:$H$596,MATCH($C35,Player_Analysis!$A$2:$A$596,0)),0) -> 1
A36: GK | B36: 28 | C36: {=INDEX(Player_Analysis!$A$2:$A$700,MATCH(1,(Player_Analysis!$B$2:$B$700=A36)*(Player_Analysis!$BB$2:$BB$700=B36),0))} -> Jason Steele | D36: =INDEX(Player_Analysis!$D$2:$D$700,MATCH(C36,Player_Analysis!$A$2:$A$700,0)) -> BHA | E36: =INDEX(Player_Analysis!$E$2:$E$700,MATCH(C36,Player_Analysis!$A$2:$A$700,0)) -> 4 | F36: =INDEX(Player_Analysis!$BA$2:$BA$700,MATCH(C36,Player_Analysis!$A$2:$A$700,0)) -> 0 | G36: 0 | H36: =INDEX(Player_Analysis!$AT$2:$AT$700,MATCH(C36,Player_Analysis!$A$2:$A$700,0)) -> 0 | J36: =IFERROR(INDEX(Player_Analysis!$H$2:$H$596,MATCH($C36,Player_Analysis!$A$2:$A$596,0)),0) -> 1
A37: GK | B37: 29 | C37: {=INDEX(Player_Analysis!$A$2:$A$700,MATCH(1,(Player_Analysis!$B$2:$B$700=A37)*(Player_Analysis!$BB$2:$BB$700=B37),0))} -> Filip Jörgensen | D37: =INDEX(Player_Analysis!$D$2:$D$700,MATCH(C37,Player_Analysis!$A$2:$A$700,0)) -> CHE | E37: =INDEX(Player_Analysis!$E$2:$E$700,MATCH(C37,Player_Analysis!$A$2:$A$700,0)) -> 5 | F37: =INDEX(Player_Analysis!$BA$2:$BA$700,MATCH(C37,Player_Analysis!$A$2:$A$700,0)) -> 0 | G37: 0 | H37: =INDEX(Player_Analysis!$AT$2:$AT$700,MATCH(C37,Player_Analysis!$A$2:$A$700,0)) -> 0 | J37: =IFERROR(INDEX(Player_Analysis!$H$2:$H$596,MATCH($C37,Player_Analysis!$A$2:$A$596,0)),0) -> 0
A38: GK | B38: 30 | C38: {=INDEX(Player_Analysis!$A$2:$A$700,MATCH(1,(Player_Analysis!$B$2:$B$700=A38)*(Player_Analysis!$BB$2:$BB$700=B38),0))} -> Mike Penders | D38: =INDEX(Player_Analysis!$D$2:$D$700,MATCH(C38,Player_Analysis!$A$2:$A$700,0)) -> CHE | E38: =INDEX(Player_Analysis!$E$2:$E$700,MATCH(C38,Player_Analysis!$A$2:$A$700,0)) -> 4.5 | F38: =INDEX(Player_Analysis!$BA$2:$BA$700,MATCH(C38,Player_Analysis!$A$2:$A$700,0)) -> 0 | G38: 0 | H38: =INDEX(Player_Analysis!$AT$2:$AT$700,MATCH(C38,Player_Analysis!$A$2:$A$700,0)) -> 0 | J38: =IFERROR(INDEX(Player_Analysis!$H$2:$H$596,MATCH($C38,Player_Analysis!$A$2:$A$596,0)),0) -> 1
A39: DEF | B39: 1 | C39: {=INDEX(Player_Analysis!$A$2:$A$700,MATCH(1,(Player_Analysis!$B$2:$B$700=A39)*(Player_Analysis!$BB$2:$BB$700=B39),0))} -> John Egan | D39: =INDEX(Player_Analysis!$D$2:$D$700,MATCH(C39,Player_Analysis!$A$2:$A$700,0)) -> HUL | E39: =INDEX(Player_Analysis!$E$2:$E$700,MATCH(C39,Player_Analysis!$A$2:$A$700,0)) -> 4.1 | F39: =INDEX(Player_Analysis!$BA$2:$BA$700,MATCH(C39,Player_Analysis!$A$2:$A$700,0)) -> 10.502855 | G39: 1 | H39: =INDEX(Player_Analysis!$AT$2:$AT$700,MATCH(C39,Player_Analysis!$A$2:$A$700,0)) -> 10.502855 | I39: =IF(G39=1,COUNTIF($G$9:G39,1),"") -> 3 | J39: =IFERROR(INDEX(Player_Analysis!$H$2:$H$596,MATCH($C39,Player_Analysis!$A$2:$A$596,0)),0) -> 1
A40: DEF | B40: 2 | C40: {=INDEX(Player_Analysis!$A$2:$A$700,MATCH(1,(Player_Analysis!$B$2:$B$700=A40)*(Player_Analysis!$BB$2:$BB$700=B40),0))} -> Semi Ajayi | D40: =INDEX(Player_Analysis!$D$2:$D$700,MATCH(C40,Player_Analysis!$A$2:$A$700,0)) -> HUL | E40: =INDEX(Player_Analysis!$E$2:$E$700,MATCH(C40,Player_Analysis!$A$2:$A$700,0)) -> 4.1 | F40: =INDEX(Player_Analysis!$BA$2:$BA$700,MATCH(C40,Player_Analysis!$A$2:$A$700,0)) -> 10.364444 | G40: 1 | H40: =INDEX(Player_Analysis!$AT$2:$AT$700,MATCH(C40,Player_Analysis!$A$2:$A$700,0)) -> 10.364444 | I40: =IF(G40=1,COUNTIF($G$9:G40,1),"") -> 4 | J40: =IFERROR(INDEX(Player_Analysis!$H$2:$H$596,MATCH($C40,Player_Analysis!$A$2:$A$596,0)),0) -> 1
A41: DEF | B41: 3 | C41: {=INDEX(Player_Analysis!$A$2:$A$700,MATCH(1,(Player_Analysis!$B$2:$B$700=A41)*(Player_Analysis!$BB$2:$BB$700=B41),0))} -> Nobel Mendy | D41: =INDEX(Player_Analysis!$D$2:$D$700,MATCH(C41,Player_Analysis!$A$2:$A$700,0)) -> HUL | E41: =INDEX(Player_Analysis!$E$2:$E$700,MATCH(C41,Player_Analysis!$A$2:$A$700,0)) -> 4 | F41: =INDEX(Player_Analysis!$BA$2:$BA$700,MATCH(C41,Player_Analysis!$A$2:$A$700,0)) -> 10.304503 | G41: 0 | H41: =INDEX(Player_Analysis!$AT$2:$AT$700,MATCH(C41,Player_Analysis!$A$2:$A$700,0)) -> 10.304503 | I41: =IF(G41=1,COUNTIF($G$9:G41,1),"") | J41: =IFERROR(INDEX(Player_Analysis!$H$2:$H$596,MATCH($C41,Player_Analysis!$A$2:$A$596,0)),0) -> 1
A42: DEF | B42: 4 | C42: {=INDEX(Player_Analysis!$A$2:$A$700,MATCH(1,(Player_Analysis!$B$2:$B$700=A42)*(Player_Analysis!$BB$2:$BB$700=B42),0))} -> Ryan Giles | D42: =INDEX(Player_Analysis!$D$2:$D$700,MATCH(C42,Player_Analysis!$A$2:$A$700,0)) -> HUL | E42: =INDEX(Player_Analysis!$E$2:$E$700,MATCH(C42,Player_Analysis!$A$2:$A$700,0)) -> 4 | F42: =INDEX(Player_Analysis!$BA$2:$BA$700,MATCH(C42,Player_Analysis!$A$2:$A$700,0)) -> 8.481876 | G42: 0 | H42: =INDEX(Player_Analysis!$AT$2:$AT$700,MATCH(C42,Player_Analysis!$A$2:$A$700,0)) -> 8.481876 | I42: =IF(G42=1,COUNTIF($G$9:G42,1),"") | J42: =IFERROR(INDEX(Player_Analysis!$H$2:$H$596,MATCH($C42,Player_Analysis!$A$2:$A$596,0)),0) -> 1
A43: DEF | B43: 5 | C43: {=INDEX(Player_Analysis!$A$2:$A$700,MATCH(1,(Player_Analysis!$B$2:$B$700=A43)*(Player_Analysis!$BB$2:$BB$700=B43),0))} -> Cristhian Mosquera | D43: =INDEX(Player_Analysis!$D$2:$D$700,MATCH(C43,Player_Analysis!$A$2:$A$700,0)) -> ARS | E43: =INDEX(Player_Analysis!$E$2:$E$700,MATCH(C43,Player_Analysis!$A$2:$A$700,0)) -> 5.4 | F43: =INDEX(Player_Analysis!$BA$2:$BA$700,MATCH(C43,Player_Analysis!$A$2:$A$700,0)) -> 8.282242 | G43: 0 | H43: =INDEX(Player_Analysis!$AT$2:$AT$700,MATCH(C43,Player_Analysis!$A$2:$A$700,0)) -> 8.282242 | I43: =IF(G43=1,COUNTIF($G$9:G43,1),"") | J43: =IFERROR(INDEX(Player_Analysis!$H$2:$H$596,MATCH($C43,Player_Analysis!$A$2:$A$596,0)),0) -> 0
A44: DEF | B44: 6 | C44: {=INDEX(Player_Analysis!$A$2:$A$700,MATCH(1,(Player_Analysis!$B$2:$B$700=A44)*(Player_Analysis!$BB$2:$BB$700=B44),0))} -> Gabriel dos Santos Magalhães | D44: =INDEX(Player_Analysis!$D$2:$D$700,MATCH(C44,Player_Analysis!$A$2:$A$700,0)) -> ARS | E44: =INDEX(Player_Analysis!$E$2:$E$700,MATCH(C44,Player_Analysis!$A$2:$A$700,0)) -> 8 | F44: =INDEX(Player_Analysis!$BA$2:$BA$700,MATCH(C44,Player_Analysis!$A$2:$A$700,0)) -> 8.1528293 | G44: 1 | H44: =INDEX(Player_Analysis!$AT$2:$AT$700,MATCH(C44,Player_Analysis!$A$2:$A$700,0)) -> 8.1528293 | I44: =IF(G44=1,COUNTIF($G$9:G44,1),"") -> 5 | J44: =IFERROR(INDEX(Player_Analysis!$H$2:$H$596,MATCH($C44,Player_Analysis!$A$2:$A$596,0)),0) -> 1
A45: DEF | B45: 7 | C45: {=INDEX(Player_Analysis!$A$2:$A$700,MATCH(1,(Player_Analysis!$B$2:$B$700=A45)*(Player_Analysis!$BB$2:$BB$700=B45),0))} -> Jayden Bogle | D45: =INDEX(Player_Analysis!$D$2:$D$700,MATCH(C45,Player_Analysis!$A$2:$A$700,0)) -> LEE | E45: =INDEX(Player_Analysis!$E$2:$E$700,MATCH(C45,Player_Analysis!$A$2:$A$700,0)) -> 4.5 | F45: =INDEX(Player_Analysis!$BA$2:$BA$700,MATCH(C45,Player_Analysis!$A$2:$A$700,0)) -> 8.1476383 | G45: 1 | H45: =INDEX(Player_Analysis!$AT$2:$AT$700,MATCH(C45,Player_Analysis!$A$2:$A$700,0)) -> 8.1476383 | I45: =IF(G45=1,COUNTIF($G$9:G45,1),"") -> 6 | J45: =IFERROR(INDEX(Player_Analysis!$H$2:$H$596,MATCH($C45,Player_Analysis!$A$2:$A$596,0)),0) -> 1
A46: DEF | B46: 8 | C46: {=INDEX(Player_Analysis!$A$2:$A$700,MATCH(1,(Player_Analysis!$B$2:$B$700=A46)*(Player_Analysis!$BB$2:$BB$700=B46),0))} -> Riccardo Calafiori | D46: =INDEX(Player_Analysis!$D$2:$D$700,MATCH(C46,Player_Analysis!$A$2:$A$700,0)) -> ARS | E46: =INDEX(Player_Analysis!$E$2:$E$700,MATCH(C46,Player_Analysis!$A$2:$A$700,0)) -> 5.7 | F46: =INDEX(Player_Analysis!$BA$2:$BA$700,MATCH(C46,Player_Analysis!$A$2:$A$700,0)) -> 8.1388646 | G46: 1 | H46: =INDEX(Player_Analysis!$AT$2:$AT$700,MATCH(C46,Player_Analysis!$A$2:$A$700,0)) -> 8.1388646 | I46: =IF(G46=1,COUNTIF($G$9:G46,1),"") -> 7 | J46: =IFERROR(INDEX(Player_Analysis!$H$2:$H$596,MATCH($C46,Player_Analysis!$A$2:$A$596,0)),0) -> 1
A47: DEF | B47: 9 | C47: {=INDEX(Player_Analysis!$A$2:$A$700,MATCH(1,(Player_Analysis!$B$2:$B$700=A47)*(Player_Analysis!$BB$2:$BB$700=B47),0))} -> Benjamin White | D47: =INDEX(Player_Analysis!$D$2:$D$700,MATCH(C47,Player_Analysis!$A$2:$A$700,0)) -> ARS | E47: =INDEX(Player_Analysis!$E$2:$E$700,MATCH(C47,Player_Analysis!$A$2:$A$700,0)) -> 5.5 | F47: =INDEX(Player_Analysis!$BA$2:$BA$700,MATCH(C47,Player_Analysis!$A$2:$A$700,0)) -> 7.2527706 | G47: 0 | H47: =INDEX(Player_Analysis!$AT$2:$AT$700,MATCH(C47,Player_Analysis!$A$2:$A$700,0)) -> 7.2527706 | I47: =IF(G47=1,COUNTIF($G$9:G47,1),"") | J47: =IFERROR(INDEX(Player_Analysis!$H$2:$H$596,MATCH($C47,Player_Analysis!$A$2:$A$596,0)),0) -> 1
A48: DEF | B48: 10 | C48: {=INDEX(Player_Analysis!$A$2:$A$700,MATCH(1,(Player_Analysis!$B$2:$B$700=A48)*(Player_Analysis!$BB$2:$BB$700=B48),0))} -> Jaka Bijol | D48: =INDEX(Player_Analysis!$D$2:$D$700,MATCH(C48,Player_Analysis!$A$2:$A$700,0)) -> LEE | E48: =INDEX(Player_Analysis!$E$2:$E$700,MATCH(C48,Player_Analysis!$A$2:$A$700,0)) -> 5 | F48: =INDEX(Player_Analysis!$BA$2:$BA$700,MATCH(C48,Player_Analysis!$A$2:$A$700,0)) -> 7.2093002 | G48: 0 | H48: =INDEX(Player_Analysis!$AT$2:$AT$700,MATCH(C48,Player_Analysis!$A$2:$A$700,0)) -> 7.2093002 | I48: =IF(G48=1,COUNTIF($G$9:G48,1),"") | J48: =IFERROR(INDEX(Player_Analysis!$H$2:$H$596,MATCH($C48,Player_Analysis!$A$2:$A$596,0)),0) -> 1
A49: DEF | B49: 11 | C49: {=INDEX(Player_Analysis!$A$2:$A$700,MATCH(1,(Player_Analysis!$B$2:$B$700=A49)*(Player_Analysis!$BB$2:$BB$700=B49),0))} -> Marc Guéhi | D49: =INDEX(Player_Analysis!$D$2:$D$700,MATCH(C49,Player_Analysis!$A$2:$A$700,0)) -> MCI | E49: =INDEX(Player_Analysis!$E$2:$E$700,MATCH(C49,Player_Analysis!$A$2:$A$700,0)) -> 6 | F49: =INDEX(Player_Analysis!$BA$2:$BA$700,MATCH(C49,Player_Analysis!$A$2:$A$700,0)) -> 7.0409237 | G49: 0 | H49: =INDEX(Player_Analysis!$AT$2:$AT$700,MATCH(C49,Player_Analysis!$A$2:$A$700,0)) -> 7.0409237 | I49: =IF(G49=1,COUNTIF($G$9:G49,1),"") | J49: =IFERROR(INDEX(Player_Analysis!$H$2:$H$596,MATCH($C49,Player_Analysis!$A$2:$A$596,0)),0) -> 1
A50: DEF | B50: 12 | C50: {=INDEX(Player_Analysis!$A$2:$A$700,MATCH(1,(Player_Analysis!$B$2:$B$700=A50)*(Player_Analysis!$BB$2:$BB$700=B50),0))} -> Murillo Costa dos Santos | D50: =INDEX(Player_Analysis!$D$2:$D$700,MATCH(C50,Player_Analysis!$A$2:$A$700,0)) -> NFO | E50: =INDEX(Player_Analysis!$E$2:$E$700,MATCH(C50,Player_Analysis!$A$2:$A$700,0)) -> 5.5 | F50: =INDEX(Player_Analysis!$BA$2:$BA$700,MATCH(C50,Player_Analysis!$A$2:$A$700,0)) -> 6.7012868 | G50: 0 | H50: =INDEX(Player_Analysis!$AT$2:$AT$700,MATCH(C50,Player_Analysis!$A$2:$A$700,0)) -> 6.7012868 | I50: =IF(G50=1,COUNTIF($G$9:G50,1),"") | J50: =IFERROR(INDEX(Player_Analysis!$H$2:$H$596,MATCH($C50,Player_Analysis!$A$2:$A$596,0)),0) -> 1
... A68: DEF | B68: 30 | C68: {=INDEX(Player_Analysis!$A$2:$A$700,MATCH(1,(Player_Analysis!$B$2:$B$700=A68)*(Player_Analysis!$BB$2:$BB$700=B68),0))} -> Joško Gvardiol | D68: =INDEX(Player_Analysis!$D$2:$D$700,MATCH(C68,Player_Analysis!$A$2:$A$700,0)) -> MCI | E68: =INDEX(Player_Analysis!$E$2:$E$700,MATCH(C68,Player_Analysis!$A$2:$A$700,0)) -> 5.6 | F68: =INDEX(Player_Analysis!$BA$2:$BA$700,MATCH(C68,Player_Analysis!$A$2:$A$700,0)) -> 5.4627788 | G68: 0 | H68: =INDEX(Player_Analysis!$AT$2:$AT$700,MATCH(C68,Player_Analysis!$A$2:$A$700,0)) -> 5.4627788 | I68: =IF(G68=1,COUNTIF($G$9:G68,1),"") | J68: =IFERROR(INDEX(Player_Analysis!$H$2:$H$596,MATCH($C68,Player_Analysis!$A$2:$A$596,0)),0) -> 1
A69: DEF | B69: 31 | C69: {=INDEX(Player_Analysis!$A$2:$A$700,MATCH(1,(Player_Analysis!$B$2:$B$700=A69)*(Player_Analysis!$BB$2:$BB$700=B69),0))} -> Ola Aina | D69: =INDEX(Player_Analysis!$D$2:$D$700,MATCH(C69,Player_Analysis!$A$2:$A$700,0)) -> NFO | E69: =INDEX(Player_Analysis!$E$2:$E$700,MATCH(C69,Player_Analysis!$A$2:$A$700,0)) -> 4.5 | F69: =INDEX(Player_Analysis!$BA$2:$BA$700,MATCH(C69,Player_Analysis!$A$2:$A$700,0)) -> 5.3892408 | G69: 0 | H69: =INDEX(Player_Analysis!$AT$2:$AT$700,MATCH(C69,Player_Analysis!$A$2:$A$700,0)) -> 5.3892408 | J69: =IFERROR(INDEX(Player_Analysis!$H$2:$H$596,MATCH($C69,Player_Analysis!$A$2:$A$596,0)),0) -> 1
A70: DEF | B70: 32 | C70: {=INDEX(Player_Analysis!$A$2:$A$700,MATCH(1,(Player_Analysis!$B$2:$B$700=A70)*(Player_Analysis!$BB$2:$BB$700=B70),0))} -> Sven Botman | D70: =INDEX(Player_Analysis!$D$2:$D$700,MATCH(C70,Player_Analysis!$A$2:$A$700,0)) -> NEW | E70: =INDEX(Player_Analysis!$E$2:$E$700,MATCH(C70,Player_Analysis!$A$2:$A$700,0)) -> 5 | F70: =INDEX(Player_Analysis!$BA$2:$BA$700,MATCH(C70,Player_Analysis!$A$2:$A$700,0)) -> 5.3424078 | G70: 0 | H70: =INDEX(Player_Analysis!$AT$2:$AT$700,MATCH(C70,Player_Analysis!$A$2:$A$700,0)) -> 5.3424078 | J70: =IFERROR(INDEX(Player_Analysis!$H$2:$H$596,MATCH($C70,Player_Analysis!$A$2:$A$596,0)),0) -> 1
A71: DEF | B71: 33 | C71: {=INDEX(Player_Analysis!$A$2:$A$700,MATCH(1,(Player_Analysis!$B$2:$B$700=A71)*(Player_Analysis!$BB$2:$BB$700=B71),0))} -> Ronald Araujo | D71: =INDEX(Player_Analysis!$D$2:$D$700,MATCH(C71,Player_Analysis!$A$2:$A$700,0)) -> LIV | E71: =INDEX(Player_Analysis!$E$2:$E$700,MATCH(C71,Player_Analysis!$A$2:$A$700,0)) -> 5.4 | F71: =INDEX(Player_Analysis!$BA$2:$BA$700,MATCH(C71,Player_Analysis!$A$2:$A$700,0)) -> 5.2253363 | G71: 0 | H71: =INDEX(Player_Analysis!$AT$2:$AT$700,MATCH(C71,Player_Analysis!$A$2:$A$700,0)) -> 5.2253363 | J71: =IFERROR(INDEX(Player_Analysis!$H$2:$H$596,MATCH($C71,Player_Analysis!$A$2:$A$596,0)),0) -> 1
A72: DEF | B72: 34 | C72: {=INDEX(Player_Analysis!$A$2:$A$700,MATCH(1,(Player_Analysis!$B$2:$B$700=A72)*(Player_Analysis!$BB$2:$BB$700=B72),0))} -> Bobby Thomas | D72: =INDEX(Player_Analysis!$D$2:$D$700,MATCH(C72,Player_Analysis!$A$2:$A$700,0)) -> COV | E72: =INDEX(Player_Analysis!$E$2:$E$700,MATCH(C72,Player_Analysis!$A$2:$A$700,0)) -> 4 | F72: =INDEX(Player_Analysis!$BA$2:$BA$700,MATCH(C72,Player_Analysis!$A$2:$A$700,0)) -> 5.1406448 | G72: 0 | H72: =INDEX(Player_Analysis!$AT$2:$AT$700,MATCH(C72,Player_Analysis!$A$2:$A$700,0)) -> 5.1406448 | J72: =IFERROR(INDEX(Player_Analysis!$H$2:$H$596,MATCH($C72,Player_Analysis!$A$2:$A$596,0)),0) -> 1
A73: DEF | B73: 35 | C73: {=INDEX(Player_Analysis!$A$2:$A$700,MATCH(1,(Player_Analysis!$B$2:$B$700=A73)*(Player_Analysis!$BB$2:$BB$700=B73),0))} -> Amar Dedic | D73: =INDEX(Player_Analysis!$D$2:$D$700,MATCH(C73,Player_Analysis!$A$2:$A$700,0)) -> NEW | E73: =INDEX(Player_Analysis!$E$2:$E$700,MATCH(C73,Player_Analysis!$A$2:$A$700,0)) -> 4.5 | F73: =INDEX(Player_Analysis!$BA$2:$BA$700,MATCH(C73,Player_Analysis!$A$2:$A$700,0)) -> 5.013471 | G73: 0 | H73: =INDEX(Player_Analysis!$AT$2:$AT$700,MATCH(C73,Player_Analysis!$A$2:$A$700,0)) -> 5.013471 | J73: =IFERROR(INDEX(Player_Analysis!$H$2:$H$596,MATCH($C73,Player_Analysis!$A$2:$A$596,0)),0) -> 1
A74: DEF | B74: 36 | C74: {=INDEX(Player_Analysis!$A$2:$A$700,MATCH(1,(Player_Analysis!$B$2:$B$700=A74)*(Player_Analysis!$BB$2:$BB$700=B74),0))} -> Malick Thiaw | D74: =INDEX(Player_Analysis!$D$2:$D$700,MATCH(C74,Player_Analysis!$A$2:$A$700,0)) -> NEW | E74: =INDEX(Player_Analysis!$E$2:$E$700,MATCH(C74,Player_Analysis!$A$2:$A$700,0)) -> 5 | F74: =INDEX(Player_Analysis!$BA$2:$BA$700,MATCH(C74,Player_Analysis!$A$2:$A$700,0)) -> 5.0125538 | G74: 0 | H74: =INDEX(Player_Analysis!$AT$2:$AT$700,MATCH(C74,Player_Analysis!$A$2:$A$700,0)) -> 5.0125538 | J74: =IFERROR(INDEX(Player_Analysis!$H$2:$H$596,MATCH($C74,Player_Analysis!$A$2:$A$596,0)),0) -> 1
A75: DEF | B75: 37 | C75: {=INDEX(Player_Analysis!$A$2:$A$700,MATCH(1,(Player_Analysis!$B$2:$B$700=A75)*(Player_Analysis!$BB$2:$BB$700=B75),0))} -> Vitalii Mykolenko | D75: =INDEX(Player_Analysis!$D$2:$D$700,MATCH(C75,Player_Analysis!$A$2:$A$700,0)) -> EVE | E75: =INDEX(Player_Analysis!$E$2:$E$700,MATCH(C75,Player_Analysis!$A$2:$A$700,0)) -> 4.5 | F75: =INDEX(Player_Analysis!$BA$2:$BA$700,MATCH(C75,Player_Analysis!$A$2:$A$700,0)) -> 4.917689 | G75: 0 | H75: =INDEX(Player_Analysis!$AT$2:$AT$700,MATCH(C75,Player_Analysis!$A$2:$A$700,0)) -> 4.917689 | J75: =IFERROR(INDEX(Player_Analysis!$H$2:$H$596,MATCH($C75,Player_Analysis!$A$2:$A$596,0)),0) -> 1
A76: DEF | B76: 38 | C76: {=INDEX(Player_Analysis!$A$2:$A$700,MATCH(1,(Player_Analysis!$B$2:$B$700=A76)*(Player_Analysis!$BB$2:$BB$700=B76),0))} -> Ian Maatsen | D76: =INDEX(Player_Analysis!$D$2:$D$700,MATCH(C76,Player_Analysis!$A$2:$A$700,0)) -> AVL | E76: =INDEX(Player_Analysis!$E$2:$E$700,MATCH(C76,Player_Analysis!$A$2:$A$700,0)) -> 4.5 | F76: =INDEX(Player_Analysis!$BA$2:$BA$700,MATCH(C76,Player_Analysis!$A$2:$A$700,0)) -> 4.8789819 | G76: 0 | H76: =INDEX(Player_Analysis!$AT$2:$AT$700,MATCH(C76,Player_Analysis!$A$2:$A$700,0)) -> 4.8789819 | J76: =IFERROR(INDEX(Player_Analysis!$H$2:$H$596,MATCH($C76,Player_Analysis!$A$2:$A$596,0)),0) -> 1
A77: DEF | B77: 39 | C77: {=INDEX(Player_Analysis!$A$2:$A$700,MATCH(1,(Player_Analysis!$B$2:$B$700=A77)*(Player_Analysis!$BB$2:$BB$700=B77),0))} -> Pedro Porro Sauceda | D77: =INDEX(Player_Analysis!$D$2:$D$700,MATCH(C77,Player_Analysis!$A$2:$A$700,0)) -> TOT | E77: =INDEX(Player_Analysis!$E$2:$E$700,MATCH(C77,Player_Analysis!$A$2:$A$700,0)) -> 5.5 | F77: =INDEX(Player_Analysis!$BA$2:$BA$700,MATCH(C77,Player_Analysis!$A$2:$A$700,0)) -> 4.8752312 | G77: 0 | H77: =INDEX(Player_Analysis!$AT$2:$AT$700,MATCH(C77,Player_Analysis!$A$2:$A$700,0)) -> 4.8752312 | J77: =IFERROR(INDEX(Player_Analysis!$H$2:$H$596,MATCH($C77,Player_Analysis!$A$2:$A$596,0)),0) -> 1
A78: DEF | B78: 40 | C78: {=INDEX(Player_Analysis!$A$2:$A$700,MATCH(1,(Player_Analysis!$B$2:$B$700=A78)*(Player_Analysis!$BB$2:$BB$700=B78),0))} -> Abdukodir Khusanov | D78: =INDEX(Player_Analysis!$D$2:$D$700,MATCH(C78,Player_Analysis!$A$2:$A$700,0)) -> MCI | E78: =INDEX(Player_Analysis!$E$2:$E$700,MATCH(C78,Player_Analysis!$A$2:$A$700,0)) -> 5.5 | F78: =INDEX(Player_Analysis!$BA$2:$BA$700,MATCH(C78,Player_Analysis!$A$2:$A$700,0)) -> 4.7963666 | G78: 0 | H78: =INDEX(Player_Analysis!$AT$2:$AT$700,MATCH(C78,Player_Analysis!$A$2:$A$700,0)) -> 4.7963666 | J78: =IFERROR(INDEX(Player_Analysis!$H$2:$H$596,MATCH($C78,Player_Analysis!$A$2:$A$596,0)),0) -> 1
A79: DEF | B79: 41 | C79: {=INDEX(Player_Analysis!$A$2:$A$700,MATCH(1,(Player_Analysis!$B$2:$B$700=A79)*(Player_Analysis!$BB$2:$BB$700=B79),0))} -> Virgil van Dijk | D79: =INDEX(Player_Analysis!$D$2:$D$700,MATCH(C79,Player_Analysis!$A$2:$A$700,0)) -> LIV | E79: =INDEX(Player_Analysis!$E$2:$E$700,MATCH(C79,Player_Analysis!$A$2:$A$700,0)) -> 6.5 | F79: =INDEX(Player_Analysis!$BA$2:$BA$700,MATCH(C79,Player_Analysis!$A$2:$A$700,0)) -> 4.7302875 | G79: 0 | H79: =INDEX(Player_Analysis!$AT$2:$AT$700,MATCH(C79,Player_Analysis!$A$2:$A$700,0)) -> 4.7302875 | J79: =IFERROR(INDEX(Player_Analysis!$H$2:$H$596,MATCH($C79,Player_Analysis!$A$2:$A$596,0)),0) -> 1
A80: DEF | B80: 42 | C80: {=INDEX(Player_Analysis!$A$2:$A$700,MATCH(1,(Player_Analysis!$B$2:$B$700=A80)*(Player_Analysis!$BB$2:$BB$700=B80),0))} -> Marcos Senesi Barón | D80: =INDEX(Player_Analysis!$D$2:$D$700,MATCH(C80,Player_Analysis!$A$2:$A$700,0)) -> TOT | E80: =INDEX(Player_Analysis!$E$2:$E$700,MATCH(C80,Player_Analysis!$A$2:$A$700,0)) -> 5.9 | F80: =INDEX(Player_Analysis!$BA$2:$BA$700,MATCH(C80,Player_Analysis!$A$2:$A$700,0)) -> 4.7029776 | G80: 0 | H80: =INDEX(Player_Analysis!$AT$2:$AT$700,MATCH(C80,Player_Analysis!$A$2:$A$700,0)) -> 4.7029776 | J80: =IFERROR(INDEX(Player_Analysis!$H$2:$H$596,MATCH($C80,Player_Analysis!$A$2:$A$596,0)),0) -> 1
A81: DEF | B81: 43 | C81: {=INDEX(Player_Analysis!$A$2:$A$700,MATCH(1,(Player_Analysis!$B$2:$B$700=A81)*(Player_Analysis!$BB$2:$BB$700=B81),0))} -> Luka Vušković | D81: =INDEX(Player_Analysis!$D$2:$D$700,MATCH(C81,Player_Analysis!$A$2:$A$700,0)) -> BHA | E81: =INDEX(Player_Analysis!$E$2:$E$700,MATCH(C81,Player_Analysis!$A$2:$A$700,0)) -> 5 | F81: =INDEX(Player_Analysis!$BA$2:$BA$700,MATCH(C81,Player_Analysis!$A$2:$A$700,0)) -> 4.638972 | G81: 0 | H81: =INDEX(Player_Analysis!$AT$2:$AT$700,MATCH(C81,Player_Analysis!$A$2:$A$700,0)) -> 4.638972 | J81: =IFERROR(INDEX(Player_Analysis!$H$2:$H$596,MATCH($C81,Player_Analysis!$A$2:$A$596,0)),0) -> 1
A82: MID | B82: 1 | C82: {=INDEX(Player_Analysis!$A$2:$A$700,MATCH(1,(Player_Analysis!$B$2:$B$700=A82)*(Player_Analysis!$BB$2:$BB$700=B82),0))} -> Bruno Borges Fernandes | D82: =INDEX(Player_Analysis!$D$2:$D$700,MATCH(C82,Player_Analysis!$A$2:$A$700,0)) -> MUN | E82: =INDEX(Player_Analysis!$E$2:$E$700,MATCH(C82,Player_Analysis!$A$2:$A$700,0)) -> 12 | F82: =INDEX(Player_Analysis!$BA$2:$BA$700,MATCH(C82,Player_Analysis!$A$2:$A$700,0)) -> 7.9365199 | G82: 0 | H82: =INDEX(Player_Analysis!$AT$2:$AT$700,MATCH(C82,Player_Analysis!$A$2:$A$700,0)) -> 7.9365199 | I82: =IF(G82=1,COUNTIF($G$9:G82,1),"") | J82: =IFERROR(INDEX(Player_Analysis!$H$2:$H$596,MATCH($C82,Player_Analysis!$A$2:$A$596,0)),0) -> 1
A83: MID | B83: 2 | C83: {=INDEX(Player_Analysis!$A$2:$A$700,MATCH(1,(Player_Analysis!$B$2:$B$700=A83)*(Player_Analysis!$BB$2:$BB$700=B83),0))} -> Bryan Mbeumo | D83: =INDEX(Player_Analysis!$D$2:$D$700,MATCH(C83,Player_Analysis!$A$2:$A$700,0)) -> MUN | E83: =INDEX(Player_Analysis!$E$2:$E$700,MATCH(C83,Player_Analysis!$A$2:$A$700,0)) -> 7.9 | F83: =INDEX(Player_Analysis!$BA$2:$BA$700,MATCH(C83,Player_Analysis!$A$2:$A$700,0)) -> 7.787795 | G83: 1 | H83: =INDEX(Player_Analysis!$AT$2:$AT$700,MATCH(C83,Player_Analysis!$A$2:$A$700,0)) -> 7.787795 | I83: =IF(G83=1,COUNTIF($G$9:G83,1),"") -> 8 | J83: =IFERROR(INDEX(Player_Analysis!$H$2:$H$596,MATCH($C83,Player_Analysis!$A$2:$A$596,0)),0) -> 1
A84: MID | B84: 3 | C84: {=INDEX(Player_Analysis!$A$2:$A$700,MATCH(1,(Player_Analysis!$B$2:$B$700=A84)*(Player_Analysis!$BB$2:$BB$700=B84),0))} -> Jack Hinshelwood | D84: =INDEX(Player_Analysis!$D$2:$D$700,MATCH(C84,Player_Analysis!$A$2:$A$700,0)) -> BHA | E84: =INDEX(Player_Analysis!$E$2:$E$700,MATCH(C84,Player_Analysis!$A$2:$A$700,0)) -> 6 | F84: =INDEX(Player_Analysis!$BA$2:$BA$700,MATCH(C84,Player_Analysis!$A$2:$A$700,0)) -> 7.7433503 | G84: 0 | H84: =INDEX(Player_Analysis!$AT$2:$AT$700,MATCH(C84,Player_Analysis!$A$2:$A$700,0)) -> 7.7433503 | I84: =IF(G84=1,COUNTIF($G$9:G84,1),"") | J84: =IFERROR(INDEX(Player_Analysis!$H$2:$H$596,MATCH($C84,Player_Analysis!$A$2:$A$596,0)),0) -> 0
A85: MID | B85: 4 | C85: {=INDEX(Player_Analysis!$A$2:$A$700,MATCH(1,(Player_Analysis!$B$2:$B$700=A85)*(Player_Analysis!$BB$2:$BB$700=B85),0))} -> Phil Foden | D85: =INDEX(Player_Analysis!$D$2:$D$700,MATCH(C85,Player_Analysis!$A$2:$A$700,0)) -> MCI | E85: =INDEX(Player_Analysis!$E$2:$E$700,MATCH(C85,Player_Analysis!$A$2:$A$700,0)) -> 7 | F85: =INDEX(Player_Analysis!$BA$2:$BA$700,MATCH(C85,Player_Analysis!$A$2:$A$700,0)) -> 7.6213819 | G85: 1 | H85: =INDEX(Player_Analysis!$AT$2:$AT$700,MATCH(C85,Player_Analysis!$A$2:$A$700,0)) -> 7.6213819 | I85: =IF(G85=1,COUNTIF($G$9:G85,1),"") -> 9 | J85: =IFERROR(INDEX(Player_Analysis!$H$2:$H$596,MATCH($C85,Player_Analysis!$A$2:$A$596,0)),0) -> 1
A86: MID | B86: 5 | C86: {=INDEX(Player_Analysis!$A$2:$A$700,MATCH(1,(Player_Analysis!$B$2:$B$700=A86)*(Player_Analysis!$BB$2:$BB$700=B86),0))} -> Dango Ouattara | D86: =INDEX(Player_Analysis!$D$2:$D$700,MATCH(C86,Player_Analysis!$A$2:$A$700,0)) -> BRE | E86: =INDEX(Player_Analysis!$E$2:$E$700,MATCH(C86,Player_Analysis!$A$2:$A$700,0)) -> 6.4 | F86: =INDEX(Player_Analysis!$BA$2:$BA$700,MATCH(C86,Player_Analysis!$A$2:$A$700,0)) -> 7.4311304 | G86: 1 | H86: =INDEX(Player_Analysis!$AT$2:$AT$700,MATCH(C86,Player_Analysis!$A$2:$A$700,0)) -> 7.4311304 | I86: =IF(G86=1,COUNTIF($G$9:G86,1),"") -> 10 | J86: =IFERROR(INDEX(Player_Analysis!$H$2:$H$596,MATCH($C86,Player_Analysis!$A$2:$A$596,0)),0) -> 1
A87: MID | B87: 6 | C87: {=INDEX(Player_Analysis!$A$2:$A$700,MATCH(1,(Player_Analysis!$B$2:$B$700=A87)*(Player_Analysis!$BB$2:$BB$700=B87),0))} -> Bukayo Saka | D87: =INDEX(Player_Analysis!$D$2:$D$700,MATCH(C87,Player_Analysis!$A$2:$A$700,0)) -> ARS | E87: =INDEX(Player_Analysis!$E$2:$E$700,MATCH(C87,Player_Analysis!$A$2:$A$700,0)) -> 9.5 | F87: =INDEX(Player_Analysis!$BA$2:$BA$700,MATCH(C87,Player_Analysis!$A$2:$A$700,0)) -> 7.3785097 | G87: 0 | H87: =INDEX(Player_Analysis!$AT$2:$AT$700,MATCH(C87,Player_Analysis!$A$2:$A$700,0)) -> 7.3785097 | I87: =IF(G87=1,COUNTIF($G$9:G87,1),"") | J87: =IFERROR(INDEX(Player_Analysis!$H$2:$H$596,MATCH($C87,Player_Analysis!$A$2:$A$596,0)),0) -> 1
A88: MID | B88: 7 | C88: {=INDEX(Player_Analysis!$A$2:$A$700,MATCH(1,(Player_Analysis!$B$2:$B$700=A88)*(Player_Analysis!$BB$2:$BB$700=B88),0))} -> Rayan Cherki | D88: =INDEX(Player_Analysis!$D$2:$D$700,MATCH(C88,Player_Analysis!$A$2:$A$700,0)) -> MCI | E88: =INDEX(Player_Analysis!$E$2:$E$700,MATCH(C88,Player_Analysis!$A$2:$A$700,0)) -> 7.8 | F88: =INDEX(Player_Analysis!$BA$2:$BA$700,MATCH(C88,Player_Analysis!$A$2:$A$700,0)) -> 7.2204286 | G88: 1 | H88: =INDEX(Player_Analysis!$AT$2:$AT$700,MATCH(C88,Player_Analysis!$A$2:$A$700,0)) -> 7.2204286 | I88: =IF(G88=1,COUNTIF($G$9:G88,1),"") -> 11 | J88: =IFERROR(INDEX(Player_Analysis!$H$2:$H$596,MATCH($C88,Player_Analysis!$A$2:$A$596,0)),0) -> 1
A89: MID | B89: 8 | C89: {=INDEX(Player_Analysis!$A$2:$A$700,MATCH(1,(Player_Analysis!$B$2:$B$700=A89)*(Player_Analysis!$BB$2:$BB$700=B89),0))} -> Andrey Nascimento dos Santos | D89: =INDEX(Player_Analysis!$D$2:$D$700,MATCH(C89,Player_Analysis!$A$2:$A$700,0)) -> MUN | E89: =INDEX(Player_Analysis!$E$2:$E$700,MATCH(C89,Player_Analysis!$A$2:$A$700,0)) -> 4.9 | F89: =INDEX(Player_Analysis!$BA$2:$BA$700,MATCH(C89,Player_Analysis!$A$2:$A$700,0)) -> 7.0275502 | G89: 1 | H89: =INDEX(Player_Analysis!$AT$2:$AT$700,MATCH(C89,Player_Analysis!$A$2:$A$700,0)) -> 7.0275502 | I89: =IF(G89=1,COUNTIF($G$9:G89,1),"") -> 12 | J89: =IFERROR(INDEX(Player_Analysis!$H$2:$H$596,MATCH($C89,Player_Analysis!$A$2:$A$596,0)),0) -> 1
A90: MID | B90: 9 | C90: {=INDEX(Player_Analysis!$A$2:$A$700,MATCH(1,(Player_Analysis!$B$2:$B$700=A90)*(Player_Analysis!$BB$2:$BB$700=B90),0))} -> Keane Lewis-Potter | D90: =INDEX(Player_Analysis!$D$2:$D$700,MATCH(C90,Player_Analysis!$A$2:$A$700,0)) -> BRE | E90: =INDEX(Player_Analysis!$E$2:$E$700,MATCH(C90,Player_Analysis!$A$2:$A$700,0)) -> 5.5 | F90: =INDEX(Player_Analysis!$BA$2:$BA$700,MATCH(C90,Player_Analysis!$A$2:$A$700,0)) -> 6.9157377 | G90: 0 | H90: =INDEX(Player_Analysis!$AT$2:$AT$700,MATCH(C90,Player_Analysis!$A$2:$A$700,0)) -> 6.9157377 | I90: =IF(G90=1,COUNTIF($G$9:G90,1),"") | J90: =IFERROR(INDEX(Player_Analysis!$H$2:$H$596,MATCH($C90,Player_Analysis!$A$2:$A$596,0)),0) -> 1
A91: MID | B91: 10 | C91: {=INDEX(Player_Analysis!$A$2:$A$700,MATCH(1,(Player_Analysis!$B$2:$B$700=A91)*(Player_Analysis!$BB$2:$BB$700=B91),0))} -> Martin Ødegaard | D91: =INDEX(Player_Analysis!$D$2:$D$700,MATCH(C91,Player_Analysis!$A$2:$A$700,0)) -> ARS | E91: =INDEX(Player_Analysis!$E$2:$E$700,MATCH(C91,Player_Analysis!$A$2:$A$700,0)) -> 6.6 | F91: =INDEX(Player_Analysis!$BA$2:$BA$700,MATCH(C91,Player_Analysis!$A$2:$A$700,0)) -> 6.8862225 | G91: 0 | H91: =INDEX(Player_Analysis!$AT$2:$AT$700,MATCH(C91,Player_Analysis!$A$2:$A$700,0)) -> 6.8862225 | I91: =IF(G91=1,COUNTIF($G$9:G91,1),"") | J91: =IFERROR(INDEX(Player_Analysis!$H$2:$H$596,MATCH($C91,Player_Analysis!$A$2:$A$596,0)),0) -> 1
A92: MID | B92: 11 | C92: {=INDEX(Player_Analysis!$A$2:$A$700,MATCH(1,(Player_Analysis!$B$2:$B$700=A92)*(Player_Analysis!$BB$2:$BB$700=B92),0))} -> Dominik Szoboszlai | D92: =INDEX(Player_Analysis!$D$2:$D$700,MATCH(C92,Player_Analysis!$A$2:$A$700,0)) -> LIV | E92: =INDEX(Player_Analysis!$E$2:$E$700,MATCH(C92,Player_Analysis!$A$2:$A$700,0)) -> 7 | F92: =INDEX(Player_Analysis!$BA$2:$BA$700,MATCH(C92,Player_Analysis!$A$2:$A$700,0)) -> 6.88584 | G92: 0 | H92: =INDEX(Player_Analysis!$AT$2:$AT$700,MATCH(C92,Player_Analysis!$A$2:$A$700,0)) -> 6.88584 | I92: =IF(G92=1,COUNTIF($G$9:G92,1),"") | J92: =IFERROR(INDEX(Player_Analysis!$H$2:$H$596,MATCH($C92,Player_Analysis!$A$2:$A$596,0)),0) -> 1
A93: MID | B93: 12 | C93: {=INDEX(Player_Analysis!$A$2:$A$700,MATCH(1,(Player_Analysis!$B$2:$B$700=A93)*(Player_Analysis!$BB$2:$BB$700=B93),0))} -> Mamadou Sangaré | D93: =INDEX(Player_Analysis!$D$2:$D$700,MATCH(C93,Player_Analysis!$A$2:$A$700,0)) -> BRE | E93: =INDEX(Player_Analysis!$E$2:$E$700,MATCH(C93,Player_Analysis!$A$2:$A$700,0)) -> 5.7 | F93: =INDEX(Player_Analysis!$BA$2:$BA$700,MATCH(C93,Player_Analysis!$A$2:$A$700,0)) -> 6.7532254 | G93: 0 | H93: =INDEX(Player_Analysis!$AT$2:$AT$700,MATCH(C93,Player_Analysis!$A$2:$A$700,0)) -> 6.7532254 | I93: =IF(G93=1,COUNTIF($G$9:G93,1),"") | J93: =IFERROR(INDEX(Player_Analysis!$H$2:$H$596,MATCH($C93,Player_Analysis!$A$2:$A$596,0)),0) -> 1
... A121: MID | B121: 40 | C121: {=INDEX(Player_Analysis!$A$2:$A$700,MATCH(1,(Player_Analysis!$B$2:$B$700=A121)*(Player_Analysis!$BB$2:$BB$700=B121),0))} -> Anton Stach | D121: =INDEX(Player_Analysis!$D$2:$D$700,MATCH(C121,Player_Analysis!$A$2:$A$700,0)) -> LEE | E121: =INDEX(Player_Analysis!$E$2:$E$700,MATCH(C121,Player_Analysis!$A$2:$A$700,0)) -> 6 | F121: =INDEX(Player_Analysis!$BA$2:$BA$700,MATCH(C121,Player_Analysis!$A$2:$A$700,0)) -> 5.117675 | G121: 0 | H121: =INDEX(Player_Analysis!$AT$2:$AT$700,MATCH(C121,Player_Analysis!$A$2:$A$700,0)) -> 5.117675 | I121: =IF(G121=1,COUNTIF($G$9:G121,1),"") | J121: =IFERROR(INDEX(Player_Analysis!$H$2:$H$596,MATCH($C121,Player_Analysis!$A$2:$A$596,0)),0) -> 1
A122: MID | B122: 41 | C122: {=INDEX(Player_Analysis!$A$2:$A$700,MATCH(1,(Player_Analysis!$B$2:$B$700=A122)*(Player_Analysis!$BB$2:$BB$700=B122),0))} -> Mohamed Belloumi | D122: =INDEX(Player_Analysis!$D$2:$D$700,MATCH(C122,Player_Analysis!$A$2:$A$700,0)) -> HUL | E122: =INDEX(Player_Analysis!$E$2:$E$700,MATCH(C122,Player_Analysis!$A$2:$A$700,0)) -> 5 | F122: =INDEX(Player_Analysis!$BA$2:$BA$700,MATCH(C122,Player_Analysis!$A$2:$A$700,0)) -> 5.0775472 | G122: 0 | H122: =INDEX(Player_Analysis!$AT$2:$AT$700,MATCH(C122,Player_Analysis!$A$2:$A$700,0)) -> 5.0775472 | J122: =IFERROR(INDEX(Player_Analysis!$H$2:$H$596,MATCH($C122,Player_Analysis!$A$2:$A$596,0)),0) -> 1
A123: MID | B123: 42 | C123: {=INDEX(Player_Analysis!$A$2:$A$700,MATCH(1,(Player_Analysis!$B$2:$B$700=A123)*(Player_Analysis!$BB$2:$BB$700=B123),0))} -> Alex Scott | D123: =INDEX(Player_Analysis!$D$2:$D$700,MATCH(C123,Player_Analysis!$A$2:$A$700,0)) -> BOU | E123: =INDEX(Player_Analysis!$E$2:$E$700,MATCH(C123,Player_Analysis!$A$2:$A$700,0)) -> 6 | F123: =INDEX(Player_Analysis!$BA$2:$BA$700,MATCH(C123,Player_Analysis!$A$2:$A$700,0)) -> 5.0484146 | G123: 0 | H123: =INDEX(Player_Analysis!$AT$2:$AT$700,MATCH(C123,Player_Analysis!$A$2:$A$700,0)) -> 5.0484146 | J123: =IFERROR(INDEX(Player_Analysis!$H$2:$H$596,MATCH($C123,Player_Analysis!$A$2:$A$596,0)),0) -> 1
A124: MID | B124: 43 | C124: {=INDEX(Player_Analysis!$A$2:$A$700,MATCH(1,(Player_Analysis!$B$2:$B$700=A124)*(Player_Analysis!$BB$2:$BB$700=B124),0))} -> Antoine Semenyo | D124: =INDEX(Player_Analysis!$D$2:$D$700,MATCH(C124,Player_Analysis!$A$2:$A$700,0)) -> MCI | E124: =INDEX(Player_Analysis!$E$2:$E$700,MATCH(C124,Player_Analysis!$A$2:$A$700,0)) -> 8.4 | F124: =INDEX(Player_Analysis!$BA$2:$BA$700,MATCH(C124,Player_Analysis!$A$2:$A$700,0)) -> 5.0365719 | G124: 0 | H124: =INDEX(Player_Analysis!$AT$2:$AT$700,MATCH(C124,Player_Analysis!$A$2:$A$700,0)) -> 5.0365719 | J124: =IFERROR(INDEX(Player_Analysis!$H$2:$H$596,MATCH($C124,Player_Analysis!$A$2:$A$596,0)),0) -> 1
A125: MID | B125: 44 | C125: {=INDEX(Player_Analysis!$A$2:$A$700,MATCH(1,(Player_Analysis!$B$2:$B$700=A125)*(Player_Analysis!$BB$2:$BB$700=B125),0))} -> Malick Yalcouyé | D125: =INDEX(Player_Analysis!$D$2:$D$700,MATCH(C125,Player_Analysis!$A$2:$A$700,0)) -> BHA | E125: =INDEX(Player_Analysis!$E$2:$E$700,MATCH(C125,Player_Analysis!$A$2:$A$700,0)) -> 4.5 | F125: =INDEX(Player_Analysis!$BA$2:$BA$700,MATCH(C125,Player_Analysis!$A$2:$A$700,0)) -> 4.9805113 | G125: 0 | H125: =INDEX(Player_Analysis!$AT$2:$AT$700,MATCH(C125,Player_Analysis!$A$2:$A$700,0)) -> 4.9805113 | J125: =IFERROR(INDEX(Player_Analysis!$H$2:$H$596,MATCH($C125,Player_Analysis!$A$2:$A$596,0)),0) -> 1
A126: MID | B126: 45 | C126: {=INDEX(Player_Analysis!$A$2:$A$700,MATCH(1,(Player_Analysis!$B$2:$B$700=A126)*(Player_Analysis!$BB$2:$BB$700=B126),0))} -> Declan Rice | D126: =INDEX(Player_Analysis!$D$2:$D$700,MATCH(C126,Player_Analysis!$A$2:$A$700,0)) -> ARS | E126: =INDEX(Player_Analysis!$E$2:$E$700,MATCH(C126,Player_Analysis!$A$2:$A$700,0)) -> 7.4 | F126: =INDEX(Player_Analysis!$BA$2:$BA$700,MATCH(C126,Player_Analysis!$A$2:$A$700,0)) -> 4.9578802 | G126: 0 | H126: =INDEX(Player_Analysis!$AT$2:$AT$700,MATCH(C126,Player_Analysis!$A$2:$A$700,0)) -> 4.9578802 | J126: =IFERROR(INDEX(Player_Analysis!$H$2:$H$596,MATCH($C126,Player_Analysis!$A$2:$A$596,0)),0) -> 1
A127: MID | B127: 46 | C127: {=INDEX(Player_Analysis!$A$2:$A$700,MATCH(1,(Player_Analysis!$B$2:$B$700=A127)*(Player_Analysis!$BB$2:$BB$700=B127),0))} -> Brennan Johnson | D127: =INDEX(Player_Analysis!$D$2:$D$700,MATCH(C127,Player_Analysis!$A$2:$A$700,0)) -> EVE | E127: =INDEX(Player_Analysis!$E$2:$E$700,MATCH(C127,Player_Analysis!$A$2:$A$700,0)) -> 5.9 | F127: =INDEX(Player_Analysis!$BA$2:$BA$700,MATCH(C127,Player_Analysis!$A$2:$A$700,0)) -> 4.9353696 | G127: 0 | H127: =INDEX(Player_Analysis!$AT$2:$AT$700,MATCH(C127,Player_Analysis!$A$2:$A$700,0)) -> 4.9353696 | J127: =IFERROR(INDEX(Player_Analysis!$H$2:$H$596,MATCH($C127,Player_Analysis!$A$2:$A$596,0)),0) -> 1
A128: MID | B128: 47 | C128: {=INDEX(Player_Analysis!$A$2:$A$700,MATCH(1,(Player_Analysis!$B$2:$B$700=A128)*(Player_Analysis!$BB$2:$BB$700=B128),0))} -> Exequiel Palacios | D128: =INDEX(Player_Analysis!$D$2:$D$700,MATCH(C128,Player_Analysis!$A$2:$A$700,0)) -> IPS | E128: =INDEX(Player_Analysis!$E$2:$E$700,MATCH(C128,Player_Analysis!$A$2:$A$700,0)) -> 5 | F128: =INDEX(Player_Analysis!$BA$2:$BA$700,MATCH(C128,Player_Analysis!$A$2:$A$700,0)) -> 4.8888344 | G128: 0 | H128: =INDEX(Player_Analysis!$AT$2:$AT$700,MATCH(C128,Player_Analysis!$A$2:$A$700,0)) -> 4.8888344 | J128: =IFERROR(INDEX(Player_Analysis!$H$2:$H$596,MATCH($C128,Player_Analysis!$A$2:$A$596,0)),0) -> 1
A129: MID | B129: 48 | C129: {=INDEX(Player_Analysis!$A$2:$A$700,MATCH(1,(Player_Analysis!$B$2:$B$700=A129)*(Player_Analysis!$BB$2:$BB$700=B129),0))} -> Daizen Maeda | D129: =INDEX(Player_Analysis!$D$2:$D$700,MATCH(C129,Player_Analysis!$A$2:$A$700,0)) -> IPS | E129: =INDEX(Player_Analysis!$E$2:$E$700,MATCH(C129,Player_Analysis!$A$2:$A$700,0)) -> 5.4 | F129: =INDEX(Player_Analysis!$BA$2:$BA$700,MATCH(C129,Player_Analysis!$A$2:$A$700,0)) -> 4.8580153 | G129: 0 | H129: =INDEX(Player_Analysis!$AT$2:$AT$700,MATCH(C129,Player_Analysis!$A$2:$A$700,0)) -> 4.8580153 | J129: =IFERROR(INDEX(Player_Analysis!$H$2:$H$596,MATCH($C129,Player_Analysis!$A$2:$A$596,0)),0) -> 1
A130: MID | B130: 49 | C130: {=INDEX(Player_Analysis!$A$2:$A$700,MATCH(1,(Player_Analysis!$B$2:$B$700=A130)*(Player_Analysis!$BB$2:$BB$700=B130),0))} -> Morgan Gibbs-White | D130: =INDEX(Player_Analysis!$D$2:$D$700,MATCH(C130,Player_Analysis!$A$2:$A$700,0)) -> NFO | E130: =INDEX(Player_Analysis!$E$2:$E$700,MATCH(C130,Player_Analysis!$A$2:$A$700,0)) -> 7.9 | F130: =INDEX(Player_Analysis!$BA$2:$BA$700,MATCH(C130,Player_Analysis!$A$2:$A$700,0)) -> 4.8564199 | G130: 0 | H130: =INDEX(Player_Analysis!$AT$2:$AT$700,MATCH(C130,Player_Analysis!$A$2:$A$700,0)) -> 4.8564199 | J130: =IFERROR(INDEX(Player_Analysis!$H$2:$H$596,MATCH($C130,Player_Analysis!$A$2:$A$596,0)),0) -> 1
A131: FWD | B131: 1 | C131: {=INDEX(Player_Analysis!$A$2:$A$700,MATCH(1,(Player_Analysis!$B$2:$B$700=A131)*(Player_Analysis!$BB$2:$BB$700=B131),0))} -> Erling Haaland | D131: =INDEX(Player_Analysis!$D$2:$D$700,MATCH(C131,Player_Analysis!$A$2:$A$700,0)) -> MCI | E131: =INDEX(Player_Analysis!$E$2:$E$700,MATCH(C131,Player_Analysis!$A$2:$A$700,0)) -> 15.5 | F131: =INDEX(Player_Analysis!$BA$2:$BA$700,MATCH(C131,Player_Analysis!$A$2:$A$700,0)) -> 7.7831264 | G131: 1 | H131: =INDEX(Player_Analysis!$AT$2:$AT$700,MATCH(C131,Player_Analysis!$A$2:$A$700,0)) -> 7.7831264 | I131: =IF(G131=1,COUNTIF($G$9:G131,1),"") -> 13 | J131: =IFERROR(INDEX(Player_Analysis!$H$2:$H$596,MATCH($C131,Player_Analysis!$A$2:$A$596,0)),0) -> 1
A132: FWD | B132: 2 | C132: {=INDEX(Player_Analysis!$A$2:$A$700,MATCH(1,(Player_Analysis!$B$2:$B$700=A132)*(Player_Analysis!$BB$2:$BB$700=B132),0))} -> Igor Thiago Nascimento Rodrigues | D132: =INDEX(Player_Analysis!$D$2:$D$700,MATCH(C132,Player_Analysis!$A$2:$A$700,0)) -> BRE | E132: =INDEX(Player_Analysis!$E$2:$E$700,MATCH(C132,Player_Analysis!$A$2:$A$700,0)) -> 7.9 | F132: =INDEX(Player_Analysis!$BA$2:$BA$700,MATCH(C132,Player_Analysis!$A$2:$A$700,0)) -> 6.688367 | G132: 1 | H132: =INDEX(Player_Analysis!$AT$2:$AT$700,MATCH(C132,Player_Analysis!$A$2:$A$700,0)) -> 6.688367 | I132: =IF(G132=1,COUNTIF($G$9:G132,1),"") -> 14 | J132: =IFERROR(INDEX(Player_Analysis!$H$2:$H$596,MATCH($C132,Player_Analysis!$A$2:$A$596,0)),0) -> 1
A133: FWD | B133: 3 | C133: {=INDEX(Player_Analysis!$A$2:$A$700,MATCH(1,(Player_Analysis!$B$2:$B$700=A133)*(Player_Analysis!$BB$2:$BB$700=B133),0))} -> Thierno Barry | D133: =INDEX(Player_Analysis!$D$2:$D$700,MATCH(C133,Player_Analysis!$A$2:$A$700,0)) -> EVE | E133: =INDEX(Player_Analysis!$E$2:$E$700,MATCH(C133,Player_Analysis!$A$2:$A$700,0)) -> 5.6 | F133: =INDEX(Player_Analysis!$BA$2:$BA$700,MATCH(C133,Player_Analysis!$A$2:$A$700,0)) -> 6.2822815 | G133: 1 | H133: =INDEX(Player_Analysis!$AT$2:$AT$700,MATCH(C133,Player_Analysis!$A$2:$A$700,0)) -> 6.2822815 | I133: =IF(G133=1,COUNTIF($G$9:G133,1),"") -> 15 | J133: =IFERROR(INDEX(Player_Analysis!$H$2:$H$596,MATCH($C133,Player_Analysis!$A$2:$A$596,0)),0) -> 1
A134: FWD | B134: 4 | C134: {=INDEX(Player_Analysis!$A$2:$A$700,MATCH(1,(Player_Analysis!$B$2:$B$700=A134)*(Player_Analysis!$BB$2:$BB$700=B134),0))} -> Alexander Isak | D134: =INDEX(Player_Analysis!$D$2:$D$700,MATCH(C134,Player_Analysis!$A$2:$A$700,0)) -> LIV | E134: =INDEX(Player_Analysis!$E$2:$E$700,MATCH(C134,Player_Analysis!$A$2:$A$700,0)) -> 9 | F134: =INDEX(Player_Analysis!$BA$2:$BA$700,MATCH(C134,Player_Analysis!$A$2:$A$700,0)) -> 6.0486494 | G134: 0 | H134: =INDEX(Player_Analysis!$AT$2:$AT$700,MATCH(C134,Player_Analysis!$A$2:$A$700,0)) -> 6.0486494 | I134: =IF(G134=1,COUNTIF($G$9:G134,1),"") | J134: =IFERROR(INDEX(Player_Analysis!$H$2:$H$596,MATCH($C134,Player_Analysis!$A$2:$A$596,0)),0) -> 1
A135: FWD | B135: 5 | C135: {=INDEX(Player_Analysis!$A$2:$A$700,MATCH(1,(Player_Analysis!$B$2:$B$700=A135)*(Player_Analysis!$BB$2:$BB$700=B135),0))} -> Jean-Philippe Mateta | D135: =INDEX(Player_Analysis!$D$2:$D$700,MATCH(C135,Player_Analysis!$A$2:$A$700,0)) -> CRY | E135: =INDEX(Player_Analysis!$E$2:$E$700,MATCH(C135,Player_Analysis!$A$2:$A$700,0)) -> 6.4 | F135: =INDEX(Player_Analysis!$BA$2:$BA$700,MATCH(C135,Player_Analysis!$A$2:$A$700,0)) -> 5.7344533 | G135: 0 | H135: =INDEX(Player_Analysis!$AT$2:$AT$700,MATCH(C135,Player_Analysis!$A$2:$A$700,0)) -> 5.7344533 | I135: =IF(G135=1,COUNTIF($G$9:G135,1),"") | J135: =IFERROR(INDEX(Player_Analysis!$H$2:$H$596,MATCH($C135,Player_Analysis!$A$2:$A$596,0)),0) -> 0
A136: FWD | B136: 6 | C136: {=INDEX(Player_Analysis!$A$2:$A$700,MATCH(1,(Player_Analysis!$B$2:$B$700=A136)*(Player_Analysis!$BB$2:$BB$700=B136),0))} -> Eddie Nketiah | D136: =INDEX(Player_Analysis!$D$2:$D$700,MATCH(C136,Player_Analysis!$A$2:$A$700,0)) -> CRY | E136: =INDEX(Player_Analysis!$E$2:$E$700,MATCH(C136,Player_Analysis!$A$2:$A$700,0)) -> 5.5 | F136: =INDEX(Player_Analysis!$BA$2:$BA$700,MATCH(C136,Player_Analysis!$A$2:$A$700,0)) -> 5.5734821 | G136: 0 | H136: =INDEX(Player_Analysis!$AT$2:$AT$700,MATCH(C136,Player_Analysis!$A$2:$A$700,0)) -> 5.5734821 | I136: =IF(G136=1,COUNTIF($G$9:G136,1),"") | J136: =IFERROR(INDEX(Player_Analysis!$H$2:$H$596,MATCH($C136,Player_Analysis!$A$2:$A$596,0)),0) -> 1
A137: FWD | B137: 7 | C137: {=INDEX(Player_Analysis!$A$2:$A$700,MATCH(1,(Player_Analysis!$B$2:$B$700=A137)*(Player_Analysis!$BB$2:$BB$700=B137),0))} -> Charalampos Kostoulas | D137: =INDEX(Player_Analysis!$D$2:$D$700,MATCH(C137,Player_Analysis!$A$2:$A$700,0)) -> BHA | E137: =INDEX(Player_Analysis!$E$2:$E$700,MATCH(C137,Player_Analysis!$A$2:$A$700,0)) -> 5.5 | F137: =INDEX(Player_Analysis!$BA$2:$BA$700,MATCH(C137,Player_Analysis!$A$2:$A$700,0)) -> 5.2940592 | G137: 0 | H137: =INDEX(Player_Analysis!$AT$2:$AT$700,MATCH(C137,Player_Analysis!$A$2:$A$700,0)) -> 5.2940592 | I137: =IF(G137=1,COUNTIF($G$9:G137,1),"") | J137: =IFERROR(INDEX(Player_Analysis!$H$2:$H$596,MATCH($C137,Player_Analysis!$A$2:$A$596,0)),0) -> 1
A138: FWD | B138: 8 | C138: {=INDEX(Player_Analysis!$A$2:$A$700,MATCH(1,(Player_Analysis!$B$2:$B$700=A138)*(Player_Analysis!$BB$2:$BB$700=B138),0))} -> João Pedro Junqueira de Jesus | D138: =INDEX(Player_Analysis!$D$2:$D$700,MATCH(C138,Player_Analysis!$A$2:$A$700,0)) -> CHE | E138: =INDEX(Player_Analysis!$E$2:$E$700,MATCH(C138,Player_Analysis!$A$2:$A$700,0)) -> 7.7 | F138: =INDEX(Player_Analysis!$BA$2:$BA$700,MATCH(C138,Player_Analysis!$A$2:$A$700,0)) -> 5.2331744 | G138: 0 | H138: =INDEX(Player_Analysis!$AT$2:$AT$700,MATCH(C138,Player_Analysis!$A$2:$A$700,0)) -> 5.2331744 | I138: =IF(G138=1,COUNTIF($G$9:G138,1),"") | J138: =IFERROR(INDEX(Player_Analysis!$H$2:$H$596,MATCH($C138,Player_Analysis!$A$2:$A$596,0)),0) -> 1
A139: FWD | B139: 9 | C139: {=INDEX(Player_Analysis!$A$2:$A$700,MATCH(1,(Player_Analysis!$B$2:$B$700=A139)*(Player_Analysis!$BB$2:$BB$700=B139),0))} -> Gonzalo García | D139: =INDEX(Player_Analysis!$D$2:$D$700,MATCH(C139,Player_Analysis!$A$2:$A$700,0)) -> FUL | E139: =INDEX(Player_Analysis!$E$2:$E$700,MATCH(C139,Player_Analysis!$A$2:$A$700,0)) -> 6 | F139: =INDEX(Player_Analysis!$BA$2:$BA$700,MATCH(C139,Player_Analysis!$A$2:$A$700,0)) -> 5.060791 | G139: 0 | H139: =INDEX(Player_Analysis!$AT$2:$AT$700,MATCH(C139,Player_Analysis!$A$2:$A$700,0)) -> 5.060791 | I139: =IF(G139=1,COUNTIF($G$9:G139,1),"") | J139: =IFERROR(INDEX(Player_Analysis!$H$2:$H$596,MATCH($C139,Player_Analysis!$A$2:$A$596,0)),0) -> 1
A140: FWD | B140: 10 | C140: {=INDEX(Player_Analysis!$A$2:$A$700,MATCH(1,(Player_Analysis!$B$2:$B$700=A140)*(Player_Analysis!$BB$2:$BB$700=B140),0))} -> Georginio Rutter | D140: =INDEX(Player_Analysis!$D$2:$D$700,MATCH(C140,Player_Analysis!$A$2:$A$700,0)) -> BHA | E140: =INDEX(Player_Analysis!$E$2:$E$700,MATCH(C140,Player_Analysis!$A$2:$A$700,0)) -> 5.5 | F140: =INDEX(Player_Analysis!$BA$2:$BA$700,MATCH(C140,Player_Analysis!$A$2:$A$700,0)) -> 4.986297 | G140: 0 | H140: =INDEX(Player_Analysis!$AT$2:$AT$700,MATCH(C140,Player_Analysis!$A$2:$A$700,0)) -> 4.986297 | I140: =IF(G140=1,COUNTIF($G$9:G140,1),"") | J140: =IFERROR(INDEX(Player_Analysis!$H$2:$H$596,MATCH($C140,Player_Analysis!$A$2:$A$596,0)),0) -> 0
A141: FWD | B141: 11 | C141: {=INDEX(Player_Analysis!$A$2:$A$700,MATCH(1,(Player_Analysis!$B$2:$B$700=A141)*(Player_Analysis!$BB$2:$BB$700=B141),0))} -> Yoane Wissa | D141: =INDEX(Player_Analysis!$D$2:$D$700,MATCH(C141,Player_Analysis!$A$2:$A$700,0)) -> NEW | E141: =INDEX(Player_Analysis!$E$2:$E$700,MATCH(C141,Player_Analysis!$A$2:$A$700,0)) -> 6.2 | F141: =INDEX(Player_Analysis!$BA$2:$BA$700,MATCH(C141,Player_Analysis!$A$2:$A$700,0)) -> 4.9737151 | G141: 0 | H141: =INDEX(Player_Analysis!$AT$2:$AT$700,MATCH(C141,Player_Analysis!$A$2:$A$700,0)) -> 4.9737151 | I141: =IF(G141=1,COUNTIF($G$9:G141,1),"") | J141: =IFERROR(INDEX(Player_Analysis!$H$2:$H$596,MATCH($C141,Player_Analysis!$A$2:$A$596,0)),0) -> 1
A142: FWD | B142: 12 | C142: {=INDEX(Player_Analysis!$A$2:$A$700,MATCH(1,(Player_Analysis!$B$2:$B$700=A142)*(Player_Analysis!$BB$2:$BB$700=B142),0))} -> Emersonn Correia da Silva | D142: =INDEX(Player_Analysis!$D$2:$D$700,MATCH(C142,Player_Analysis!$A$2:$A$700,0)) -> IPS | E142: =INDEX(Player_Analysis!$E$2:$E$700,MATCH(C142,Player_Analysis!$A$2:$A$700,0)) -> 5.5 | F142: =INDEX(Player_Analysis!$BA$2:$BA$700,MATCH(C142,Player_Analysis!$A$2:$A$700,0)) -> 4.8791078 | G142: 0 | H142: =INDEX(Player_Analysis!$AT$2:$AT$700,MATCH(C142,Player_Analysis!$A$2:$A$700,0)) -> 4.8791078 | I142: =IF(G142=1,COUNTIF($G$9:G142,1),"") | J142: =IFERROR(INDEX(Player_Analysis!$H$2:$H$596,MATCH($C142,Player_Analysis!$A$2:$A$596,0)),0) -> 1
... A150: FWD | B150: 20 | C150: {=INDEX(Player_Analysis!$A$2:$A$700,MATCH(1,(Player_Analysis!$B$2:$B$700=A150)*(Player_Analysis!$BB$2:$BB$700=B150),0))} -> Igor Jesus Maciel da Cruz | D150: =INDEX(Player_Analysis!$D$2:$D$700,MATCH(C150,Player_Analysis!$A$2:$A$700,0)) -> NFO | E150: =INDEX(Player_Analysis!$E$2:$E$700,MATCH(C150,Player_Analysis!$A$2:$A$700,0)) -> 5.9 | F150: =INDEX(Player_Analysis!$BA$2:$BA$700,MATCH(C150,Player_Analysis!$A$2:$A$700,0)) -> 3.1395653 | G150: 0 | H150: =INDEX(Player_Analysis!$AT$2:$AT$700,MATCH(C150,Player_Analysis!$A$2:$A$700,0)) -> 3.1395653 | I150: =IF(G150=1,COUNTIF($G$9:G150,1),"") | J150: =IFERROR(INDEX(Player_Analysis!$H$2:$H$596,MATCH($C150,Player_Analysis!$A$2:$A$596,0)),0) -> 1
A151: FWD | B151: 21 | C151: {=INDEX(Player_Analysis!$A$2:$A$700,MATCH(1,(Player_Analysis!$B$2:$B$700=A151)*(Player_Analysis!$BB$2:$BB$700=B151),0))} -> Nicolas Jackson | D151: =INDEX(Player_Analysis!$D$2:$D$700,MATCH(C151,Player_Analysis!$A$2:$A$700,0)) -> AVL | E151: =INDEX(Player_Analysis!$E$2:$E$700,MATCH(C151,Player_Analysis!$A$2:$A$700,0)) -> 6.5 | F151: =INDEX(Player_Analysis!$BA$2:$BA$700,MATCH(C151,Player_Analysis!$A$2:$A$700,0)) -> 3.0610863 | G151: 0 | H151: =INDEX(Player_Analysis!$AT$2:$AT$700,MATCH(C151,Player_Analysis!$A$2:$A$700,0)) -> 3.0610863 | J151: =IFERROR(INDEX(Player_Analysis!$H$2:$H$596,MATCH($C151,Player_Analysis!$A$2:$A$596,0)),0) -> 1
...

Sheet FPL_Raw_Data
A1: element_type | B1: first_name | C1: second_name | D1: id | E1: form | F1: now_cost | G1: points_per_game | H1: selected_by_percent | I1: team | J1: total_points | K1: minutes | L1: goals_scored | M1: assists | N1: clean_sheets | O1: goals_conceded | P1: saves | Q1: bonus | R1: bps | S1: defensive_contribution | T1: starts | U1: expected_goals | V1: expected_assists | W1: expected_goal_involvements | X1: expected_goals_conceded | Y1: status | Z1: can_select | AA1: Player
A2: 1 | B2: David | C2: Raya Martín | D2: 1 | E2: 5 | F2: 60 | G2: 5 | H2: 38.7 | I2: 1 | J2: 15 | K2: 270 | L2: 0 | M2: 0 | N2: 2 | O2: 1 | P2: 5 | Q2: 0 | R2: 60 | S2: 0 | T2: 3 | U2: 0 | V2: 0.01 | W2: 0.01 | X2: 0.92 | Y2: a | Z2: TRUE | AA2: =B2&" "&C2 -> David Raya Martín
A3: 1 | B3: Kepa | C3: Arrizabalaga Revuelta | D3: 2 | E3: 0 | F3: 49 | G3: 0 | H3: 0.1 | I3: 1 | J3: 0 | K3: 0 | L3: 0 | M3: 0 | N3: 0 | O3: 0 | P3: 0 | Q3: 0 | R3: 0 | S3: 0 | T3: 0 | U3: 0 | V3: 0 | W3: 0 | X3: 0 | Y3: a | Z3: TRUE | AA3: =B3&" "&C3 -> Kepa Arrizabalaga Revuelta
A4: 1 | B4: Illan | C4: Meslier | D4: 3 | E4: 0 | F4: 49 | G4: 0 | H4: 0 | I4: 1 | J4: 0 | K4: 0 | L4: 0 | M4: 0 | N4: 0 | O4: 0 | P4: 0 | Q4: 0 | R4: 0 | S4: 0 | T4: 0 | U4: 0 | V4: 0 | W4: 0 | X4: 0 | Y4: a | Z4: TRUE | AA4: =B4&" "&C4 -> Illan Meslier
A5: 2 | B5: Gabriel | C5: dos Santos Magalhães | D5: 4 | E5: 5 | F5: 80 | G5: 5 | H5: 25.1 | I5: 1 | J5: 15 | K5: 270 | L5: 0 | M5: 0 | N5: 2 | O5: 1 | P5: 0 | Q5: 0 | R5: 54 | S5: 21 | T5: 3 | U5: 0.49 | V5: 0.05 | W5: 0.54 | X5: 0.92 | Y5: a | Z5: TRUE | AA5: =B5&" "&C5 -> Gabriel dos Santos Magalhães
A6: 2 | B6: Jurriën | C6: Timber | D6: 5 | E6: 0 | F6: 65 | G6: 0 | H6: 0.1 | I6: 1 | J6: 0 | K6: 0 | L6: 0 | M6: 0 | N6: 0 | O6: 0 | P6: 0 | Q6: 0 | R6: 0 | S6: 0 | T6: 0 | U6: 0 | V6: 0 | W6: 0 | X6: 0 | Y6: d | Z6: TRUE | AA6: =B6&" "&C6 -> Jurriën Timber
A7: 2 | B7: William | C7: Saliba | D7: 6 | E7: 0 | F7: 60 | G7: 0 | H7: 0.2 | I7: 1 | J7: 0 | K7: 0 | L7: 0 | M7: 0 | N7: 0 | O7: 0 | P7: 0 | Q7: 0 | R7: 0 | S7: 0 | T7: 0 | U7: 0 | V7: 0 | W7: 0 | X7: 0 | Y7: i | Z7: TRUE | AA7: =B7&" "&C7 -> William Saliba
A8: 3 | B8: Myles | C8: Lewis-Skelly | D8: 7 | E8: 2.7 | F8: 55 | G8: 2.7 | H8: 0.7 | I8: 1 | J8: 8 | K8: 226 | L8: 0 | M8: 0 | N8: 2 | O8: 1 | P8: 0 | Q8: 0 | R8: 35 | S8: 14 | T8: 3 | U8: 0.16 | V8: 0.23 | W8: 0.39 | X8: 0.79 | Y8: a | Z8: TRUE | AA8: =B8&" "&C8 -> Myles Lewis-Skelly
A9: 2 | B9: Riccardo | C9: Calafiori | D9: 8 | E9: 7.3 | F9: 57 | G9: 7.3 | H9: 46.9 | I9: 1 | J9: 22 | K9: 236 | L9: 0 | M9: 2 | N9: 2 | O9: 1 | P9: 0 | Q9: 2 | R9: 61 | S9: 9 | T9: 3 | U9: 0.54 | V9: 0.58 | W9: 1.12 | X9: 0.65 | Y9: a | Z9: TRUE | AA9: =B9&" "&C9 -> Riccardo Calafiori
A10: 2 | B10: Piero | C10: Hincapié | D10: 9 | E10: 0.7 | F10: 53 | G10: 1 | H10: 1.1 | I10: 1 | J10: 2 | K10: 32 | L10: 0 | M10: 0 | N10: 0 | O10: 0 | P10: 0 | Q10: 0 | R10: 6 | S10: 3 | T10: 0 | U10: 0 | V10: 0 | W10: 0 | X10: 0.28 | Y10: a | Z10: TRUE | AA10: =B10&" "&C10 -> Piero Hincapié
A11: 2 | B11: Benjamin | C11: White | D11: 10 | E11: 6.7 | F11: 55 | G11: 6.7 | H11: 7.7 | I11: 1 | J11: 20 | K11: 270 | L11: 0 | M11: 1 | N11: 2 | O11: 1 | P11: 0 | Q11: 3 | R11: 74 | S11: 15 | T11: 3 | U11: 0.18 | V11: 0.29 | W11: 0.47 | X11: 0.92 | Y11: a | Z11: TRUE | AA11: =B11&" "&C11 -> Benjamin White
A12: 2 | B12: Cristhian | C12: Mosquera | D12: 11 | E12: 4 | F12: 54 | G12: 6 | H12: 3.8 | I12: 1 | J12: 12 | K12: 168 | L12: 0 | M12: 0 | N12: 2 | O12: 0 | P12: 0 | Q12: 0 | R12: 52 | S12: 10 | T12: 2 | U12: 0 | V12: 0.01 | W12: 0.01 | X12: 0.53 | Y12: d | Z12: TRUE | AA12: =B12&" "&C12 -> Cristhian Mosquera
A13: 3 | B13: Bukayo | C13: Saka | D13: 12 | E13: 7.3 | F13: 95 | G13: 7.3 | H13: 11.3 | I13: 1 | J13: 22 | K13: 246 | L13: 2 | M13: 0 | N13: 2 | O13: 1 | P13: 0 | Q13: 4 | R13: 95 | S13: 22 | T13: 3 | U13: 1.5 | V13: 0.35 | W13: 1.85 | X13: 0.78 | Y13: a | Z13: TRUE | AA13: =B13&" "&C13 -> Bukayo Saka
... A655: 4 | B655: Juan | C655: Angulo | D655: 651 | E655: 0 | F655: 45 | G655: 0 | H655: 0.3 | I655: 20 | J655: 0 | K655: 0 | L655: 0 | M655: 0 | N655: 0 | O655: 0 | P655: 0 | Q655: 0 | R655: 0 | S655: 0 | T655: 0 | U655: 0 | V655: 0 | W655: 0 | X655: 0 | Y655: a | Z655: TRUE | AA655: =B655&" "&C655 -> Juan Angulo

Sheet Player_Analysis
A1: Player | B1: Position | C1: Team | D1: Team Code | E1: Price | F1: Availability Status | G1: Can Select | H1: Player Eligible | I1: Minutes | J1: Minutes / 90 | K1: Start % | L1: Total Points | M1: PPG | N1: Form | O1: xG | P1: xA | Q1: xGI | R1: Points/90 | S1: xG/90 | T1: xA/90 | U1: xGI/90 | V1: Points/£m | W1: xGI/£m | X1: Fixture Score | Y1: Fixture Adjustment | Z1: Starts | AA1: Defensive Contributions | AB1: DC Potential | AC1: Bonus | AD1: BPS | AE1: Clean Sheets | AF1: Goals | AG1: Assists | AH1: Expected Goal Points / 90 | AI1: Expected Assist Points / 90 | AJ1: Expected Appearance Points / 90 | AK1: Expected DC Points / 90 | AL1: Clean Sheet Rate | AM1: Expected Clean Sheet Points / 90 | AN1: Bonus / Start | AO1: Points/90 score | AP1: xGI/90 Score | AQ1: Points/£m Score | AR1: xGI/£m Score | AS1: Start Score | AT1: Model Expected Points | AU1: Fixture Adjusted Points / 90 | AV1: Expected Points / £m | AW1: Attacking score | AX1: Defensive score | AY1: Reliability Score | AZ1: Fixture Adjusted Score | BA1: Model Score | BB1: Position Rank | BC1: Recommendation | BD1: Solver Score | BE1: Model Overall Rank | BF1: Model Position Rank | BG1: Model Score2
A2: =tblPlayers[first_name]&" "&tblPlayers[second_name] -> David Raya Martín | B2: =_xlfn.SWITCH(tblPlayers[element_type],1,"GK",2,"DEF",3,"MID",4,"FWD") -> GK | C2: =tblPlayers[team] -> 1 | D2: =INDEX(tblTeams[Column1.short_name],MATCH(C2,tblTeams[Column1.id],0)) -> ARS | E2: =INDEX(FPL_Raw_Data!$F:$F,MATCH(A2,FPL_Raw_Data!$AA:$AA,0))/10 -> 6 | F2: =tblPlayers[[#This Row],[status]] -> a | G2: =tblPlayers[[#This Row],[can_select]] -> TRUE | H2: =IF(AND(Table8[[#This Row],[Availability Status]]="a",Table8[[#This Row],[Can Select]]=TRUE),1,0) -> 1 | I2: =tblPlayers[minutes] -> 270 | J2: =Table8[[#This Row],[Minutes]]/90 -> 3 | K2: =IFERROR(Z2/(FIXTURE_ANALYSIS!$B$1-1),0) -> 1 | L2: =tblPlayers[total_points] -> 15 | M2: =tblPlayers[points_per_game] -> 5 | N2: =tblPlayers[form] -> 5 | O2: =tblPlayers[expected_goals] -> 0 | P2: =tblPlayers[expected_assists] -> 0.01 | Q2: =tblPlayers[expected_goal_involvements] -> 0.01 | R2: =IF(I2=0,0,L2/I2*90) -> 5 | S2: =IF(I2=0,0,O2/I2*90) -> 0 | T2: =IF(I2=0,0,P2/I2*90) -> 0.0033333333 | U2: =IF(I2=0,0,Q2/I2*90) -> 0.0033333333 | V2: =IF(E2=0,0,L2/E2) -> 2.5 | W2: =IF(E2=0,0,Q2/E2) -> 0.0016666667 | X2: =IFERROR(IF(OR($B2="MID",$B2="FWD"),INDEX(FIXTURE_ANALYSIS!$Q:$Q,MATCH($D2,FIXTURE_ANALYSIS!$A:$A,0)),INDEX(FIXTURE_ANALYSIS!$R:$R,MATCH($D2,FIXTURE_ANALYSIS!$A:$A,0))),1) -> 1.1808552 | Y2: =X2 -> 1.1808552 | Z2: =INDEX(FPL_Raw_Data!$T:$T,MATCH(A2,FPL_Raw_Data!$AA:$AA,0)) -> 3 | AA2: =INDEX(FPL_Raw_Data!$S:$S,MATCH(A2,FPL_Raw_Data!$AA:$AA,0)) -> 0 | AB2: =IF(B2="DEF",MIN(AA2/10,1),IF(OR(B2="MID",B2="FWD"),MIN(AA2/12,1),0)) -> 0 | AC2: =INDEX(FPL_Raw_Data!$Q:$Q,MATCH(A2,FPL_Raw_Data!$AA:$AA,0)) -> 0 | AD2: =INDEX(FPL_Raw_Data!$R:$R,MATCH(A2,FPL_Raw_Data!$AA:$AA,0)) -> 60 | AE2: =INDEX(FPL_Raw_Data!$N:$N,MATCH(A2,FPL_Raw_Data!$AA:$AA,0)) -> 2 | AF2: =INDEX(FPL_Raw_Data!$L:$L,MATCH(A2,FPL_Raw_Data!$AA:$AA,0)) -> 0 | AG2: =INDEX(FPL_Raw_Data!$M:$M,MATCH(A2,FPL_Raw_Data!$AA:$AA,0)) -> 0 | AH2: =IF(B2="GK",S2*10,IF(B2="DEF",S2*6,IF(B2="MID",S2*5,S2*4))) -> 0 | AI2: =T2*3 -> 0.01 | AJ2: =K2*2 -> 2 | AK2: =AB2*2 -> 0 | AL2: =IFERROR(AE2/Z2,0) -> 0.66666667 | AM2: =IF(OR(B2="GK",B2="DEF"),AL2*4,IF(B2="MID",AL2*1,0)) -> 2.6666667 | AN2: =IFERROR(AC2/Z2,0) -> 0 | AO2: =IFERROR(_xlfn.PERCENTRANK.INC($R$2:$R$700,R2)*100,0) -> 75.4 | AP2: =IFERROR(_xlfn.PERCENTRANK.INC($U$2:$U$700,U2)*100,0) -> 50.8 | AQ2: =IFERROR(_xlfn.PERCENTRANK.INC($V$2:$V$700,V2)*100,0) -> 91.7 | AR2: =IFERROR(_xlfn.PERCENTRANK.INC($W$2:$W$700,W2)*100,0) -> 51 | AS2: =K2*100 -> 100 | AT2: =IFERROR(INDEX(Player_Model!$BC$2:$BC$596,MATCH($A2,Player_Model!$A$2:$A$596,0)),0) -> 6.1779862 | AU2: =Table8[[#This Row],[Model Expected Points]]*Table8[[#This Row],[Fixture Adjustment]] -> 7.2953071 | AV2: =Table8[[#This Row],[Fixture Adjusted Points / 90]]/Table8[[#This Row],[Price]] -> 1.2158845 | AW2: =IF(OR(B2="MID",B2="FWD"),AVERAGE(AO2,AP2),IF(B2="DEF",AP2,0)) -> 0 | AX2: =IF(B2="GK",AVERAGE(AS2,X2),IF(B2="DEF",AVERAGE(AB2,X2),IF(B2="MID",AB2,0))) -> 50.590428 | AY2: =AS2 -> 100 | AZ2: =X2 -> 1.1808552 | BA2: =Table8[[#This Row],[Model Score2]] -> 6.1779862 | BB2: =IFERROR(INDEX(Player_Model!$BG$2:$BG$596,MATCH($A2,Player_Model!$A$2:$A$596,0)),"") -> 2 | BC2: =IF(BB2=1,"TOP PICK",IF(BB2<=5,"STRONG PICK",IF(BB2<=10,"CONSIDER","AVOID"))) -> STRONG PICK | BD2: =IF(H2=1,Table8[[#This Row],[Model Score]],-10000) -> 6.1779862 | BE2: =IFERROR(INDEX(Player_Model!$BF$2:$BF$596,MATCH($A2,Player_Model!$A$2:$A$596,0)),"") -> 38 | BF2: =IFERROR(INDEX(Player_Model!$BG$2:$BG$596,MATCH($A2,Player_Model!$A$2:$A$596,0)),"") -> 2 | BG2: =IFERROR(INDEX(Player_Model!$BE$2:$BE$596,MATCH($A2,Player_Model!$A$2:$A$596,0)),0) -> 6.1779862
A3: =tblPlayers[first_name]&" "&tblPlayers[second_name] -> Kepa Arrizabalaga Revuelta | B3: =_xlfn.SWITCH(tblPlayers[element_type],1,"GK",2,"DEF",3,"MID",4,"FWD") -> GK | C3: =tblPlayers[team] -> 1 | D3: =INDEX(tblTeams[Column1.short_name],MATCH(C3,tblTeams[Column1.id],0)) -> ARS | E3: =INDEX(FPL_Raw_Data!$F:$F,MATCH(A3,FPL_Raw_Data!$AA:$AA,0))/10 -> 4.9 | F3: =tblPlayers[[#This Row],[status]] -> a | G3: =tblPlayers[[#This Row],[can_select]] -> TRUE | H3: =IF(AND(Table8[[#This Row],[Availability Status]]="a",Table8[[#This Row],[Can Select]]=TRUE),1,0) -> 1 | I3: =tblPlayers[minutes] -> 0 | J3: =Table8[[#This Row],[Minutes]]/90 -> 0 | K3: =IFERROR(Z3/(FIXTURE_ANALYSIS!$B$1-1),0) -> 0 | L3: =tblPlayers[total_points] -> 0 | M3: =tblPlayers[points_per_game] -> 0 | N3: =tblPlayers[form] -> 0 | O3: =tblPlayers[expected_goals] -> 0 | P3: =tblPlayers[expected_assists] -> 0 | Q3: =tblPlayers[expected_goal_involvements] -> 0 | R3: =IF(I3=0,0,L3/I3*90) -> 0 | S3: =IF(I3=0,0,O3/I3*90) -> 0 | T3: =IF(I3=0,0,P3/I3*90) -> 0 | U3: =IF(I3=0,0,Q3/I3*90) -> 0 | V3: =IF(E3=0,0,L3/E3) -> 0 | W3: =IF(E3=0,0,Q3/E3) -> 0 | X3: =IFERROR(IF(OR($B3="MID",$B3="FWD"),INDEX(FIXTURE_ANALYSIS!$Q:$Q,MATCH($D3,FIXTURE_ANALYSIS!$A:$A,0)),INDEX(FIXTURE_ANALYSIS!$R:$R,MATCH($D3,FIXTURE_ANALYSIS!$A:$A,0))),1) -> 1.1808552 | Y3: =X3 -> 1.1808552 | Z3: =INDEX(FPL_Raw_Data!$T:$T,MATCH(A3,FPL_Raw_Data!$AA:$AA,0)) -> 0 | AA3: =INDEX(FPL_Raw_Data!$S:$S,MATCH(A3,FPL_Raw_Data!$AA:$AA,0)) -> 0 | AB3: =IF(B3="DEF",MIN(AA3/10,1),IF(OR(B3="MID",B3="FWD"),MIN(AA3/12,1),0)) -> 0 | AC3: =INDEX(FPL_Raw_Data!$Q:$Q,MATCH(A3,FPL_Raw_Data!$AA:$AA,0)) -> 0 | AD3: =INDEX(FPL_Raw_Data!$R:$R,MATCH(A3,FPL_Raw_Data!$AA:$AA,0)) -> 0 | AE3: =INDEX(FPL_Raw_Data!$N:$N,MATCH(A3,FPL_Raw_Data!$AA:$AA,0)) -> 0 | AF3: =INDEX(FPL_Raw_Data!$L:$L,MATCH(A3,FPL_Raw_Data!$AA:$AA,0)) -> 0 | AG3: =INDEX(FPL_Raw_Data!$M:$M,MATCH(A3,FPL_Raw_Data!$AA:$AA,0)) -> 0 | AH3: =IF(B3="GK",S3*10,IF(B3="DEF",S3*6,IF(B3="MID",S3*5,S3*4))) -> 0 | AI3: =T3*3 -> 0 | AJ3: =K3*2 -> 0 | AK3: =AB3*2 -> 0 | AL3: =IFERROR(AE3/Z3,0) -> 0 | AM3: =IF(OR(B3="GK",B3="DEF"),AL3*4,IF(B3="MID",AL3*1,0)) -> 0 | AN3: =IFERROR(AC3/Z3,0) -> 0 | AO3: =IFERROR(_xlfn.PERCENTRANK.INC($R$2:$R$700,R3)*100,0) -> 0.1 | AP3: =IFERROR(_xlfn.PERCENTRANK.INC($U$2:$U$700,U3)*100,0) -> 0 | AQ3: =IFERROR(_xlfn.PERCENTRANK.INC($V$2:$V$700,V3)*100,0) -> 0.1 | AR3: =IFERROR(_xlfn.PERCENTRANK.INC($W$2:$W$700,W3)*100,0) -> 0 | AS3: =K3*100 -> 0 | AT3: =IFERROR(INDEX(Player_Model!$BC$2:$BC$596,MATCH($A3,Player_Model!$A$2:$A$596,0)),0) -> 0 | AU3: =Table8[[#This Row],[Model Expected Points]]*Table8[[#This Row],[Fixture Adjustment]] -> 0 | AV3: =Table8[[#This Row],[Fixture Adjusted Points / 90]]/Table8[[#This Row],[Price]] -> 0 | AW3: =IF(OR(B3="MID",B3="FWD"),AVERAGE(AO3,AP3),IF(B3="DEF",AP3,0)) -> 0 | AX3: =IF(B3="GK",AVERAGE(AS3,X3),IF(B3="DEF",AVERAGE(AB3,X3),IF(B3="MID",AB3,0))) -> 0.5904276 | AY3: =AS3 -> 0 | AZ3: =X3 -> 1.1808552 | BA3: =Table8[[#This Row],[Model Score2]] -> 0 | BB3: =IFERROR(INDEX(Player_Model!$BG$2:$BG$596,MATCH($A3,Player_Model!$A$2:$A$596,0)),"") -> 22 | BC3: =IF(BB3=1,"TOP PICK",IF(BB3<=5,"STRONG PICK",IF(BB3<=10,"CONSIDER","AVOID"))) -> AVOID | BD3: =IF(H3=1,Table8[[#This Row],[Model Score]],-10000) -> 0 | BE3: =IFERROR(INDEX(Player_Model!$BF$2:$BF$596,MATCH($A3,Player_Model!$A$2:$A$596,0)),"") -> 253 | BF3: =IFERROR(INDEX(Player_Model!$BG$2:$BG$596,MATCH($A3,Player_Model!$A$2:$A$596,0)),"") -> 22 | BG3: =IFERROR(INDEX(Player_Model!$BE$2:$BE$596,MATCH($A3,Player_Model!$A$2:$A$596,0)),0) -> 0
A4: =tblPlayers[first_name]&" "&tblPlayers[second_name] -> Illan Meslier | B4: =_xlfn.SWITCH(tblPlayers[element_type],1,"GK",2,"DEF",3,"MID",4,"FWD") -> GK | C4: =tblPlayers[team] -> 1 | D4: =INDEX(tblTeams[Column1.short_name],MATCH(C4,tblTeams[Column1.id],0)) -> ARS | E4: =INDEX(FPL_Raw_Data!$F:$F,MATCH(A4,FPL_Raw_Data!$AA:$AA,0))/10 -> 4.9 | F4: =tblPlayers[[#This Row],[status]] -> a | G4: =tblPlayers[[#This Row],[can_select]] -> TRUE | H4: =IF(AND(Table8[[#This Row],[Availability Status]]="a",Table8[[#This Row],[Can Select]]=TRUE),1,0) -> 1 | I4: =tblPlayers[minutes] -> 0 | J4: =Table8[[#This Row],[Minutes]]/90 -> 0 | K4: =IFERROR(Z4/(FIXTURE_ANALYSIS!$B$1-1),0) -> 0 | L4: =tblPlayers[total_points] -> 0 | M4: =tblPlayers[points_per_game] -> 0 | N4: =tblPlayers[form] -> 0 | O4: =tblPlayers[expected_goals] -> 0 | P4: =tblPlayers[expected_assists] -> 0 | Q4: =tblPlayers[expected_goal_involvements] -> 0 | R4: =IF(I4=0,0,L4/I4*90) -> 0 | S4: =IF(I4=0,0,O4/I4*90) -> 0 | T4: =IF(I4=0,0,P4/I4*90) -> 0 | U4: =IF(I4=0,0,Q4/I4*90) -> 0 | V4: =IF(E4=0,0,L4/E4) -> 0 | W4: =IF(E4=0,0,Q4/E4) -> 0 | X4: =IFERROR(IF(OR($B4="MID",$B4="FWD"),INDEX(FIXTURE_ANALYSIS!$Q:$Q,MATCH($D4,FIXTURE_ANALYSIS!$A:$A,0)),INDEX(FIXTURE_ANALYSIS!$R:$R,MATCH($D4,FIXTURE_ANALYSIS!$A:$A,0))),1) -> 1.1808552 | Y4: =X4 -> 1.1808552 | Z4: =INDEX(FPL_Raw_Data!$T:$T,MATCH(A4,FPL_Raw_Data!$AA:$AA,0)) -> 0 | AA4: =INDEX(FPL_Raw_Data!$S:$S,MATCH(A4,FPL_Raw_Data!$AA:$AA,0)) -> 0 | AB4: =IF(B4="DEF",MIN(AA4/10,1),IF(OR(B4="MID",B4="FWD"),MIN(AA4/12,1),0)) -> 0 | AC4: =INDEX(FPL_Raw_Data!$Q:$Q,MATCH(A4,FPL_Raw_Data!$AA:$AA,0)) -> 0 | AD4: =INDEX(FPL_Raw_Data!$R:$R,MATCH(A4,FPL_Raw_Data!$AA:$AA,0)) -> 0 | AE4: =INDEX(FPL_Raw_Data!$N:$N,MATCH(A4,FPL_Raw_Data!$AA:$AA,0)) -> 0 | AF4: =INDEX(FPL_Raw_Data!$L:$L,MATCH(A4,FPL_Raw_Data!$AA:$AA,0)) -> 0 | AG4: =INDEX(FPL_Raw_Data!$M:$M,MATCH(A4,FPL_Raw_Data!$AA:$AA,0)) -> 0 | AH4: =IF(B4="GK",S4*10,IF(B4="DEF",S4*6,IF(B4="MID",S4*5,S4*4))) -> 0 | AI4: =T4*3 -> 0 | AJ4: =K4*2 -> 0 | AK4: =AB4*2 -> 0 | AL4: =IFERROR(AE4/Z4,0) -> 0 | AM4: =IF(OR(B4="GK",B4="DEF"),AL4*4,IF(B4="MID",AL4*1,0)) -> 0 | AN4: =IFERROR(AC4/Z4,0) -> 0 | AO4: =IFERROR(_xlfn.PERCENTRANK.INC($R$2:$R$700,R4)*100,0) -> 0.1 | AP4: =IFERROR(_xlfn.PERCENTRANK.INC($U$2:$U$700,U4)*100,0) -> 0 | AQ4: =IFERROR(_xlfn.PERCENTRANK.INC($V$2:$V$700,V4)*100,0) -> 0.1 | AR4: =IFERROR(_xlfn.PERCENTRANK.INC($W$2:$W$700,W4)*100,0) -> 0 | AS4: =K4*100 -> 0 | AT4: =IFERROR(INDEX(Player_Model!$BC$2:$BC$596,MATCH($A4,Player_Model!$A$2:$A$596,0)),0) -> 0 | AU4: =Table8[[#This Row],[Model Expected Points]]*Table8[[#This Row],[Fixture Adjustment]] -> 0 | AV4: =Table8[[#This Row],[Fixture Adjusted Points / 90]]/Table8[[#This Row],[Price]] -> 0 | AW4: =IF(OR(B4="MID",B4="FWD"),AVERAGE(AO4,AP4),IF(B4="DEF",AP4,0)) -> 0 | AX4: =IF(B4="GK",AVERAGE(AS4,X4),IF(B4="DEF",AVERAGE(AB4,X4),IF(B4="MID",AB4,0))) -> 0.5904276 | AY4: =AS4 -> 0 | AZ4: =X4 -> 1.1808552 | BA4: =Table8[[#This Row],[Model Score2]] -> 0 | BB4: =IFERROR(INDEX(Player_Model!$BG$2:$BG$596,MATCH($A4,Player_Model!$A$2:$A$596,0)),"") -> 23 | BC4: =IF(BB4=1,"TOP PICK",IF(BB4<=5,"STRONG PICK",IF(BB4<=10,"CONSIDER","AVOID"))) -> AVOID | BD4: =IF(H4=1,Table8[[#This Row],[Model Score]],-10000) -> 0 | BE4: =IFERROR(INDEX(Player_Model!$BF$2:$BF$596,MATCH($A4,Player_Model!$A$2:$A$596,0)),"") -> 253 | BF4: =IFERROR(INDEX(Player_Model!$BG$2:$BG$596,MATCH($A4,Player_Model!$A$2:$A$596,0)),"") -> 23 | BG4: =IFERROR(INDEX(Player_Model!$BE$2:$BE$596,MATCH($A4,Player_Model!$A$2:$A$596,0)),0) -> 0
A5: =tblPlayers[first_name]&" "&tblPlayers[second_name] -> Gabriel dos Santos Magalhães | B5: =_xlfn.SWITCH(tblPlayers[element_type],1,"GK",2,"DEF",3,"MID",4,"FWD") -> DEF | C5: =tblPlayers[team] -> 1 | D5: =INDEX(tblTeams[Column1.short_name],MATCH(C5,tblTeams[Column1.id],0)) -> ARS | E5: =INDEX(FPL_Raw_Data!$F:$F,MATCH(A5,FPL_Raw_Data!$AA:$AA,0))/10 -> 8 | F5: =tblPlayers[[#This Row],[status]] -> a | G5: =tblPlayers[[#This Row],[can_select]] -> TRUE | H5: =IF(AND(Table8[[#This Row],[Availability Status]]="a",Table8[[#This Row],[Can Select]]=TRUE),1,0) -> 1 | I5: =tblPlayers[minutes] -> 270 | J5: =Table8[[#This Row],[Minutes]]/90 -> 3 | K5: =IFERROR(Z5/(FIXTURE_ANALYSIS!$B$1-1),0) -> 1 | L5: =tblPlayers[total_points] -> 15 | M5: =tblPlayers[points_per_game] -> 5 | N5: =tblPlayers[form] -> 5 | O5: =tblPlayers[expected_goals] -> 0.49 | P5: =tblPlayers[expected_assists] -> 0.05 | Q5: =tblPlayers[expected_goal_involvements] -> 0.54 | R5: =IF(I5=0,0,L5/I5*90) -> 5 | S5: =IF(I5=0,0,O5/I5*90) -> 0.16333333 | T5: =IF(I5=0,0,P5/I5*90) -> 0.016666667 | U5: =IF(I5=0,0,Q5/I5*90) -> 0.18 | V5: =IF(E5=0,0,L5/E5) -> 1.875 | W5: =IF(E5=0,0,Q5/E5) -> 0.0675 | X5: =IFERROR(IF(OR($B5="MID",$B5="FWD"),INDEX(FIXTURE_ANALYSIS!$Q:$Q,MATCH($D5,FIXTURE_ANALYSIS!$A:$A,0)),INDEX(FIXTURE_ANALYSIS!$R:$R,MATCH($D5,FIXTURE_ANALYSIS!$A:$A,0))),1) -> 1.1808552 | Y5: =X5 -> 1.1808552 | Z5: =INDEX(FPL_Raw_Data!$T:$T,MATCH(A5,FPL_Raw_Data!$AA:$AA,0)) -> 3 | AA5: =INDEX(FPL_Raw_Data!$S:$S,MATCH(A5,FPL_Raw_Data!$AA:$AA,0)) -> 21 | AB5: =IF(B5="DEF",MIN(AA5/10,1),IF(OR(B5="MID",B5="FWD"),MIN(AA5/12,1),0)) -> 1 | AC5: =INDEX(FPL_Raw_Data!$Q:$Q,MATCH(A5,FPL_Raw_Data!$AA:$AA,0)) -> 0 | AD5: =INDEX(FPL_Raw_Data!$R:$R,MATCH(A5,FPL_Raw_Data!$AA:$AA,0)) -> 54 | AE5: =INDEX(FPL_Raw_Data!$N:$N,MATCH(A5,FPL_Raw_Data!$AA:$AA,0)) -> 2 | AF5: =INDEX(FPL_Raw_Data!$L:$L,MATCH(A5,FPL_Raw_Data!$AA:$AA,0)) -> 0 | AG5: =INDEX(FPL_Raw_Data!$M:$M,MATCH(A5,FPL_Raw_Data!$AA:$AA,0)) -> 0 | AH5: =IF(B5="GK",S5*10,IF(B5="DEF",S5*6,IF(B5="MID",S5*5,S5*4))) -> 0.98 | AI5: =T5*3 -> 0.05 | AJ5: =K5*2 -> 2 | AK5: =AB5*2 -> 2 | AL5: =IFERROR(AE5/Z5,0) -> 0.66666667 | AM5: =IF(OR(B5="GK",B5="DEF"),AL5*4,IF(B5="MID",AL5*1,0)) -> 2.6666667 | AN5: =IFERROR(AC5/Z5,0) -> 0 | AO5: =IFERROR(_xlfn.PERCENTRANK.INC($R$2:$R$700,R5)*100,0) -> 75.4 | AP5: =IFERROR(_xlfn.PERCENTRANK.INC($U$2:$U$700,U5)*100,0) -> 74.7 | AQ5: =IFERROR(_xlfn.PERCENTRANK.INC($V$2:$V$700,V5)*100,0) -> 85.3 | AR5: =IFERROR(_xlfn.PERCENTRANK.INC($W$2:$W$700,W5)*100,0) -> 79.6 | AS5: =K5*100 -> 100 | AT5: =IFERROR(INDEX(Player_Model!$BC$2:$BC$596,MATCH($A5,Player_Model!$A$2:$A$596,0)),0) -> 8.1528293 | AU5: =Table8[[#This Row],[Model Expected Points]]*Table8[[#This Row],[Fixture Adjustment]] -> 9.6273109 | AV5: =Table8[[#This Row],[Fixture Adjusted Points / 90]]/Table8[[#This Row],[Price]] -> 1.2034139 | AW5: =IF(OR(B5="MID",B5="FWD"),AVERAGE(AO5,AP5),IF(B5="DEF",AP5,0)) -> 74.7 | AX5: =IF(B5="GK",AVERAGE(AS5,X5),IF(B5="DEF",AVERAGE(AB5,X5),IF(B5="MID",AB5,0))) -> 1.0904276 | AY5: =AS5 -> 100 | AZ5: =X5 -> 1.1808552 | BA5: =Table8[[#This Row],[Model Score2]] -> 8.1528293 | BB5: =IFERROR(INDEX(Player_Model!$BG$2:$BG$596,MATCH($A5,Player_Model!$A$2:$A$596,0)),"") -> 6 | BC5: =IF(BB5=1,"TOP PICK",IF(BB5<=5,"STRONG PICK",IF(BB5<=10,"CONSIDER","AVOID"))) -> CONSIDER | BD5: =IF(H5=1,Table8[[#This Row],[Model Score]],-10000) -> 8.1528293 | BE5: =IFERROR(INDEX(Player_Model!$BF$2:$BF$596,MATCH($A5,Player_Model!$A$2:$A$596,0)),"") -> 7 | BF5: =IFERROR(INDEX(Player_Model!$BG$2:$BG$596,MATCH($A5,Player_Model!$A$2:$A$596,0)),"") -> 6 | BG5: =IFERROR(INDEX(Player_Model!$BE$2:$BE$596,MATCH($A5,Player_Model!$A$2:$A$596,0)),0) -> 8.1528293
A6: =tblPlayers[first_name]&" "&tblPlayers[second_name] -> Jurriën Timber | B6: =_xlfn.SWITCH(tblPlayers[element_type],1,"GK",2,"DEF",3,"MID",4,"FWD") -> DEF | C6: =tblPlayers[team] -> 1 | D6: =INDEX(tblTeams[Column1.short_name],MATCH(C6,tblTeams[Column1.id],0)) -> ARS | E6: =INDEX(FPL_Raw_Data!$F:$F,MATCH(A6,FPL_Raw_Data!$AA:$AA,0))/10 -> 6.5 | F6: =tblPlayers[[#This Row],[status]] -> d | G6: =tblPlayers[[#This Row],[can_select]] -> TRUE | H6: =IF(AND(Table8[[#This Row],[Availability Status]]="a",Table8[[#This Row],[Can Select]]=TRUE),1,0) -> 0 | I6: =tblPlayers[minutes] -> 0 | J6: =Table8[[#This Row],[Minutes]]/90 -> 0 | K6: =IFERROR(Z6/(FIXTURE_ANALYSIS!$B$1-1),0) -> 0 | L6: =tblPlayers[total_points] -> 0 | M6: =tblPlayers[points_per_game] -> 0 | N6: =tblPlayers[form] -> 0 | O6: =tblPlayers[expected_goals] -> 0 | P6: =tblPlayers[expected_assists] -> 0 | Q6: =tblPlayers[expected_goal_involvements] -> 0 | R6: =IF(I6=0,0,L6/I6*90) -> 0 | S6: =IF(I6=0,0,O6/I6*90) -> 0 | T6: =IF(I6=0,0,P6/I6*90) -> 0 | U6: =IF(I6=0,0,Q6/I6*90) -> 0 | V6: =IF(E6=0,0,L6/E6) -> 0 | W6: =IF(E6=0,0,Q6/E6) -> 0 | X6: =IFERROR(IF(OR($B6="MID",$B6="FWD"),INDEX(FIXTURE_ANALYSIS!$Q:$Q,MATCH($D6,FIXTURE_ANALYSIS!$A:$A,0)),INDEX(FIXTURE_ANALYSIS!$R:$R,MATCH($D6,FIXTURE_ANALYSIS!$A:$A,0))),1) -> 1.1808552 | Y6: =X6 -> 1.1808552 | Z6: =INDEX(FPL_Raw_Data!$T:$T,MATCH(A6,FPL_Raw_Data!$AA:$AA,0)) -> 0 | AA6: =INDEX(FPL_Raw_Data!$S:$S,MATCH(A6,FPL_Raw_Data!$AA:$AA,0)) -> 0 | AB6: =IF(B6="DEF",MIN(AA6/10,1),IF(OR(B6="MID",B6="FWD"),MIN(AA6/12,1),0)) -> 0 | AC6: =INDEX(FPL_Raw_Data!$Q:$Q,MATCH(A6,FPL_Raw_Data!$AA:$AA,0)) -> 0 | AD6: =INDEX(FPL_Raw_Data!$R:$R,MATCH(A6,FPL_Raw_Data!$AA:$AA,0)) -> 0 | AE6: =INDEX(FPL_Raw_Data!$N:$N,MATCH(A6,FPL_Raw_Data!$AA:$AA,0)) -> 0 | AF6: =INDEX(FPL_Raw_Data!$L:$L,MATCH(A6,FPL_Raw_Data!$AA:$AA,0)) -> 0 | AG6: =INDEX(FPL_Raw_Data!$M:$M,MATCH(A6,FPL_Raw_Data!$AA:$AA,0)) -> 0 | AH6: =IF(B6="GK",S6*10,IF(B6="DEF",S6*6,IF(B6="MID",S6*5,S6*4))) -> 0 | AI6: =T6*3 -> 0 | AJ6: =K6*2 -> 0 | AK6: =AB6*2 -> 0 | AL6: =IFERROR(AE6/Z6,0) -> 0 | AM6: =IF(OR(B6="GK",B6="DEF"),AL6*4,IF(B6="MID",AL6*1,0)) -> 0 | AN6: =IFERROR(AC6/Z6,0) -> 0 | AO6: =IFERROR(_xlfn.PERCENTRANK.INC($R$2:$R$700,R6)*100,0) -> 0.1 | AP6: =IFERROR(_xlfn.PERCENTRANK.INC($U$2:$U$700,U6)*100,0) -> 0 | AQ6: =IFERROR(_xlfn.PERCENTRANK.INC($V$2:$V$700,V6)*100,0) -> 0.1 | AR6: =IFERROR(_xlfn.PERCENTRANK.INC($W$2:$W$700,W6)*100,0) -> 0 | AS6: =K6*100 -> 0 | AT6: =IFERROR(INDEX(Player_Model!$BC$2:$BC$596,MATCH($A6,Player_Model!$A$2:$A$596,0)),0) -> -0.1968092 | AU6: =Table8[[#This Row],[Model Expected Points]]*Table8[[#This Row],[Fixture Adjustment]] -> -0.23240317 | AV6: =Table8[[#This Row],[Fixture Adjusted Points / 90]]/Table8[[#This Row],[Price]] -> -0.035754333 | AW6: =IF(OR(B6="MID",B6="FWD"),AVERAGE(AO6,AP6),IF(B6="DEF",AP6,0)) -> 0 | AX6: =IF(B6="GK",AVERAGE(AS6,X6),IF(B6="DEF",AVERAGE(AB6,X6),IF(B6="MID",AB6,0))) -> 0.5904276 | AY6: =AS6 -> 0 | AZ6: =X6 -> 1.1808552 | BA6: =Table8[[#This Row],[Model Score2]] -> -0.1968092 | BB6: =IFERROR(INDEX(Player_Model!$BG$2:$BG$596,MATCH($A6,Player_Model!$A$2:$A$596,0)),"") -> 105 | BC6: =IF(BB6=1,"TOP PICK",IF(BB6<=5,"STRONG PICK",IF(BB6<=10,"CONSIDER","AVOID"))) -> AVOID | BD6: =IF(H6=1,Table8[[#This Row],[Model Score]],-10000) -> -10000 | BE6: =IFERROR(INDEX(Player_Model!$BF$2:$BF$596,MATCH($A6,Player_Model!$A$2:$A$596,0)),"") -> 508 | BF6: =IFERROR(INDEX(Player_Model!$BG$2:$BG$596,MATCH($A6,Player_Model!$A$2:$A$596,0)),"") -> 105 | BG6: =IFERROR(INDEX(Player_Model!$BE$2:$BE$596,MATCH($A6,Player_Model!$A$2:$A$596,0)),0) -> -0.1968092
A7: =tblPlayers[first_name]&" "&tblPlayers[second_name] -> William Saliba | B7: =_xlfn.SWITCH(tblPlayers[element_type],1,"GK",2,"DEF",3,"MID",4,"FWD") -> DEF | C7: =tblPlayers[team] -> 1 | D7: =INDEX(tblTeams[Column1.short_name],MATCH(C7,tblTeams[Column1.id],0)) -> ARS | E7: =INDEX(FPL_Raw_Data!$F:$F,MATCH(A7,FPL_Raw_Data!$AA:$AA,0))/10 -> 6 | F7: =tblPlayers[[#This Row],[status]] -> i | G7: =tblPlayers[[#This Row],[can_select]] -> TRUE | H7: =IF(AND(Table8[[#This Row],[Availability Status]]="a",Table8[[#This Row],[Can Select]]=TRUE),1,0) -> 0 | I7: =tblPlayers[minutes] -> 0 | J7: =Table8[[#This Row],[Minutes]]/90 -> 0 | K7: =IFERROR(Z7/(FIXTURE_ANALYSIS!$B$1-1),0) -> 0 | L7: =tblPlayers[total_points] -> 0 | M7: =tblPlayers[points_per_game] -> 0 | N7: =tblPlayers[form] -> 0 | O7: =tblPlayers[expected_goals] -> 0 | P7: =tblPlayers[expected_assists] -> 0 | Q7: =tblPlayers[expected_goal_involvements] -> 0 | R7: =IF(I7=0,0,L7/I7*90) -> 0 | S7: =IF(I7=0,0,O7/I7*90) -> 0 | T7: =IF(I7=0,0,P7/I7*90) -> 0 | U7: =IF(I7=0,0,Q7/I7*90) -> 0 | V7: =IF(E7=0,0,L7/E7) -> 0 | W7: =IF(E7=0,0,Q7/E7) -> 0 | X7: =IFERROR(IF(OR($B7="MID",$B7="FWD"),INDEX(FIXTURE_ANALYSIS!$Q:$Q,MATCH($D7,FIXTURE_ANALYSIS!$A:$A,0)),INDEX(FIXTURE_ANALYSIS!$R:$R,MATCH($D7,FIXTURE_ANALYSIS!$A:$A,0))),1) -> 1.1808552 | Y7: =X7 -> 1.1808552 | Z7: =INDEX(FPL_Raw_Data!$T:$T,MATCH(A7,FPL_Raw_Data!$AA:$AA,0)) -> 0 | AA7: =INDEX(FPL_Raw_Data!$S:$S,MATCH(A7,FPL_Raw_Data!$AA:$AA,0)) -> 0 | AB7: =IF(B7="DEF",MIN(AA7/10,1),IF(OR(B7="MID",B7="FWD"),MIN(AA7/12,1),0)) -> 0 | AC7: =INDEX(FPL_Raw_Data!$Q:$Q,MATCH(A7,FPL_Raw_Data!$AA:$AA,0)) -> 0 | AD7: =INDEX(FPL_Raw_Data!$R:$R,MATCH(A7,FPL_Raw_Data!$AA:$AA,0)) -> 0 | AE7: =INDEX(FPL_Raw_Data!$N:$N,MATCH(A7,FPL_Raw_Data!$AA:$AA,0)) -> 0 | AF7: =INDEX(FPL_Raw_Data!$L:$L,MATCH(A7,FPL_Raw_Data!$AA:$AA,0)) -> 0 | AG7: =INDEX(FPL_Raw_Data!$M:$M,MATCH(A7,FPL_Raw_Data!$AA:$AA,0)) -> 0 | AH7: =IF(B7="GK",S7*10,IF(B7="DEF",S7*6,IF(B7="MID",S7*5,S7*4))) -> 0 | AI7: =T7*3 -> 0 | AJ7: =K7*2 -> 0 | AK7: =AB7*2 -> 0 | AL7: =IFERROR(AE7/Z7,0) -> 0 | AM7: =IF(OR(B7="GK",B7="DEF"),AL7*4,IF(B7="MID",AL7*1,0)) -> 0 | AN7: =IFERROR(AC7/Z7,0) -> 0 | AO7: =IFERROR(_xlfn.PERCENTRANK.INC($R$2:$R$700,R7)*100,0) -> 0.1 | AP7: =IFERROR(_xlfn.PERCENTRANK.INC($U$2:$U$700,U7)*100,0) -> 0 | AQ7: =IFERROR(_xlfn.PERCENTRANK.INC($V$2:$V$700,V7)*100,0) -> 0.1 | AR7: =IFERROR(_xlfn.PERCENTRANK.INC($W$2:$W$700,W7)*100,0) -> 0 | AS7: =K7*100 -> 0 | AT7: =IFERROR(INDEX(Player_Model!$BC$2:$BC$596,MATCH($A7,Player_Model!$A$2:$A$596,0)),0) -> -0.1968092 | AU7: =Table8[[#This Row],[Model Expected Points]]*Table8[[#This Row],[Fixture Adjustment]] -> -0.23240317 | AV7: =Table8[[#This Row],[Fixture Adjusted Points / 90]]/Table8[[#This Row],[Price]] -> -0.038733861 | AW7: =IF(OR(B7="MID",B7="FWD"),AVERAGE(AO7,AP7),IF(B7="DEF",AP7,0)) -> 0 | AX7: =IF(B7="GK",AVERAGE(AS7,X7),IF(B7="DEF",AVERAGE(AB7,X7),IF(B7="MID",AB7,0))) -> 0.5904276 | AY7: =AS7 -> 0 | AZ7: =X7 -> 1.1808552 | BA7: =Table8[[#This Row],[Model Score2]] -> -0.1968092 | BB7: =IFERROR(INDEX(Player_Model!$BG$2:$BG$596,MATCH($A7,Player_Model!$A$2:$A$596,0)),"") -> 106 | BC7: =IF(BB7=1,"TOP PICK",IF(BB7<=5,"STRONG PICK",IF(BB7<=10,"CONSIDER","AVOID"))) -> AVOID | BD7: =IF(H7=1,Table8[[#This Row],[Model Score]],-10000) -> -10000 | BE7: =IFERROR(INDEX(Player_Model!$BF$2:$BF$596,MATCH($A7,Player_Model!$A$2:$A$596,0)),"") -> 508 | BF7: =IFERROR(INDEX(Player_Model!$BG$2:$BG$596,MATCH($A7,Player_Model!$A$2:$A$596,0)),"") -> 106 | BG7: =IFERROR(INDEX(Player_Model!$BE$2:$BE$596,MATCH($A7,Player_Model!$A$2:$A$596,0)),0) -> -0.1968092
A8: =tblPlayers[first_name]&" "&tblPlayers[second_name] -> Myles Lewis-Skelly | B8: =_xlfn.SWITCH(tblPlayers[element_type],1,"GK",2,"DEF",3,"MID",4,"FWD") -> MID | C8: =tblPlayers[team] -> 1 | D8: =INDEX(tblTeams[Column1.short_name],MATCH(C8,tblTeams[Column1.id],0)) -> ARS | E8: =INDEX(FPL_Raw_Data!$F:$F,MATCH(A8,FPL_Raw_Data!$AA:$AA,0))/10 -> 5.5 | F8: =tblPlayers[[#This Row],[status]] -> a | G8: =tblPlayers[[#This Row],[can_select]] -> TRUE | H8: =IF(AND(Table8[[#This Row],[Availability Status]]="a",Table8[[#This Row],[Can Select]]=TRUE),1,0) -> 1 | I8: =tblPlayers[minutes] -> 226 | J8: =Table8[[#This Row],[Minutes]]/90 -> 2.5111111 | K8: =IFERROR(Z8/(FIXTURE_ANALYSIS!$B$1-1),0) -> 1 | L8: =tblPlayers[total_points] -> 8 | M8: =tblPlayers[points_per_game] -> 2.7 | N8: =tblPlayers[form] -> 2.7 | O8: =tblPlayers[expected_goals] -> 0.16 | P8: =tblPlayers[expected_assists] -> 0.23 | Q8: =tblPlayers[expected_goal_involvements] -> 0.39 | R8: =IF(I8=0,0,L8/I8*90) -> 3.1858407 | S8: =IF(I8=0,0,O8/I8*90) -> 0.063716814 | T8: =IF(I8=0,0,P8/I8*90) -> 0.09159292 | U8: =IF(I8=0,0,Q8/I8*90) -> 0.15530973 | V8: =IF(E8=0,0,L8/E8) -> 1.4545455 | W8: =IF(E8=0,0,Q8/E8) -> 0.070909091 | X8: =IFERROR(IF(OR($B8="MID",$B8="FWD"),INDEX(FIXTURE_ANALYSIS!$Q:$Q,MATCH($D8,FIXTURE_ANALYSIS!$A:$A,0)),INDEX(FIXTURE_ANALYSIS!$R:$R,MATCH($D8,FIXTURE_ANALYSIS!$A:$A,0))),1) -> 1.0430363 | Y8: =X8 -> 1.0430363 | Z8: =INDEX(FPL_Raw_Data!$T:$T,MATCH(A8,FPL_Raw_Data!$AA:$AA,0)) -> 3 | AA8: =INDEX(FPL_Raw_Data!$S:$S,MATCH(A8,FPL_Raw_Data!$AA:$AA,0)) -> 14 | AB8: =IF(B8="DEF",MIN(AA8/10,1),IF(OR(B8="MID",B8="FWD"),MIN(AA8/12,1),0)) -> 1 | AC8: =INDEX(FPL_Raw_Data!$Q:$Q,MATCH(A8,FPL_Raw_Data!$AA:$AA,0)) -> 0 | AD8: =INDEX(FPL_Raw_Data!$R:$R,MATCH(A8,FPL_Raw_Data!$AA:$AA,0)) -> 35 | AE8: =INDEX(FPL_Raw_Data!$N:$N,MATCH(A8,FPL_Raw_Data!$AA:$AA,0)) -> 2 | AF8: =INDEX(FPL_Raw_Data!$L:$L,MATCH(A8,FPL_Raw_Data!$AA:$AA,0)) -> 0 | AG8: =INDEX(FPL_Raw_Data!$M:$M,MATCH(A8,FPL_Raw_Data!$AA:$AA,0)) -> 0 | AH8: =IF(B8="GK",S8*10,IF(B8="DEF",S8*6,IF(B8="MID",S8*5,S8*4))) -> 0.31858407 | AI8: =T8*3 -> 0.27477876 | AJ8: =K8*2 -> 2 | AK8: =AB8*2 -> 2 | AL8: =IFERROR(AE8/Z8,0) -> 0.66666667 | AM8: =IF(OR(B8="GK",B8="DEF"),AL8*4,IF(B8="MID",AL8*1,0)) -> 0.66666667 | AN8: =IFERROR(AC8/Z8,0) -> 0 | AO8: =IFERROR(_xlfn.PERCENTRANK.INC($R$2:$R$700,R8)*100,0) -> 61.4 | AP8: =IFERROR(_xlfn.PERCENTRANK.INC($U$2:$U$700,U8)*100,0) -> 72.8 | AQ8: =IFERROR(_xlfn.PERCENTRANK.INC($V$2:$V$700,V8)*100,0) -> 77.2 | AR8: =IFERROR(_xlfn.PERCENTRANK.INC($W$2:$W$700,W8)*100,0) -> 80.4 | AS8: =K8*100 -> 100 | AT8: =IFERROR(INDEX(Player_Model!$BC$2:$BC$596,MATCH($A8,Player_Model!$A$2:$A$596,0)),0) -> 4.2470161 | AU8: =Table8[[#This Row],[Model Expected Points]]*Table8[[#This Row],[Fixture Adjustment]] -> 4.4297921 | AV8: =Table8[[#This Row],[Fixture Adjusted Points / 90]]/Table8[[#This Row],[Price]] -> 0.80541674 | AW8: =IF(OR(B8="MID",B8="FWD"),AVERAGE(AO8,AP8),IF(B8="DEF",AP8,0)) -> 67.1 | AX8: =IF(B8="GK",AVERAGE(AS8,X8),IF(B8="DEF",AVERAGE(AB8,X8),IF(B8="MID",AB8,0))) -> 1 | AY8: =AS8 -> 100 | AZ8: =X8 -> 1.0430363 | BA8: =Table8[[#This Row],[Model Score2]] -> 4.2470161 | BB8: =IFERROR(INDEX(Player_Model!$BG$2:$BG$596,MATCH($A8,Player_Model!$A$2:$A$596,0)),"") -> 69 | BC8: =IF(BB8=1,"TOP PICK",IF(BB8<=5,"STRONG PICK",IF(BB8<=10,"CONSIDER","AVOID"))) -> AVOID | BD8: =IF(H8=1,Table8[[#This Row],[Model Score]],-10000) -> 4.2470161 | BE8: =IFERROR(INDEX(Player_Model!$BF$2:$BF$596,MATCH($A8,Player_Model!$A$2:$A$596,0)),"") -> 140 | BF8: =IFERROR(INDEX(Player_Model!$BG$2:$BG$596,MATCH($A8,Player_Model!$A$2:$A$596,0)),"") -> 69 | BG8: =IFERROR(INDEX(Player_Model!$BE$2:$BE$596,MATCH($A8,Player_Model!$A$2:$A$596,0)),0) -> 4.2470161
A9: =tblPlayers[first_name]&" "&tblPlayers[second_name] -> Riccardo Calafiori | B9: =_xlfn.SWITCH(tblPlayers[element_type],1,"GK",2,"DEF",3,"MID",4,"FWD") -> DEF | C9: =tblPlayers[team] -> 1 | D9: =INDEX(tblTeams[Column1.short_name],MATCH(C9,tblTeams[Column1.id],0)) -> ARS | E9: =INDEX(FPL_Raw_Data!$F:$F,MATCH(A9,FPL_Raw_Data!$AA:$AA,0))/10 -> 5.7 | F9: =tblPlayers[[#This Row],[status]] -> a | G9: =tblPlayers[[#This Row],[can_select]] -> TRUE | H9: =IF(AND(Table8[[#This Row],[Availability Status]]="a",Table8[[#This Row],[Can Select]]=TRUE),1,0) -> 1 | I9: =tblPlayers[minutes] -> 236 | J9: =Table8[[#This Row],[Minutes]]/90 -> 2.6222222 | K9: =IFERROR(Z9/(FIXTURE_ANALYSIS!$B$1-1),0) -> 1 | L9: =tblPlayers[total_points] -> 22 | M9: =tblPlayers[points_per_game] -> 7.3 | N9: =tblPlayers[form] -> 7.3 | O9: =tblPlayers[expected_goals] -> 0.54 | P9: =tblPlayers[expected_assists] -> 0.58 | Q9: =tblPlayers[expected_goal_involvements] -> 1.12 | R9: =IF(I9=0,0,L9/I9*90) -> 8.3898305 | S9: =IF(I9=0,0,O9/I9*90) -> 0.2059322 | T9: =IF(I9=0,0,P9/I9*90) -> 0.22118644 | U9: =IF(I9=0,0,Q9/I9*90) -> 0.42711864 | V9: =IF(E9=0,0,L9/E9) -> 3.8596491 | W9: =IF(E9=0,0,Q9/E9) -> 0.19649123 | X9: =IFERROR(IF(OR($B9="MID",$B9="FWD"),INDEX(FIXTURE_ANALYSIS!$Q:$Q,MATCH($D9,FIXTURE_ANALYSIS!$A:$A,0)),INDEX(FIXTURE_ANALYSIS!$R:$R,MATCH($D9,FIXTURE_ANALYSIS!$A:$A,0))),1) -> 1.1808552 | Y9: =X9 -> 1.1808552 | Z9: =INDEX(FPL_Raw_Data!$T:$T,MATCH(A9,FPL_Raw_Data!$AA:$AA,0)) -> 3 | AA9: =INDEX(FPL_Raw_Data!$S:$S,MATCH(A9,FPL_Raw_Data!$AA:$AA,0)) -> 9 | AB9: =IF(B9="DEF",MIN(AA9/10,1),IF(OR(B9="MID",B9="FWD"),MIN(AA9/12,1),0)) -> 0.9 | AC9: =INDEX(FPL_Raw_Data!$Q:$Q,MATCH(A9,FPL_Raw_Data!$AA:$AA,0)) -> 2 | AD9: =INDEX(FPL_Raw_Data!$R:$R,MATCH(A9,FPL_Raw_Data!$AA:$AA,0)) -> 61 | AE9: =INDEX(FPL_Raw_Data!$N:$N,MATCH(A9,FPL_Raw_Data!$AA:$AA,0)) -> 2 | AF9: =INDEX(FPL_Raw_Data!$L:$L,MATCH(A9,FPL_Raw_Data!$AA:$AA,0)) -> 0 | AG9: =INDEX(FPL_Raw_Data!$M:$M,MATCH(A9,FPL_Raw_Data!$AA:$AA,0)) -> 2 | AH9: =IF(B9="GK",S9*10,IF(B9="DEF",S9*6,IF(B9="MID",S9*5,S9*4))) -> 1.2355932 | AI9: =T9*3 -> 0.66355932 | AJ9: =K9*2 -> 2 | AK9: =AB9*2 -> 1.8 | AL9: =IFERROR(AE9/Z9,0) -> 0.66666667 | AM9: =IF(OR(B9="GK",B9="DEF"),AL9*4,IF(B9="MID",AL9*1,0)) -> 2.6666667 | AN9: =IFERROR(AC9/Z9,0) -> 0.66666667 | AO9: =IFERROR(_xlfn.PERCENTRANK.INC($R$2:$R$700,R9)*100,0) -> 90.5 | AP9: =IFERROR(_xlfn.PERCENTRANK.INC($U$2:$U$700,U9)*100,0) -> 89.5 | AQ9: =IFERROR(_xlfn.PERCENTRANK.INC($V$2:$V$700,V9)*100,0) -> 98.1 | AR9: =IFERROR(_xlfn.PERCENTRANK.INC($W$2:$W$700,W9)*100,0) -> 94.4 | AS9: =K9*100 -> 100 | AT9: =IFERROR(INDEX(Player_Model!$BC$2:$BC$596,MATCH($A9,Player_Model!$A$2:$A$596,0)),0) -> 8.1388646 | AU9: =Table8[[#This Row],[Model Expected Points]]*Table8[[#This Row],[Fixture Adjustment]] -> 9.6108206 | AV9: =Table8[[#This Row],[Fixture Adjusted Points / 90]]/Table8[[#This Row],[Price]] -> 1.6861089 | AW9: =IF(OR(B9="MID",B9="FWD"),AVERAGE(AO9,AP9),IF(B9="DEF",AP9,0)) -> 89.5 | AX9: =IF(B9="GK",AVERAGE(AS9,X9),IF(B9="DEF",AVERAGE(AB9,X9),IF(B9="MID",AB9,0))) -> 1.0404276 | AY9: =AS9 -> 100 | AZ9: =X9 -> 1.1808552 | BA9: =Table8[[#This Row],[Model Score2]] -> 8.1388646 | BB9: =IFERROR(INDEX(Player_Model!$BG$2:$BG$596,MATCH($A9,Player_Model!$A$2:$A$596,0)),"") -> 8 | BC9: =IF(BB9=1,"TOP PICK",IF(BB9<=5,"STRONG PICK",IF(BB9<=10,"CONSIDER","AVOID"))) -> CONSIDER | BD9: =IF(H9=1,Table8[[#This Row],[Model Score]],-10000) -> 8.1388646 | BE9: =IFERROR(INDEX(Player_Model!$BF$2:$BF$596,MATCH($A9,Player_Model!$A$2:$A$596,0)),"") -> 9 | BF9: =IFERROR(INDEX(Player_Model!$BG$2:$BG$596,MATCH($A9,Player_Model!$A$2:$A$596,0)),"") -> 8 | BG9: =IFERROR(INDEX(Player_Model!$BE$2:$BE$596,MATCH($A9,Player_Model!$A$2:$A$596,0)),0) -> 8.1388646
A10: =tblPlayers[first_name]&" "&tblPlayers[second_name] -> Piero Hincapié | B10: =_xlfn.SWITCH(tblPlayers[element_type],1,"GK",2,"DEF",3,"MID",4,"FWD") -> DEF | C10: =tblPlayers[team] -> 1 | D10: =INDEX(tblTeams[Column1.short_name],MATCH(C10,tblTeams[Column1.id],0)) -> ARS | E10: =INDEX(FPL_Raw_Data!$F:$F,MATCH(A10,FPL_Raw_Data!$AA:$AA,0))/10 -> 5.3 | F10: =tblPlayers[[#This Row],[status]] -> a | G10: =tblPlayers[[#This Row],[can_select]] -> TRUE | H10: =IF(AND(Table8[[#This Row],[Availability Status]]="a",Table8[[#This Row],[Can Select]]=TRUE),1,0) -> 1 | I10: =tblPlayers[minutes] -> 32 | J10: =Table8[[#This Row],[Minutes]]/90 -> 0.35555556 | K10: =IFERROR(Z10/(FIXTURE_ANALYSIS!$B$1-1),0) -> 0 | L10: =tblPlayers[total_points] -> 2 | M10: =tblPlayers[points_per_game] -> 1 | N10: =tblPlayers[form] -> 0.7 | O10: =tblPlayers[expected_goals] -> 0 | P10: =tblPlayers[expected_assists] -> 0 | Q10: =tblPlayers[expected_goal_involvements] -> 0 | R10: =IF(I10=0,0,L10/I10*90) -> 5.625 | S10: =IF(I10=0,0,O10/I10*90) -> 0 | T10: =IF(I10=0,0,P10/I10*90) -> 0 | U10: =IF(I10=0,0,Q10/I10*90) -> 0 | V10: =IF(E10=0,0,L10/E10) -> 0.37735849 | W10: =IF(E10=0,0,Q10/E10) -> 0 | X10: =IFERROR(IF(OR($B10="MID",$B10="FWD"),INDEX(FIXTURE_ANALYSIS!$Q:$Q,MATCH($D10,FIXTURE_ANALYSIS!$A:$A,0)),INDEX(FIXTURE_ANALYSIS!$R:$R,MATCH($D10,FIXTURE_ANALYSIS!$A:$A,0))),1) -> 1.1808552 | Y10: =X10 -> 1.1808552 | Z10: =INDEX(FPL_Raw_Data!$T:$T,MATCH(A10,FPL_Raw_Data!$AA:$AA,0)) -> 0 | AA10: =INDEX(FPL_Raw_Data!$S:$S,MATCH(A10,FPL_Raw_Data!$AA:$AA,0)) -> 3 | AB10: =IF(B10="DEF",MIN(AA10/10,1),IF(OR(B10="MID",B10="FWD"),MIN(AA10/12,1),0)) -> 0.3 | AC10: =INDEX(FPL_Raw_Data!$Q:$Q,MATCH(A10,FPL_Raw_Data!$AA:$AA,0)) -> 0 | AD10: =INDEX(FPL_Raw_Data!$R:$R,MATCH(A10,FPL_Raw_Data!$AA:$AA,0)) -> 6 | AE10: =INDEX(FPL_Raw_Data!$N:$N,MATCH(A10,FPL_Raw_Data!$AA:$AA,0)) -> 0 | AF10: =INDEX(FPL_Raw_Data!$L:$L,MATCH(A10,FPL_Raw_Data!$AA:$AA,0)) -> 0 | AG10: =INDEX(FPL_Raw_Data!$M:$M,MATCH(A10,FPL_Raw_Data!$AA:$AA,0)) -> 0 | AH10: =IF(B10="GK",S10*10,IF(B10="DEF",S10*6,IF(B10="MID",S10*5,S10*4))) -> 0 | AI10: =T10*3 -> 0 | AJ10: =K10*2 -> 0 | AK10: =AB10*2 -> 0.6 | AL10: =IFERROR(AE10/Z10,0) -> 0 | AM10: =IF(OR(B10="GK",B10="DEF"),AL10*4,IF(B10="MID",AL10*1,0)) -> 0 | AN10: =IFERROR(AC10/Z10,0) -> 0 | AO10: =IFERROR(_xlfn.PERCENTRANK.INC($R$2:$R$700,R10)*100,0) -> 79.2 | AP10: =IFERROR(_xlfn.PERCENTRANK.INC($U$2:$U$700,U10)*100,0) -> 0 | AQ10: =IFERROR(_xlfn.PERCENTRANK.INC($V$2:$V$700,V10)*100,0) -> 53.1 | AR10: =IFERROR(_xlfn.PERCENTRANK.INC($W$2:$W$700,W10)*100,0) -> 0 | AS10: =K10*100 -> 0 | AT10: =IFERROR(INDEX(Player_Model!$BC$2:$BC$596,MATCH($A10,Player_Model!$A$2:$A$596,0)),0) -> -0.1968092 | AU10: =Table8[[#This Row],[Model Expected Points]]*Table8[[#This Row],[Fixture Adjustment]] -> -0.23240317 | AV10: =Table8[[#This Row],[Fixture Adjusted Points / 90]]/Table8[[#This Row],[Price]] -> -0.043849654 | AW10: =IF(OR(B10="MID",B10="FWD"),AVERAGE(AO10,AP10),IF(B10="DEF",AP10,0)) -> 0 | AX10: =IF(B10="GK",AVERAGE(AS10,X10),IF(B10="DEF",AVERAGE(AB10,X10),IF(B10="MID",AB10,0))) -> 0.7404276 | AY10: =AS10 -> 0 | AZ10: =X10 -> 1.1808552 | BA10: =Table8[[#This Row],[Model Score2]] -> -0.1968092 | BB10: =IFERROR(INDEX(Player_Model!$BG$2:$BG$596,MATCH($A10,Player_Model!$A$2:$A$596,0)),"") -> 107 | BC10: =IF(BB10=1,"TOP PICK",IF(BB10<=5,"STRONG PICK",IF(BB10<=10,"CONSIDER","AVOID"))) -> AVOID | BD10: =IF(H10=1,Table8[[#This Row],[Model Score]],-10000) -> -0.1968092 | BE10: =IFERROR(INDEX(Player_Model!$BF$2:$BF$596,MATCH($A10,Player_Model!$A$2:$A$596,0)),"") -> 508 | BF10: =IFERROR(INDEX(Player_Model!$BG$2:$BG$596,MATCH($A10,Player_Model!$A$2:$A$596,0)),"") -> 107 | BG10: =IFERROR(INDEX(Player_Model!$BE$2:$BE$596,MATCH($A10,Player_Model!$A$2:$A$596,0)),0) -> -0.1968092
A11: =tblPlayers[first_name]&" "&tblPlayers[second_name] -> Benjamin White | B11: =_xlfn.SWITCH(tblPlayers[element_type],1,"GK",2,"DEF",3,"MID",4,"FWD") -> DEF | C11: =tblPlayers[team] -> 1 | D11: =INDEX(tblTeams[Column1.short_name],MATCH(C11,tblTeams[Column1.id],0)) -> ARS | E11: =INDEX(FPL_Raw_Data!$F:$F,MATCH(A11,FPL_Raw_Data!$AA:$AA,0))/10 -> 5.5 | F11: =tblPlayers[[#This Row],[status]] -> a | G11: =tblPlayers[[#This Row],[can_select]] -> TRUE | H11: =IF(AND(Table8[[#This Row],[Availability Status]]="a",Table8[[#This Row],[Can Select]]=TRUE),1,0) -> 1 | I11: =tblPlayers[minutes] -> 270 | J11: =Table8[[#This Row],[Minutes]]/90 -> 3 | K11: =IFERROR(Z11/(FIXTURE_ANALYSIS!$B$1-1),0) -> 1 | L11: =tblPlayers[total_points] -> 20 | M11: =tblPlayers[points_per_game] -> 6.7 | N11: =tblPlayers[form] -> 6.7 | O11: =tblPlayers[expected_goals] -> 0.18 | P11: =tblPlayers[expected_assists] -> 0.29 | Q11: =tblPlayers[expected_goal_involvements] -> 0.47 | R11: =IF(I11=0,0,L11/I11*90) -> 6.6666667 | S11: =IF(I11=0,0,O11/I11*90) -> 0.06 | T11: =IF(I11=0,0,P11/I11*90) -> 0.096666667 | U11: =IF(I11=0,0,Q11/I11*90) -> 0.15666667 | V11: =IF(E11=0,0,L11/E11) -> 3.6363636 | W11: =IF(E11=0,0,Q11/E11) -> 0.085454545 | X11: =IFERROR(IF(OR($B11="MID",$B11="FWD"),INDEX(FIXTURE_ANALYSIS!$Q:$Q,MATCH($D11,FIXTURE_ANALYSIS!$A:$A,0)),INDEX(FIXTURE_ANALYSIS!$R:$R,MATCH($D11,FIXTURE_ANALYSIS!$A:$A,0))),1) -> 1.1808552 | Y11: =X11 -> 1.1808552 | Z11: =INDEX(FPL_Raw_Data!$T:$T,MATCH(A11,FPL_Raw_Data!$AA:$AA,0)) -> 3 | AA11: =INDEX(FPL_Raw_Data!$S:$S,MATCH(A11,FPL_Raw_Data!$AA:$AA,0)) -> 15 | AB11: =IF(B11="DEF",MIN(AA11/10,1),IF(OR(B11="MID",B11="FWD"),MIN(AA11/12,1),0)) -> 1 | AC11: =INDEX(FPL_Raw_Data!$Q:$Q,MATCH(A11,FPL_Raw_Data!$AA:$AA,0)) -> 3 | AD11: =INDEX(FPL_Raw_Data!$R:$R,MATCH(A11,FPL_Raw_Data!$AA:$AA,0)) -> 74 | AE11: =INDEX(FPL_Raw_Data!$N:$N,MATCH(A11,FPL_Raw_Data!$AA:$AA,0)) -> 2 | AF11: =INDEX(FPL_Raw_Data!$L:$L,MATCH(A11,FPL_Raw_Data!$AA:$AA,0)) -> 0 | AG11: =INDEX(FPL_Raw_Data!$M:$M,MATCH(A11,FPL_Raw_Data!$AA:$AA,0)) -> 1 | AH11: =IF(B11="GK",S11*10,IF(B11="DEF",S11*6,IF(B11="MID",S11*5,S11*4))) -> 0.36 | AI11: =T11*3 -> 0.29 | AJ11: =K11*2 -> 2 | AK11: =AB11*2 -> 2 | AL11: =IFERROR(AE11/Z11,0) -> 0.66666667 | AM11: =IF(OR(B11="GK",B11="DEF"),AL11*4,IF(B11="MID",AL11*1,0)) -> 2.6666667 | AN11: =IFERROR(AC11/Z11,0) -> 1 | AO11: =IFERROR(_xlfn.PERCENTRANK.INC($R$2:$R$700,R11)*100,0) -> 84.8 | AP11: =IFERROR(_xlfn.PERCENTRANK.INC($U$2:$U$700,U11)*100,0) -> 73 | AQ11: =IFERROR(_xlfn.PERCENTRANK.INC($V$2:$V$700,V11)*100,0) -> 97.6 | AR11: =IFERROR(_xlfn.PERCENTRANK.INC($W$2:$W$700,W11)*100,0) -> 82.8 | AS11: =K11*100 -> 100 | AT11: =IFERROR(INDEX(Player_Model!$BC$2:$BC$596,MATCH($A11,Player_Model!$A$2:$A$596,0)),0) -> 7.2527706 | AU11: =Table8[[#This Row],[Model Expected Points]]*Table8[[#This Row],[Fixture Adjustment]] -> 8.5644719 | AV11: =Table8[[#This Row],[Fixture Adjusted Points / 90]]/Table8[[#This Row],[Price]] -> 1.5571767 | AW11: =IF(OR(B11="MID",B11="FWD"),AVERAGE(AO11,AP11),IF(B11="DEF",AP11,0)) -> 73 | AX11: =IF(B11="GK",AVERAGE(AS11,X11),IF(B11="DEF",AVERAGE(AB11,X11),IF(B11="MID",AB11,0))) -> 1.0904276 | AY11: =AS11 -> 100 | AZ11: =X11 -> 1.1808552 | BA11: =Table8[[#This Row],[Model Score2]] -> 7.2527706 | BB11: =IFERROR(INDEX(Player_Model!$BG$2:$BG$596,MATCH($A11,Player_Model!$A$2:$A$596,0)),"") -> 9 | BC11: =IF(BB11=1,"TOP PICK",IF(BB11<=5,"STRONG PICK",IF(BB11<=10,"CONSIDER","AVOID"))) -> CONSIDER | BD11: =IF(H11=1,Table8[[#This Row],[Model Score]],-10000) -> 7.2527706 | BE11: =IFERROR(INDEX(Player_Model!$BF$2:$BF$596,MATCH($A11,Player_Model!$A$2:$A$596,0)),"") -> 17 | BF11: =IFERROR(INDEX(Player_Model!$BG$2:$BG$596,MATCH($A11,Player_Model!$A$2:$A$596,0)),"") -> 9 | BG11: =IFERROR(INDEX(Player_Model!$BE$2:$BE$596,MATCH($A11,Player_Model!$A$2:$A$596,0)),0) -> 7.2527706
A12: =tblPlayers[first_name]&" "&tblPlayers[second_name] -> Cristhian Mosquera | B12: =_xlfn.SWITCH(tblPlayers[element_type],1,"GK",2,"DEF",3,"MID",4,"FWD") -> DEF | C12: =tblPlayers[team] -> 1 | D12: =INDEX(tblTeams[Column1.short_name],MATCH(C12,tblTeams[Column1.id],0)) -> ARS | E12: =INDEX(FPL_Raw_Data!$F:$F,MATCH(A12,FPL_Raw_Data!$AA:$AA,0))/10 -> 5.4 | F12: =tblPlayers[[#This Row],[status]] -> d | G12: =tblPlayers[[#This Row],[can_select]] -> TRUE | H12: =IF(AND(Table8[[#This Row],[Availability Status]]="a",Table8[[#This Row],[Can Select]]=TRUE),1,0) -> 0 | I12: =tblPlayers[minutes] -> 168 | J12: =Table8[[#This Row],[Minutes]]/90 -> 1.8666667 | K12: =IFERROR(Z12/(FIXTURE_ANALYSIS!$B$1-1),0) -> 0.66666667 | L12: =tblPlayers[total_points] -> 12 | M12: =tblPlayers[points_per_game] -> 6 | N12: =tblPlayers[form] -> 4 | O12: =tblPlayers[expected_goals] -> 0 | P12: =tblPlayers[expected_assists] -> 0.01 | Q12: =tblPlayers[expected_goal_involvements] -> 0.01 | R12: =IF(I12=0,0,L12/I12*90) -> 6.4285714 | S12: =IF(I12=0,0,O12/I12*90) -> 0 | T12: =IF(I12=0,0,P12/I12*90) -> 0.0053571429 | U12: =IF(I12=0,0,Q12/I12*90) -> 0.0053571429 | V12: =IF(E12=0,0,L12/E12) -> 2.2222222 | W12: =IF(E12=0,0,Q12/E12) -> 0.0018518519 | X12: =IFERROR(IF(OR($B12="MID",$B12="FWD"),INDEX(FIXTURE_ANALYSIS!$Q:$Q,MATCH($D12,FIXTURE_ANALYSIS!$A:$A,0)),INDEX(FIXTURE_ANALYSIS!$R:$R,MATCH($D12,FIXTURE_ANALYSIS!$A:$A,0))),1) -> 1.1808552 | Y12: =X12 -> 1.1808552 | Z12: =INDEX(FPL_Raw_Data!$T:$T,MATCH(A12,FPL_Raw_Data!$AA:$AA,0)) -> 2 | AA12: =INDEX(FPL_Raw_Data!$S:$S,MATCH(A12,FPL_Raw_Data!$AA:$AA,0)) -> 10 | AB12: =IF(B12="DEF",MIN(AA12/10,1),IF(OR(B12="MID",B12="FWD"),MIN(AA12/12,1),0)) -> 1 | AC12: =INDEX(FPL_Raw_Data!$Q:$Q,MATCH(A12,FPL_Raw_Data!$AA:$AA,0)) -> 0 | AD12: =INDEX(FPL_Raw_Data!$R:$R,MATCH(A12,FPL_Raw_Data!$AA:$AA,0)) -> 52 | AE12: =INDEX(FPL_Raw_Data!$N:$N,MATCH(A12,FPL_Raw_Data!$AA:$AA,0)) -> 2 | AF12: =INDEX(FPL_Raw_Data!$L:$L,MATCH(A12,FPL_Raw_Data!$AA:$AA,0)) -> 0 | AG12: =INDEX(FPL_Raw_Data!$M:$M,MATCH(A12,FPL_Raw_Data!$AA:$AA,0)) -> 0 | AH12: =IF(B12="GK",S12*10,IF(B12="DEF",S12*6,IF(B12="MID",S12*5,S12*4))) -> 0 | AI12: =T12*3 -> 0.016071429 | AJ12: =K12*2 -> 1.3333333 | AK12: =AB12*2 -> 2 | AL12: =IFERROR(AE12/Z12,0) -> 1 | AM12: =IF(OR(B12="GK",B12="DEF"),AL12*4,IF(B12="MID",AL12*1,0)) -> 4 | AN12: =IFERROR(AC12/Z12,0) -> 0 | AO12: =IFERROR(_xlfn.PERCENTRANK.INC($R$2:$R$700,R12)*100,0) -> 83.1 | AP12: =IFERROR(_xlfn.PERCENTRANK.INC($U$2:$U$700,U12)*100,0) -> 51.8 | AQ12: =IFERROR(_xlfn.PERCENTRANK.INC($V$2:$V$700,V12)*100,0) -> 89 | AR12: =IFERROR(_xlfn.PERCENTRANK.INC($W$2:$W$700,W12)*100,0) -> 51.3 | AS12: =K12*100 -> 66.666667 | AT12: =IFERROR(INDEX(Player_Model!$BC$2:$BC$596,MATCH($A12,Player_Model!$A$2:$A$596,0)),0) -> 8.282242 | AU12: =Table8[[#This Row],[Model Expected Points]]*Table8[[#This Row],[Fixture Adjustment]] -> 9.7801285 | AV12: =Table8[[#This Row],[Fixture Adjusted Points / 90]]/Table8[[#This Row],[Price]] -> 1.8111349 | AW12: =IF(OR(B12="MID",B12="FWD"),AVERAGE(AO12,AP12),IF(B12="DEF",AP12,0)) -> 51.8 | AX12: =IF(B12="GK",AVERAGE(AS12,X12),IF(B12="DEF",AVERAGE(AB12,X12),IF(B12="MID",AB12,0))) -> 1.0904276 | AY12: =AS12 -> 66.666667 | AZ12: =X12 -> 1.1808552 | BA12: =Table8[[#This Row],[Model Score2]] -> 8.282242 | BB12: =IFERROR(INDEX(Player_Model!$BG$2:$BG$596,MATCH($A12,Player_Model!$A$2:$A$596,0)),"") -> 5 | BC12: =IF(BB12=1,"TOP PICK",IF(BB12<=5,"STRONG PICK",IF(BB12<=10,"CONSIDER","AVOID"))) -> STRONG PICK | BD12: =IF(H12=1,Table8[[#This Row],[Model Score]],-10000) -> -10000 | BE12: =IFERROR(INDEX(Player_Model!$BF$2:$BF$596,MATCH($A12,Player_Model!$A$2:$A$596,0)),"") -> 6 | BF12: =IFERROR(INDEX(Player_Model!$BG$2:$BG$596,MATCH($A12,Player_Model!$A$2:$A$596,0)),"") -> 5 | BG12: =IFERROR(INDEX(Player_Model!$BE$2:$BE$596,MATCH($A12,Player_Model!$A$2:$A$596,0)),0) -> 8.282242
A13: =tblPlayers[first_name]&" "&tblPlayers[second_name] -> Bukayo Saka | B13: =_xlfn.SWITCH(tblPlayers[element_type],1,"GK",2,"DEF",3,"MID",4,"FWD") -> MID | C13: =tblPlayers[team] -> 1 | D13: =INDEX(tblTeams[Column1.short_name],MATCH(C13,tblTeams[Column1.id],0)) -> ARS | E13: =INDEX(FPL_Raw_Data!$F:$F,MATCH(A13,FPL_Raw_Data!$AA:$AA,0))/10 -> 9.5 | F13: =tblPlayers[[#This Row],[status]] -> a | G13: =tblPlayers[[#This Row],[can_select]] -> TRUE | H13: =IF(AND(Table8[[#This Row],[Availability Status]]="a",Table8[[#This Row],[Can Select]]=TRUE),1,0) -> 1 | I13: =tblPlayers[minutes] -> 246 | J13: =Table8[[#This Row],[Minutes]]/90 -> 2.7333333 | K13: =IFERROR(Z13/(FIXTURE_ANALYSIS!$B$1-1),0) -> 1 | L13: =tblPlayers[total_points] -> 22 | M13: =tblPlayers[points_per_game] -> 7.3 | N13: =tblPlayers[form] -> 7.3 | O13: =tblPlayers[expected_goals] -> 1.5 | P13: =tblPlayers[expected_assists] -> 0.35 | Q13: =tblPlayers[expected_goal_involvements] -> 1.85 | R13: =IF(I13=0,0,L13/I13*90) -> 8.0487805 | S13: =IF(I13=0,0,O13/I13*90) -> 0.54878049 | T13: =IF(I13=0,0,P13/I13*90) -> 0.12804878 | U13: =IF(I13=0,0,Q13/I13*90) -> 0.67682927 | V13: =IF(E13=0,0,L13/E13) -> 2.3157895 | W13: =IF(E13=0,0,Q13/E13) -> 0.19473684 | X13: =IFERROR(IF(OR($B13="MID",$B13="FWD"),INDEX(FIXTURE_ANALYSIS!$Q:$Q,MATCH($D13,FIXTURE_ANALYSIS!$A:$A,0)),INDEX(FIXTURE_ANALYSIS!$R:$R,MATCH($D13,FIXTURE_ANALYSIS!$A:$A,0))),1) -> 1.0430363 | Y13: =X13 -> 1.0430363 | Z13: =INDEX(FPL_Raw_Data!$T:$T,MATCH(A13,FPL_Raw_Data!$AA:$AA,0)) -> 3 | AA13: =INDEX(FPL_Raw_Data!$S:$S,MATCH(A13,FPL_Raw_Data!$AA:$AA,0)) -> 22 | AB13: =IF(B13="DEF",MIN(AA13/10,1),IF(OR(B13="MID",B13="FWD"),MIN(AA13/12,1),0)) -> 1 | AC13: =INDEX(FPL_Raw_Data!$Q:$Q,MATCH(A13,FPL_Raw_Data!$AA:$AA,0)) -> 4 | AD13: =INDEX(FPL_Raw_Data!$R:$R,MATCH(A13,FPL_Raw_Data!$AA:$AA,0)) -> 95 | AE13: =INDEX(FPL_Raw_Data!$N:$N,MATCH(A13,FPL_Raw_Data!$AA:$AA,0)) -> 2 | AF13: =INDEX(FPL_Raw_Data!$L:$L,MATCH(A13,FPL_Raw_Data!$AA:$AA,0)) -> 2 | AG13: =INDEX(FPL_Raw_Data!$M:$M,MATCH(A13,FPL_Raw_Data!$AA:$AA,0)) -> 0 | AH13: =IF(B13="GK",S13*10,IF(B13="DEF",S13*6,IF(B13="MID",S13*5,S13*4))) -> 2.7439024 | AI13: =T13*3 -> 0.38414634 | AJ13: =K13*2 -> 2 | AK13: =AB13*2 -> 2 | AL13: =IFERROR(AE13/Z13,0) -> 0.66666667 | AM13: =IF(OR(B13="GK",B13="DEF"),AL13*4,IF(B13="MID",AL13*1,0)) -> 0.66666667 | AN13: =IFERROR(AC13/Z13,0) -> 1.3333333 | AO13: =IFERROR(_xlfn.PERCENTRANK.INC($R$2:$R$700,R13)*100,0) -> 89.5 | AP13: =IFERROR(_xlfn.PERCENTRANK.INC($U$2:$U$700,U13)*100,0) -> 95.2 | AQ13: =IFERROR(_xlfn.PERCENTRANK.INC($V$2:$V$700,V13)*100,0) -> 90.2 | AR13: =IFERROR(_xlfn.PERCENTRANK.INC($W$2:$W$700,W13)*100,0) -> 94.2 | AS13: =K13*100 -> 100 | AT13: =IFERROR(INDEX(Player_Model!$BC$2:$BC$596,MATCH($A13,Player_Model!$A$2:$A$596,0)),0) -> 7.3785097 | AU13: =Table8[[#This Row],[Model Expected Points]]*Table8[[#This Row],[Fixture Adjustment]] -> 7.6960537 | AV13: =Table8[[#This Row],[Fixture Adjusted Points / 90]]/Table8[[#This Row],[Price]] -> 0.81011092 | AW13: =IF(OR(B13="MID",B13="FWD"),AVERAGE(AO13,AP13),IF(B13="DEF",AP13,0)) -> 92.35 | AX13: =IF(B13="GK",AVERAGE(AS13,X13),IF(B13="DEF",AVERAGE(AB13,X13),IF(B13="MID",AB13,0))) -> 1 | AY13: =AS13 -> 100 | AZ13: =X13 -> 1.0430363 | BA13: =Table8[[#This Row],[Model Score2]] -> 7.3785097 | BB13: =IFERROR(INDEX(Player_Model!$BG$2:$BG$596,MATCH($A13,Player_Model!$A$2:$A$596,0)),"") -> 6 | BC13: =IF(BB13=1,"TOP PICK",IF(BB13<=5,"STRONG PICK",IF(BB13<=10,"CONSIDER","AVOID"))) -> CONSIDER | BD13: =IF(H13=1,Table8[[#This Row],[Model Score]],-10000) -> 7.3785097 | BE13: =IFERROR(INDEX(Player_Model!$BF$2:$BF$596,MATCH($A13,Player_Model!$A$2:$A$596,0)),"") -> 16 | BF13: =IFERROR(INDEX(Player_Model!$BG$2:$BG$596,MATCH($A13,Player_Model!$A$2:$A$596,0)),"") -> 6 | BG13: =IFERROR(INDEX(Player_Model!$BE$2:$BE$596,MATCH($A13,Player_Model!$A$2:$A$596,0)),0) -> 7.3785097
... A596: =tblPlayers[first_name]&" "&tblPlayers[second_name] -> Pedro Porro Sauceda | B596: =_xlfn.SWITCH(tblPlayers[element_type],1,"GK",2,"DEF",3,"MID",4,"FWD") -> DEF | C596: =tblPlayers[team] -> 19 | D596: =INDEX(tblTeams[Column1.short_name],MATCH(C596,tblTeams[Column1.id],0)) -> TOT | E596: =INDEX(FPL_Raw_Data!$F:$F,MATCH(A596,FPL_Raw_Data!$AA:$AA,0))/10 -> 5.5 | F596: =tblPlayers[[#This Row],[status]] -> a | G596: =tblPlayers[[#This Row],[can_select]] -> TRUE | H596: =IF(AND(Table8[[#This Row],[Availability Status]]="a",Table8[[#This Row],[Can Select]]=TRUE),1,0) -> 1 | I596: =tblPlayers[minutes] -> 180 | J596: =Table8[[#This Row],[Minutes]]/90 -> 2 | K596: =IFERROR(Z596/(FIXTURE_ANALYSIS!$B$1-1),0) -> 0.66666667 | L596: =tblPlayers[total_points] -> 8 | M596: =tblPlayers[points_per_game] -> 4 | N596: =tblPlayers[form] -> 2.7 | O596: =tblPlayers[expected_goals] -> 0.36 | P596: =tblPlayers[expected_assists] -> 0.16 | Q596: =tblPlayers[expected_goal_involvements] -> 0.52 | R596: =IF(I596=0,0,L596/I596*90) -> 4 | S596: =IF(I596=0,0,O596/I596*90) -> 0.18 | T596: =IF(I596=0,0,P596/I596*90) -> 0.08 | U596: =IF(I596=0,0,Q596/I596*90) -> 0.26 | V596: =IF(E596=0,0,L596/E596) -> 1.4545455 | W596: =IF(E596=0,0,Q596/E596) -> 0.094545455 | X596: =IFERROR(IF(OR($B596="MID",$B596="FWD"),INDEX(FIXTURE_ANALYSIS!$Q:$Q,MATCH($D596,FIXTURE_ANALYSIS!$A:$A,0)),INDEX(FIXTURE_ANALYSIS!$R:$R,MATCH($D596,FIXTURE_ANALYSIS!$A:$A,0))),1) -> 0.97332359 | Y596: =X596 -> 0.97332359 | Z596: =INDEX(FPL_Raw_Data!$T:$T,MATCH(A596,FPL_Raw_Data!$AA:$AA,0)) -> 2 | AA596: =INDEX(FPL_Raw_Data!$S:$S,MATCH(A596,FPL_Raw_Data!$AA:$AA,0)) -> 8 | AB596: =IF(B596="DEF",MIN(AA596/10,1),IF(OR(B596="MID",B596="FWD"),MIN(AA596/12,1),0)) -> 0.8 | AC596: =INDEX(FPL_Raw_Data!$Q:$Q,MATCH(A596,FPL_Raw_Data!$AA:$AA,0)) -> 1 | AD596: =INDEX(FPL_Raw_Data!$R:$R,MATCH(A596,FPL_Raw_Data!$AA:$AA,0)) -> 29 | AE596: =INDEX(FPL_Raw_Data!$N:$N,MATCH(A596,FPL_Raw_Data!$AA:$AA,0)) -> 1 | AF596: =INDEX(FPL_Raw_Data!$L:$L,MATCH(A596,FPL_Raw_Data!$AA:$AA,0)) -> 0 | AG596: =INDEX(FPL_Raw_Data!$M:$M,MATCH(A596,FPL_Raw_Data!$AA:$AA,0)) -> 0 | AH596: =IF(B596="GK",S596*10,IF(B596="DEF",S596*6,IF(B596="MID",S596*5,S596*4))) -> 1.08 | AI596: =T596*3 -> 0.24 | AJ596: =K596*2 -> 1.3333333 | AK596: =AB596*2 -> 1.6 | AL596: =IFERROR(AE596/Z596,0) -> 0.5 | AM596: =IF(OR(B596="GK",B596="DEF"),AL596*4,IF(B596="MID",AL596*1,0)) -> 2 | AN596: =IFERROR(AC596/Z596,0) -> 0.5 | AO596: =IFERROR(_xlfn.PERCENTRANK.INC($R$2:$R$700,R596)*100,0) -> 69.3 | AP596: =IFERROR(_xlfn.PERCENTRANK.INC($U$2:$U$700,U596)*100,0) -> 81.1 | AQ596: =IFERROR(_xlfn.PERCENTRANK.INC($V$2:$V$700,V596)*100,0) -> 77.2 | AR596: =IFERROR(_xlfn.PERCENTRANK.INC($W$2:$W$700,W596)*100,0) -> 83.3 | AS596: =K596*100 -> 66.666667 | AT596: =IFERROR(INDEX(Player_Model!$BC$2:$BC$596,MATCH($A596,Player_Model!$A$2:$A$596,0)),0) -> 4.8752312 | AU596: =Table8[[#This Row],[Model Expected Points]]*Table8[[#This Row],[Fixture Adjustment]] -> 4.7451775 | AV596: =Table8[[#This Row],[Fixture Adjusted Points / 90]]/Table8[[#This Row],[Price]] -> 0.86275955 | AW596: =IF(OR(B596="MID",B596="FWD"),AVERAGE(AO596,AP596),IF(B596="DEF",AP596,0)) -> 81.1 | AX596: =IF(B596="GK",AVERAGE(AS596,X596),IF(B596="DEF",AVERAGE(AB596,X596),IF(B596="MID",AB596,0))) -> 0.8866618 | AY596: =AS596 -> 66.666667 | AZ596: =X596 -> 0.97332359 | BA596: =Table8[[#This Row],[Model Score2]] -> 4.8752312 | BB596: =IFERROR(INDEX(Player_Model!$BG$2:$BG$596,MATCH($A596,Player_Model!$A$2:$A$596,0)),"") -> 39 | BC596: =IF(BB596=1,"TOP PICK",IF(BB596<=5,"STRONG PICK",IF(BB596<=10,"CONSIDER","AVOID"))) -> AVOID | BD596: =IF(H596=1,Table8[[#This Row],[Model Score]],-10000) -> 4.8752312 | BE596: =IFERROR(INDEX(Player_Model!$BF$2:$BF$596,MATCH($A596,Player_Model!$A$2:$A$596,0)),"") -> 103 | BF596: =IFERROR(INDEX(Player_Model!$BG$2:$BG$596,MATCH($A596,Player_Model!$A$2:$A$596,0)),"") -> 39 | BG596: =IFERROR(INDEX(Player_Model!$BE$2:$BE$596,MATCH($A596,Player_Model!$A$2:$A$596,0)),0) -> 4.8752312

Sheet Player_Model
A1: Player | B1: Team | C1: Position | D1: Price | E1: Minutes | F1: Starts | G1: Start % | H1: Expected Minutes | I1: Goals | J1: Assists | K1: xG | L1: xA | M1: xG/90 | N1: xA/90 | O1: Points/90 | P1: xGI/90 | Q1: BPS/90 | R1: DC/90 | S1: 23/24 xG/90 | T1: 24/25 xG/90 | U1: 25/26 xG/90 | V1: 23/24 xA/90 | W1: 24/25 xA/90 | X1: 25/26 xA/90 | Y1: 23/24 Points/90 | Z1: 24/25 Points/90 | AA1: 25/26 Points/90 | AB1: Weighted_xG90 | AC1: Weighted_xA90 | AD1: Weighted Historical Points/90 | AE1: Historical Seasons | AF1: Avg Minutes | AG1: Smoothed xG/90 | AH1: Smoothed xA/90 | AI1: Smoothed Points/90 | AJ1: Minutes Reliability | AK1: New PL Player | AL1: Expected xG | AM1: Expected xA | AN1: Expected Goals | AO1: Expected Assists | AP1: Expected Goal Points | AQ1: Expected Assist Points | AR1: Expected Appearance Points | AS1: Expected Clean Sheet Points | AT1: Expected DC Points | AU1: Expected Bonus Points | AV1: Expected Saves | AW1: Expected Save Points | AX1: Expected Goals Conceded | AY1: Expected GC Points | AZ1: Predicted FPL Points | BA1: Predicted Points/£m | BB1: Fixture Adjustment | BC1: Fixture Adjusted Points | BD1: Fixture Adjusted Points/£m | BE1: Model Score | BF1: Overall Rank | BG1: Position Rank
A2: =Player_Analysis!A2 -> David Raya Martín | B2: =Player_Analysis!C2 -> 1 | C2: =Player_Analysis!B2 -> GK | D2: =Player_Analysis!E2 -> 6 | E2: =Player_Analysis!I2 -> 270 | F2: =Player_Analysis!Z2 -> 3 | G2: =IF(E2=0,0,MIN(1,F2/(E2/90))) -> 1 | H2: =IF($E2=0,0,MIN(90,$G2*90)) -> 90 | I2: =Player_Analysis!AF2 -> 0 | J2: =Player_Analysis!AG2 -> 0 | K2: =Player_Analysis!O2 -> 0 | L2: =Player_Analysis!P2 -> 0.01 | M2: =IF(E2=0,"",K2/E2*90) -> 0 | N2: =IF(E2=0,"",L2/E2*90) -> 0.0033333333 | O2: =IF(E2=0,"",Player_Analysis!L2/E2*90) -> 5 | P2: =IF(E2=0,"",Player_Analysis!Q2/E2*90) -> 0.0033333333 | Q2: =IF(E2=0,"",(Player_Analysis!AD2/E2)*90) -> 20 | R2: =IF(E2=0,"",Player_Analysis!AA2/E2*90) -> 0 | S2: {=IFERROR(INDEX('2023_24'!$O:$O,MATCH($A2,'2023_24'!$A:$A,0)),"")} | T2: =IFERROR(INDEX('2024_25'!$P:$P,MATCH($A2,'2024_25'!$A:$A,0)),"") | U2: =IFERROR(INDEX('2025_26'!$P:$P,MATCH($A2,'2025_26'!$A:$A,0)),"") -> 0 | V2: =IFERROR(INDEX('2023_24'!$P:$P,MATCH($A2,'2023_24'!$A:$A,0)),"") | W2: =IFERROR(INDEX('2024_25'!$Q:$Q,MATCH($A2,'2024_25'!$A:$A,0)),"") | X2: =IFERROR(INDEX('2025_26'!$Q:$Q,MATCH($A2,'2025_26'!$A:$A,0)),"") -> 0.0018918919 | Y2: =IFERROR(INDEX('2023_24'!$M:$M,MATCH($A2,'2023_24'!$A:$A,0))/INDEX('2023_24'!$G:$G,MATCH($A2,'2023_24'!$A:$A,0))*90,"") | Z2: =IFERROR(INDEX('2024_25'!$M:$M,MATCH($A2,'2024_25'!$A:$A,0))/INDEX('2024_25'!$G:$G,MATCH($A2,'2024_25'!$A:$A,0))*90,"") | AA2: =IFERROR(INDEX('2025_26'!$M:$M,MATCH($A2,'2025_26'!$A:$A,0))/INDEX('2025_26'!$G:$G,MATCH($A2,'2025_26'!$A:$A,0))*90,"") -> 4.3783784 | AB2: =IFERROR(SUMPRODUCT(S2:U2,{0.2,0.3,0.5})/SUMPRODUCT(--(S2:U2<>""),{0.2,0.3,0.5}),"") -> 0 | AC2: =IFERROR(SUMPRODUCT(V2:X2,{0.2,0.3,0.5})/SUMPRODUCT(--(V2:X2<>""),{0.2,0.3,0.5}),"") -> 0.0018918919 | AD2: =IFERROR(SUMPRODUCT(Y2:AA2,{0.2,0.3,0.5})/SUMPRODUCT((Y2:AA2<>"")*{0.2,0.3,0.5}),O2) -> 4.3783784 | AE2: =COUNT(S2:U2) -> 1 | AF2: =IF(F2=0,"",E2/F2) -> 90 | AG2: =IF(AND(M2="",AB2=""),0,IF(M2="",AB2,IF(AB2="",M2,M2*AJ2+AB2*(1-AJ2)))) -> 0 | AH2: =IF(AND(N2="",AC2=""),0,IF(N2="",AC2,IF(AC2="",N2,N2*AJ2+AC2*(1-AJ2)))) -> 0.0031891892 | AI2: =IF(AND(O2="",AD2=""),0,IF(O2="",AD2,IF(AD2="",O2,O2*AJ2+AD2*(1-AJ2)))) -> 4.9378378 | AJ2: =IF($E2=0,0,MIN(0.9,$E2/300)) -> 0.9 | AK2: =IF(AE2=0,"YES","NO") -> NO | AL2: =IF($H2=0,0,$AG2*$H2/90) -> 0 | AM2: =IF($H2=0,0,$AH2*$H2/90) -> 0.0031891892 | AN2: =AL2 -> 0 | AO2: =AM2 -> 0.0031891892 | AP2: {=AL2*IF($C2="GKP",10,IF($C2="DEF",6,IF($C2="MID",5,4)))} -> 0 | AQ2: =AM2*3 -> 0.0095675676 | AR2: =$G2*2 -> 2 | AS2: =IF($H2=0,0,Player_Analysis!$AM2*$H2/90) -> 2.6666667 | AT2: =IF($H2=0,0,$R2*$H2/90*2/IF(OR($C2="GKP",$C2="DEF"),10,12)) -> 0 | AU2: =0 -> 0 | AV2: =IF(INDEX(FPL_Raw_Data!K:K,MATCH(A2,FPL_Raw_Data!AA:AA,0))=0,"",INDEX(FPL_Raw_Data!P:P,MATCH(A2,FPL_Raw_Data!AA:AA,0))/INDEX(FPL_Raw_Data!K:K,MATCH(A2,FPL_Raw_Data!AA:AA,0))*90) -> 1.6666667 | AW2: =IF(AV2="",0,AV2/3) -> 0.55555556 | AX2: =IFERROR(INDEX(TEAM_ANALYSIS!$H$2:$H$21,MATCH($B2,TEAM_ANALYSIS!$A$2:$A$21,0)),0) -> 0.33333333 | AY2: =IF(OR($C2="GKP",$C2="DEF"),-($AX2/2),0) -> 0 | AZ2: =SUM(AP2:AU2)+AW2+AY2 -> 5.2317898 | BA2: =IF($D2=0,0,$AZ2/$D2) -> 0.87196496 | BB2: =IFERROR(Player_Analysis!$Y2,1) -> 1.1808552 | BC2: =BB2*AZ2 -> 6.1779862 | BD2: =BA2*BC2 -> 5.3869875 | BE2: =BC2 -> 6.1779862 | BF2: =IF($BE2="","",_xlfn.RANK.EQ($BE2,$BE$2:$BE$596,0)) -> 38 | BG2: =IF($BE2="","",COUNTIFS($C$2:$C$596,$C2,$BE$2:$BE$596,">"&$BE2)+COUNTIFS($C$2:$C2,$C2,$BE$2:$BE2,$BE2)) -> 2
A3: =Player_Analysis!A3 -> Kepa Arrizabalaga Revuelta | B3: =Player_Analysis!C3 -> 1 | C3: =Player_Analysis!B3 -> GK | D3: =Player_Analysis!E3 -> 4.9 | E3: =Player_Analysis!I3 -> 0 | F3: =Player_Analysis!Z3 -> 0 | G3: =IF(E3=0,0,MIN(1,F3/(E3/90))) -> 0 | H3: =IF($E3=0,0,MIN(90,$G3*90)) -> 0 | I3: =Player_Analysis!AF3 -> 0 | J3: =Player_Analysis!AG3 -> 0 | K3: =Player_Analysis!O3 -> 0 | L3: =Player_Analysis!P3 -> 0 | M3: =IF(E3=0,"",K3/E3*90) | N3: =IF(E3=0,"",L3/E3*90) | O3: =IF(E3=0,"",Player_Analysis!L3/E3*90) | P3: =IF(E3=0,"",Player_Analysis!Q3/E3*90) | Q3: =IF(E3=0,"",(Player_Analysis!AD3/E3)*90) | R3: =IF(E3=0,"",Player_Analysis!AA3/E3*90) | S3: {=IFERROR(INDEX('2023_24'!$O:$O,MATCH($A3,'2023_24'!$A:$A,0)),"")} | T3: =IFERROR(INDEX('2024_25'!$P:$P,MATCH($A3,'2024_25'!$A:$A,0)),"") | U3: =IFERROR(INDEX('2025_26'!$P:$P,MATCH($A3,'2025_26'!$A:$A,0)),"") -> 0 | V3: =IFERROR(INDEX('2023_24'!$P:$P,MATCH($A3,'2023_24'!$A:$A,0)),"") | W3: =IFERROR(INDEX('2024_25'!$Q:$Q,MATCH($A3,'2024_25'!$A:$A,0)),"") | X3: =IFERROR(INDEX('2025_26'!$Q:$Q,MATCH($A3,'2025_26'!$A:$A,0)),"") -> 0 | Y3: =IFERROR(INDEX('2023_24'!$M:$M,MATCH($A3,'2023_24'!$A:$A,0))/INDEX('2023_24'!$G:$G,MATCH($A3,'2023_24'!$A:$A,0))*90,"") | Z3: =IFERROR(INDEX('2024_25'!$M:$M,MATCH($A3,'2024_25'!$A:$A,0))/INDEX('2024_25'!$G:$G,MATCH($A3,'2024_25'!$A:$A,0))*90,"") | AA3: =IFERROR(INDEX('2025_26'!$M:$M,MATCH($A3,'2025_26'!$A:$A,0))/INDEX('2025_26'!$G:$G,MATCH($A3,'2025_26'!$A:$A,0))*90,"") -> 2 | AB3: =IFERROR(SUMPRODUCT(S3:U3,{0.2,0.3,0.5})/SUMPRODUCT(--(S3:U3<>""),{0.2,0.3,0.5}),"") -> 0 | AC3: =IFERROR(SUMPRODUCT(V3:X3,{0.2,0.3,0.5})/SUMPRODUCT(--(V3:X3<>""),{0.2,0.3,0.5}),"") -> 0 | AD3: =IFERROR(SUMPRODUCT(Y3:AA3,{0.2,0.3,0.5})/SUMPRODUCT((Y3:AA3<>"")*{0.2,0.3,0.5}),O3) -> 2 | AE3: =COUNT(S3:U3) -> 1 | AF3: =IF(F3=0,"",E3/F3) | AG3: =IF(AND(M3="",AB3=""),0,IF(M3="",AB3,IF(AB3="",M3,M3*AJ3+AB3*(1-AJ3)))) -> 0 | AH3: =IF(AND(N3="",AC3=""),0,IF(N3="",AC3,IF(AC3="",N3,N3*AJ3+AC3*(1-AJ3)))) -> 0 | AI3: =IF(AND(O3="",AD3=""),0,IF(O3="",AD3,IF(AD3="",O3,O3*AJ3+AD3*(1-AJ3)))) -> 2 | AJ3: =IF($E3=0,0,MIN(0.9,$E3/300)) -> 0 | AK3: =IF(AE3=0,"YES","NO") -> NO | AL3: =IF($H3=0,0,$AG3*$H3/90) -> 0 | AM3: =IF($H3=0,0,$AH3*$H3/90) -> 0 | AN3: =AL3 -> 0 | AO3: =AM3 -> 0 | AP3: {=AL3*IF($C3="GKP",10,IF($C3="DEF",6,IF($C3="MID",5,4)))} -> 0 | AQ3: =AM3*3 -> 0 | AR3: =$G3*2 -> 0 | AS3: =IF($H3=0,0,Player_Analysis!$AM3*$H3/90) -> 0 | AT3: =IF($H3=0,0,$R3*$H3/90*2/IF(OR($C3="GKP",$C3="DEF"),10,12)) -> 0 | AU3: =0 -> 0 | AV3: =IF(INDEX(FPL_Raw_Data!K:K,MATCH(A3,FPL_Raw_Data!AA:AA,0))=0,"",INDEX(FPL_Raw_Data!P:P,MATCH(A3,FPL_Raw_Data!AA:AA,0))/INDEX(FPL_Raw_Data!K:K,MATCH(A3,FPL_Raw_Data!AA:AA,0))*90) | AW3: =IF(AV3="",0,AV3/3) -> 0 | AX3: =IFERROR(INDEX(TEAM_ANALYSIS!$H$2:$H$21,MATCH($B3,TEAM_ANALYSIS!$A$2:$A$21,0)),0) -> 0.33333333 | AY3: =IF(OR($C3="GKP",$C3="DEF"),-($AX3/2),0) -> 0 | AZ3: =SUM(AP3:AU3)+AW3+AY3 -> 0 | BA3: =IF($D3=0,0,$AZ3/$D3) -> 0 | BB3: =IFERROR(Player_Analysis!$Y3,1) -> 1.1808552 | BC3: =BB3*AZ3 -> 0 | BD3: =BA3*BC3 -> 0 | BE3: =BC3 -> 0 | BF3: =IF($BE3="","",_xlfn.RANK.EQ($BE3,$BE$2:$BE$596,0)) -> 253 | BG3: =IF($BE3="","",COUNTIFS($C$2:$C$596,$C3,$BE$2:$BE$596,">"&$BE3)+COUNTIFS($C$2:$C3,$C3,$BE$2:$BE3,$BE3)) -> 22
A4: =Player_Analysis!A4 -> Illan Meslier | B4: =Player_Analysis!C4 -> 1 | C4: =Player_Analysis!B4 -> GK | D4: =Player_Analysis!E4 -> 4.9 | E4: =Player_Analysis!I4 -> 0 | F4: =Player_Analysis!Z4 -> 0 | G4: =IF(E4=0,0,MIN(1,F4/(E4/90))) -> 0 | H4: =IF($E4=0,0,MIN(90,$G4*90)) -> 0 | I4: =Player_Analysis!AF4 -> 0 | J4: =Player_Analysis!AG4 -> 0 | K4: =Player_Analysis!O4 -> 0 | L4: =Player_Analysis!P4 -> 0 | M4: =IF(E4=0,"",K4/E4*90) | N4: =IF(E4=0,"",L4/E4*90) | O4: =IF(E4=0,"",Player_Analysis!L4/E4*90) | P4: =IF(E4=0,"",Player_Analysis!Q4/E4*90) | Q4: =IF(E4=0,"",(Player_Analysis!AD4/E4)*90) | R4: =IF(E4=0,"",Player_Analysis!AA4/E4*90) | S4: {=IFERROR(INDEX('2023_24'!$O:$O,MATCH($A4,'2023_24'!$A:$A,0)),"")} | T4: =IFERROR(INDEX('2024_25'!$P:$P,MATCH($A4,'2024_25'!$A:$A,0)),"") | U4: =IFERROR(INDEX('2025_26'!$P:$P,MATCH($A4,'2025_26'!$A:$A,0)),"") -> 0 | V4: =IFERROR(INDEX('2023_24'!$P:$P,MATCH($A4,'2023_24'!$A:$A,0)),"") | W4: =IFERROR(INDEX('2024_25'!$Q:$Q,MATCH($A4,'2024_25'!$A:$A,0)),"") | X4: =IFERROR(INDEX('2025_26'!$Q:$Q,MATCH($A4,'2025_26'!$A:$A,0)),"") -> 0 | Y4: =IFERROR(INDEX('2023_24'!$M:$M,MATCH($A4,'2023_24'!$A:$A,0))/INDEX('2023_24'!$G:$G,MATCH($A4,'2023_24'!$A:$A,0))*90,"") | Z4: =IFERROR(INDEX('2024_25'!$M:$M,MATCH($A4,'2024_25'!$A:$A,0))/INDEX('2024_25'!$G:$G,MATCH($A4,'2024_25'!$A:$A,0))*90,"") | AA4: =IFERROR(INDEX('2025_26'!$M:$M,MATCH($A4,'2025_26'!$A:$A,0))/INDEX('2025_26'!$G:$G,MATCH($A4,'2025_26'!$A:$A,0))*90,"") | AB4: =IFERROR(SUMPRODUCT(S4:U4,{0.2,0.3,0.5})/SUMPRODUCT(--(S4:U4<>""),{0.2,0.3,0.5}),"") -> 0 | AC4: =IFERROR(SUMPRODUCT(V4:X4,{0.2,0.3,0.5})/SUMPRODUCT(--(V4:X4<>""),{0.2,0.3,0.5}),"") -> 0 | AD4: =IFERROR(SUMPRODUCT(Y4:AA4,{0.2,0.3,0.5})/SUMPRODUCT((Y4:AA4<>"")*{0.2,0.3,0.5}),O4) | AE4: =COUNT(S4:U4) -> 1 | AF4: =IF(F4=0,"",E4/F4) | AG4: =IF(AND(M4="",AB4=""),0,IF(M4="",AB4,IF(AB4="",M4,M4*AJ4+AB4*(1-AJ4)))) -> 0 | AH4: =IF(AND(N4="",AC4=""),0,IF(N4="",AC4,IF(AC4="",N4,N4*AJ4+AC4*(1-AJ4)))) -> 0 | AI4: =IF(AND(O4="",AD4=""),0,IF(O4="",AD4,IF(AD4="",O4,O4*AJ4+AD4*(1-AJ4)))) -> 0 | AJ4: =IF($E4=0,0,MIN(0.9,$E4/300)) -> 0 | AK4: =IF(AE4=0,"YES","NO") -> NO | AL4: =IF($H4=0,0,$AG4*$H4/90) -> 0 | AM4: =IF($H4=0,0,$AH4*$H4/90) -> 0 | AN4: =AL4 -> 0 | AO4: =AM4 -> 0 | AP4: {=AL4*IF($C4="GKP",10,IF($C4="DEF",6,IF($C4="MID",5,4)))} -> 0 | AQ4: =AM4*3 -> 0 | AR4: =$G4*2 -> 0 | AS4: =IF($H4=0,0,Player_Analysis!$AM4*$H4/90) -> 0 | AT4: =IF($H4=0,0,$R4*$H4/90*2/IF(OR($C4="GKP",$C4="DEF"),10,12)) -> 0 | AU4: =0 -> 0 | AV4: =IF(INDEX(FPL_Raw_Data!K:K,MATCH(A4,FPL_Raw_Data!AA:AA,0))=0,"",INDEX(FPL_Raw_Data!P:P,MATCH(A4,FPL_Raw_Data!AA:AA,0))/INDEX(FPL_Raw_Data!K:K,MATCH(A4,FPL_Raw_Data!AA:AA,0))*90) | AW4: =IF(AV4="",0,AV4/3) -> 0 | AX4: =IFERROR(INDEX(TEAM_ANALYSIS!$H$2:$H$21,MATCH($B4,TEAM_ANALYSIS!$A$2:$A$21,0)),0) -> 0.33333333 | AY4: =IF(OR($C4="GKP",$C4="DEF"),-($AX4/2),0) -> 0 | AZ4: =SUM(AP4:AU4)+AW4+AY4 -> 0 | BA4: =IF($D4=0,0,$AZ4/$D4) -> 0 | BB4: =IFERROR(Player_Analysis!$Y4,1) -> 1.1808552 | BC4: =BB4*AZ4 -> 0 | BD4: =BA4*BC4 -> 0 | BE4: =BC4 -> 0 | BF4: =IF($BE4="","",_xlfn.RANK.EQ($BE4,$BE$2:$BE$596,0)) -> 253 | BG4: =IF($BE4="","",COUNTIFS($C$2:$C$596,$C4,$BE$2:$BE$596,">"&$BE4)+COUNTIFS($C$2:$C4,$C4,$BE$2:$BE4,$BE4)) -> 23
A5: =Player_Analysis!A5 -> Gabriel dos Santos Magalhães | B5: =Player_Analysis!C5 -> 1 | C5: =Player_Analysis!B5 -> DEF | D5: =Player_Analysis!E5 -> 8 | E5: =Player_Analysis!I5 -> 270 | F5: =Player_Analysis!Z5 -> 3 | G5: =IF(E5=0,0,MIN(1,F5/(E5/90))) -> 1 | H5: =IF($E5=0,0,MIN(90,$G5*90)) -> 90 | I5: =Player_Analysis!AF5 -> 0 | J5: =Player_Analysis!AG5 -> 0 | K5: =Player_Analysis!O5 -> 0.49 | L5: =Player_Analysis!P5 -> 0.05 | M5: =IF(E5=0,"",K5/E5*90) -> 0.16333333 | N5: =IF(E5=0,"",L5/E5*90) -> 0.016666667 | O5: =IF(E5=0,"",Player_Analysis!L5/E5*90) -> 5 | P5: =IF(E5=0,"",Player_Analysis!Q5/E5*90) -> 0.18 | Q5: =IF(E5=0,"",(Player_Analysis!AD5/E5)*90) -> 18 | R5: =IF(E5=0,"",Player_Analysis!AA5/E5*90) -> 7 | S5: {=IFERROR(INDEX('2023_24'!$O:$O,MATCH($A5,'2023_24'!$A:$A,0)),"")} -> 0.13254438 | T5: =IFERROR(INDEX('2024_25'!$P:$P,MATCH($A5,'2024_25'!$A:$A,0)),"") -> 0.10283538 | U5: =IFERROR(INDEX('2025_26'!$P:$P,MATCH($A5,'2025_26'!$A:$A,0)),"") -> 0.096218182 | V5: =IFERROR(INDEX('2023_24'!$P:$P,MATCH($A5,'2023_24'!$A:$A,0)),"") -> 0.019230769 | W5: =IFERROR(INDEX('2024_25'!$Q:$Q,MATCH($A5,'2024_25'!$A:$A,0)),"") -> 0.046085485 | X5: =IFERROR(INDEX('2025_26'!$Q:$Q,MATCH($A5,'2025_26'!$A:$A,0)),"") -> 0.057272727 | Y5: =IFERROR(INDEX('2023_24'!$M:$M,MATCH($A5,'2023_24'!$A:$A,0))/INDEX('2023_24'!$G:$G,MATCH($A5,'2023_24'!$A:$A,0))*90,"") -> 4.408284 | Z5: =IFERROR(INDEX('2024_25'!$M:$M,MATCH($A5,'2024_25'!$A:$A,0))/INDEX('2024_25'!$G:$G,MATCH($A5,'2024_25'!$A:$A,0))*90,"") -> 4.4561997 | AA5: =IFERROR(INDEX('2025_26'!$M:$M,MATCH($A5,'2025_26'!$A:$A,0))/INDEX('2025_26'!$G:$G,MATCH($A5,'2025_26'!$A:$A,0))*90,"") -> 6.84 | AB5: =IFERROR(SUMPRODUCT(S5:U5,{0.2,0.3,0.5})/SUMPRODUCT(--(S5:U5<>""),{0.2,0.3,0.5}),"") -> 0.10546858 | AC5: =IFERROR(SUMPRODUCT(V5:X5,{0.2,0.3,0.5})/SUMPRODUCT(--(V5:X5<>""),{0.2,0.3,0.5}),"") -> 0.046308163 | AD5: =IFERROR(SUMPRODUCT(Y5:AA5,{0.2,0.3,0.5})/SUMPRODUCT((Y5:AA5<>"")*{0.2,0.3,0.5}),O5) -> 5.6385167 | AE5: =COUNT(S5:U5) -> 3 | AF5: =IF(F5=0,"",E5/F5) -> 90 | AG5: =IF(AND(M5="",AB5=""),0,IF(M5="",AB5,IF(AB5="",M5,M5*AJ5+AB5*(1-AJ5)))) -> 0.15754686 | AH5: =IF(AND(N5="",AC5=""),0,IF(N5="",AC5,IF(AC5="",N5,N5*AJ5+AC5*(1-AJ5)))) -> 0.019630816 | AI5: =IF(AND(O5="",AD5=""),0,IF(O5="",AD5,IF(AD5="",O5,O5*AJ5+AD5*(1-AJ5)))) -> 5.0638517 | AJ5: =IF($E5=0,0,MIN(0.9,$E5/300)) -> 0.9 | AK5: =IF(AE5=0,"YES","NO") -> NO | AL5: =IF($H5=0,0,$AG5*$H5/90) -> 0.15754686 | AM5: =IF($H5=0,0,$AH5*$H5/90) -> 0.019630816 | AN5: =AL5 -> 0.15754686 | AO5: =AM5 -> 0.019630816 | AP5: {=AL5*IF($C5="GKP",10,IF($C5="DEF",6,IF($C5="MID",5,4)))} -> 0.94528115 | AQ5: =AM5*3 -> 0.058892449 | AR5: =$G5*2 -> 2 | AS5: =IF($H5=0,0,Player_Analysis!$AM5*$H5/90) -> 2.6666667 | AT5: =IF($H5=0,0,$R5*$H5/90*2/IF(OR($C5="GKP",$C5="DEF"),10,12)) -> 1.4 | AU5: =0 -> 0 | AV5: =IF(INDEX(FPL_Raw_Data!K:K,MATCH(A5,FPL_Raw_Data!AA:AA,0))=0,"",INDEX(FPL_Raw_Data!P:P,MATCH(A5,FPL_Raw_Data!AA:AA,0))/INDEX(FPL_Raw_Data!K:K,MATCH(A5,FPL_Raw_Data!AA:AA,0))*90) -> 0 | AW5: =IF(AV5="",0,AV5/3) -> 0 | AX5: =IFERROR(INDEX(TEAM_ANALYSIS!$H$2:$H$21,MATCH($B5,TEAM_ANALYSIS!$A$2:$A$21,0)),0) -> 0.33333333 | AY5: =IF(OR($C5="GKP",$C5="DEF"),-($AX5/2),0) -> -0.16666667 | AZ5: =SUM(AP5:AU5)+AW5+AY5 -> 6.9041736 | BA5: =IF($D5=0,0,$AZ5/$D5) -> 0.8630217 | BB5: =IFERROR(Player_Analysis!$Y5,1) -> 1.1808552 | BC5: =BB5*AZ5 -> 8.1528293 | BD5: =BA5*BC5 -> 7.0360686 | BE5: =BC5 -> 8.1528293 | BF5: =IF($BE5="","",_xlfn.RANK.EQ($BE5,$BE$2:$BE$596,0)) -> 7 | BG5: =IF($BE5="","",COUNTIFS($C$2:$C$596,$C5,$BE$2:$BE$596,">"&$BE5)+COUNTIFS($C$2:$C5,$C5,$BE$2:$BE5,$BE5)) -> 6
A6: =Player_Analysis!A6 -> Jurriën Timber | B6: =Player_Analysis!C6 -> 1 | C6: =Player_Analysis!B6 -> DEF | D6: =Player_Analysis!E6 -> 6.5 | E6: =Player_Analysis!I6 -> 0 | F6: =Player_Analysis!Z6 -> 0 | G6: =IF(E6=0,0,MIN(1,F6/(E6/90))) -> 0 | H6: =IF($E6=0,0,MIN(90,$G6*90)) -> 0 | I6: =Player_Analysis!AF6 -> 0 | J6: =Player_Analysis!AG6 -> 0 | K6: =Player_Analysis!O6 -> 0 | L6: =Player_Analysis!P6 -> 0 | M6: =IF(E6=0,"",K6/E6*90) | N6: =IF(E6=0,"",L6/E6*90) | O6: =IF(E6=0,"",Player_Analysis!L6/E6*90) | P6: =IF(E6=0,"",Player_Analysis!Q6/E6*90) | Q6: =IF(E6=0,"",(Player_Analysis!AD6/E6)*90) | R6: =IF(E6=0,"",Player_Analysis!AA6/E6*90) | S6: {=IFERROR(INDEX('2023_24'!$O:$O,MATCH($A6,'2023_24'!$A:$A,0)),"")} -> 0 | T6: =IFERROR(INDEX('2024_25'!$P:$P,MATCH($A6,'2024_25'!$A:$A,0)),"") -> 0.045838509 | U6: =IFERROR(INDEX('2025_26'!$P:$P,MATCH($A6,'2025_26'!$A:$A,0)),"") -> 0.17287928 | V6: =IFERROR(INDEX('2023_24'!$P:$P,MATCH($A6,'2023_24'!$A:$A,0)),"") -> 0.025714286 | W6: =IFERROR(INDEX('2024_25'!$Q:$Q,MATCH($A6,'2024_25'!$A:$A,0)),"") -> 0.048447205 | X6: =IFERROR(INDEX('2025_26'!$Q:$Q,MATCH($A6,'2025_26'!$A:$A,0)),"") -> 0.056158238 | Y6: =IFERROR(INDEX('2023_24'!$M:$M,MATCH($A6,'2023_24'!$A:$A,0))/INDEX('2023_24'!$G:$G,MATCH($A6,'2023_24'!$A:$A,0))*90,"") -> 0 | Z6: =IFERROR(INDEX('2024_25'!$M:$M,MATCH($A6,'2024_25'!$A:$A,0))/INDEX('2024_25'!$G:$G,MATCH($A6,'2024_25'!$A:$A,0))*90,"") -> 4.2484472 | AA6: =IFERROR(INDEX('2025_26'!$M:$M,MATCH($A6,'2025_26'!$A:$A,0))/INDEX('2025_26'!$G:$G,MATCH($A6,'2025_26'!$A:$A,0))*90,"") -> 5.4690049 | AB6: =IFERROR(SUMPRODUCT(S6:U6,{0.2,0.3,0.5})/SUMPRODUCT(--(S6:U6<>""),{0.2,0.3,0.5}),"") -> 0.10019119 | AC6: =IFERROR(SUMPRODUCT(V6:X6,{0.2,0.3,0.5})/SUMPRODUCT(--(V6:X6<>""),{0.2,0.3,0.5}),"") -> 0.047756138 | AD6: =IFERROR(SUMPRODUCT(Y6:AA6,{0.2,0.3,0.5})/SUMPRODUCT((Y6:AA6<>"")*{0.2,0.3,0.5}),O6) -> 4.0090366 | AE6: =COUNT(S6:U6) -> 3 | AF6: =IF(F6=0,"",E6/F6) | AG6: =IF(AND(M6="",AB6=""),0,IF(M6="",AB6,IF(AB6="",M6,M6*AJ6+AB6*(1-AJ6)))) -> 0.10019119 | AH6: =IF(AND(N6="",AC6=""),0,IF(N6="",AC6,IF(AC6="",N6,N6*AJ6+AC6*(1-AJ6)))) -> 0.047756138 | AI6: =IF(AND(O6="",AD6=""),0,IF(O6="",AD6,IF(AD6="",O6,O6*AJ6+AD6*(1-AJ6)))) -> 4.0090366 | AJ6: =IF($E6=0,0,MIN(0.9,$E6/300)) -> 0 | AK6: =IF(AE6=0,"YES","NO") -> NO | AL6: =IF($H6=0,0,$AG6*$H6/90) -> 0 | AM6: =IF($H6=0,0,$AH6*$H6/90) -> 0 | AN6: =AL6 -> 0 | AO6: =AM6 -> 0 | AP6: {=AL6*IF($C6="GKP",10,IF($C6="DEF",6,IF($C6="MID",5,4)))} -> 0 | AQ6: =AM6*3 -> 0 | AR6: =$G6*2 -> 0 | AS6: =IF($H6=0,0,Player_Analysis!$AM6*$H6/90) -> 0 | AT6: =IF($H6=0,0,$R6*$H6/90*2/IF(OR($C6="GKP",$C6="DEF"),10,12)) -> 0 | AU6: =0 -> 0 | AV6: =IF(INDEX(FPL_Raw_Data!K:K,MATCH(A6,FPL_Raw_Data!AA:AA,0))=0,"",INDEX(FPL_Raw_Data!P:P,MATCH(A6,FPL_Raw_Data!AA:AA,0))/INDEX(FPL_Raw_Data!K:K,MATCH(A6,FPL_Raw_Data!AA:AA,0))*90) | AW6: =IF(AV6="",0,AV6/3) -> 0 | AX6: =IFERROR(INDEX(TEAM_ANALYSIS!$H$2:$H$21,MATCH($B6,TEAM_ANALYSIS!$A$2:$A$21,0)),0) -> 0.33333333 | AY6: =IF(OR($C6="GKP",$C6="DEF"),-($AX6/2),0) -> -0.16666667 | AZ6: =SUM(AP6:AU6)+AW6+AY6 -> -0.16666667 | BA6: =IF($D6=0,0,$AZ6/$D6) -> -0.025641026 | BB6: =IFERROR(Player_Analysis!$Y6,1) -> 1.1808552 | BC6: =BB6*AZ6 -> -0.1968092 | BD6: =BA6*BC6 -> 0.0050463897 | BE6: =BC6 -> -0.1968092 | BF6: =IF($BE6="","",_xlfn.RANK.EQ($BE6,$BE$2:$BE$596,0)) -> 508 | BG6: =IF($BE6="","",COUNTIFS($C$2:$C$596,$C6,$BE$2:$BE$596,">"&$BE6)+COUNTIFS($C$2:$C6,$C6,$BE$2:$BE6,$BE6)) -> 105
A7: =Player_Analysis!A7 -> William Saliba | B7: =Player_Analysis!C7 -> 1 | C7: =Player_Analysis!B7 -> DEF | D7: =Player_Analysis!E7 -> 6 | E7: =Player_Analysis!I7 -> 0 | F7: =Player_Analysis!Z7 -> 0 | G7: =IF(E7=0,0,MIN(1,F7/(E7/90))) -> 0 | H7: =IF($E7=0,0,MIN(90,$G7*90)) -> 0 | I7: =Player_Analysis!AF7 -> 0 | J7: =Player_Analysis!AG7 -> 0 | K7: =Player_Analysis!O7 -> 0 | L7: =Player_Analysis!P7 -> 0 | M7: =IF(E7=0,"",K7/E7*90) | N7: =IF(E7=0,"",L7/E7*90) | O7: =IF(E7=0,"",Player_Analysis!L7/E7*90) | P7: =IF(E7=0,"",Player_Analysis!Q7/E7*90) | Q7: =IF(E7=0,"",(Player_Analysis!AD7/E7)*90) | R7: =IF(E7=0,"",Player_Analysis!AA7/E7*90) | S7: {=IFERROR(INDEX('2023_24'!$O:$O,MATCH($A7,'2023_24'!$A:$A,0)),"")} -> 0.044736842 | T7: =IFERROR(INDEX('2024_25'!$P:$P,MATCH($A7,'2024_25'!$A:$A,0)),"") -> 0.071668312 | U7: =IFERROR(INDEX('2025_26'!$P:$P,MATCH($A7,'2025_26'!$A:$A,0)),"") -> 0.030298393 | V7: =IFERROR(INDEX('2023_24'!$P:$P,MATCH($A7,'2023_24'!$A:$A,0)),"") -> 0.023684211 | W7: =IFERROR(INDEX('2024_25'!$Q:$Q,MATCH($A7,'2024_25'!$A:$A,0)),"") -> 0.037907206 | X7: =IFERROR(INDEX('2025_26'!$Q:$Q,MATCH($A7,'2025_26'!$A:$A,0)),"") -> 0.041660291 | Y7: =IFERROR(INDEX('2023_24'!$M:$M,MATCH($A7,'2023_24'!$A:$A,0))/INDEX('2023_24'!$G:$G,MATCH($A7,'2023_24'!$A:$A,0))*90,"") -> 4.3157895 | Z7: =IFERROR(INDEX('2024_25'!$M:$M,MATCH($A7,'2024_25'!$A:$A,0))/INDEX('2024_25'!$G:$G,MATCH($A7,'2024_25'!$A:$A,0))*90,"") -> 3.8499506 | AA7: =IFERROR(INDEX('2025_26'!$M:$M,MATCH($A7,'2025_26'!$A:$A,0))/INDEX('2025_26'!$G:$G,MATCH($A7,'2025_26'!$A:$A,0))*90,"") -> 4.716909 | AB7: =IFERROR(SUMPRODUCT(S7:U7,{0.2,0.3,0.5})/SUMPRODUCT(--(S7:U7<>""),{0.2,0.3,0.5}),"") -> 0.045597059 | AC7: =IFERROR(SUMPRODUCT(V7:X7,{0.2,0.3,0.5})/SUMPRODUCT(--(V7:X7<>""),{0.2,0.3,0.5}),"") -> 0.036939149 | AD7: =IFERROR(SUMPRODUCT(Y7:AA7,{0.2,0.3,0.5})/SUMPRODUCT((Y7:AA7<>"")*{0.2,0.3,0.5}),O7) -> 4.3765976 | AE7: =COUNT(S7:U7) -> 3 | AF7: =IF(F7=0,"",E7/F7) | AG7: =IF(AND(M7="",AB7=""),0,IF(M7="",AB7,IF(AB7="",M7,M7*AJ7+AB7*(1-AJ7)))) -> 0.045597059 | AH7: =IF(AND(N7="",AC7=""),0,IF(N7="",AC7,IF(AC7="",N7,N7*AJ7+AC7*(1-AJ7)))) -> 0.036939149 | AI7: =IF(AND(O7="",AD7=""),0,IF(O7="",AD7,IF(AD7="",O7,O7*AJ7+AD7*(1-AJ7)))) -> 4.3765976 | AJ7: =IF($E7=0,0,MIN(0.9,$E7/300)) -> 0 | AK7: =IF(AE7=0,"YES","NO") -> NO | AL7: =IF($H7=0,0,$AG7*$H7/90) -> 0 | AM7: =IF($H7=0,0,$AH7*$H7/90) -> 0 | AN7: =AL7 -> 0 | AO7: =AM7 -> 0 | AP7: {=AL7*IF($C7="GKP",10,IF($C7="DEF",6,IF($C7="MID",5,4)))} -> 0 | AQ7: =AM7*3 -> 0 | AR7: =$G7*2 -> 0 | AS7: =IF($H7=0,0,Player_Analysis!$AM7*$H7/90) -> 0 | AT7: =IF($H7=0,0,$R7*$H7/90*2/IF(OR($C7="GKP",$C7="DEF"),10,12)) -> 0 | AU7: =0 -> 0 | AV7: =IF(INDEX(FPL_Raw_Data!K:K,MATCH(A7,FPL_Raw_Data!AA:AA,0))=0,"",INDEX(FPL_Raw_Data!P:P,MATCH(A7,FPL_Raw_Data!AA:AA,0))/INDEX(FPL_Raw_Data!K:K,MATCH(A7,FPL_Raw_Data!AA:AA,0))*90) | AW7: =IF(AV7="",0,AV7/3) -> 0 | AX7: =IFERROR(INDEX(TEAM_ANALYSIS!$H$2:$H$21,MATCH($B7,TEAM_ANALYSIS!$A$2:$A$21,0)),0) -> 0.33333333 | AY7: =IF(OR($C7="GKP",$C7="DEF"),-($AX7/2),0) -> -0.16666667 | AZ7: =SUM(AP7:AU7)+AW7+AY7 -> -0.16666667 | BA7: =IF($D7=0,0,$AZ7/$D7) -> -0.027777778 | BB7: =IFERROR(Player_Analysis!$Y7,1) -> 1.1808552 | BC7: =BB7*AZ7 -> -0.1968092 | BD7: =BA7*BC7 -> 0.0054669222 | BE7: =BC7 -> -0.1968092 | BF7: =IF($BE7="","",_xlfn.RANK.EQ($BE7,$BE$2:$BE$596,0)) -> 508 | BG7: =IF($BE7="","",COUNTIFS($C$2:$C$596,$C7,$BE$2:$BE$596,">"&$BE7)+COUNTIFS($C$2:$C7,$C7,$BE$2:$BE7,$BE7)) -> 106
A8: =Player_Analysis!A8 -> Myles Lewis-Skelly | B8: =Player_Analysis!C8 -> 1 | C8: =Player_Analysis!B8 -> MID | D8: =Player_Analysis!E8 -> 5.5 | E8: =Player_Analysis!I8 -> 226 | F8: =Player_Analysis!Z8 -> 3 | G8: =IF(E8=0,0,MIN(1,F8/(E8/90))) -> 1 | H8: =IF($E8=0,0,MIN(90,$G8*90)) -> 90 | I8: =Player_Analysis!AF8 -> 0 | J8: =Player_Analysis!AG8 -> 0 | K8: =Player_Analysis!O8 -> 0.16 | L8: =Player_Analysis!P8 -> 0.23 | M8: =IF(E8=0,"",K8/E8*90) -> 0.063716814 | N8: =IF(E8=0,"",L8/E8*90) -> 0.09159292 | O8: =IF(E8=0,"",Player_Analysis!L8/E8*90) -> 3.1858407 | P8: =IF(E8=0,"",Player_Analysis!Q8/E8*90) -> 0.15530973 | Q8: =IF(E8=0,"",(Player_Analysis!AD8/E8)*90) -> 13.938053 | R8: =IF(E8=0,"",Player_Analysis!AA8/E8*90) -> 5.5752212 | S8: {=IFERROR(INDEX('2023_24'!$O:$O,MATCH($A8,'2023_24'!$A:$A,0)),"")} -> 0 | T8: =IFERROR(INDEX('2024_25'!$P:$P,MATCH($A8,'2024_25'!$A:$A,0)),"") -> 0.010572687 | U8: =IFERROR(INDEX('2025_26'!$P:$P,MATCH($A8,'2025_26'!$A:$A,0)),"") -> 0.012912482 | V8: =IFERROR(INDEX('2023_24'!$P:$P,MATCH($A8,'2023_24'!$A:$A,0)),"") -> 0 | W8: =IFERROR(INDEX('2024_25'!$Q:$Q,MATCH($A8,'2024_25'!$A:$A,0)),"") -> 0.033700441 | X8: =IFERROR(INDEX('2025_26'!$Q:$Q,MATCH($A8,'2025_26'!$A:$A,0)),"") -> 0.025824964 | Y8: =IFERROR(INDEX('2023_24'!$M:$M,MATCH($A8,'2023_24'!$A:$A,0))/INDEX('2023_24'!$G:$G,MATCH($A8,'2023_24'!$A:$A,0))*90,"") | Z8: =IFERROR(INDEX('2024_25'!$M:$M,MATCH($A8,'2024_25'!$A:$A,0))/INDEX('2024_25'!$G:$G,MATCH($A8,'2024_25'!$A:$A,0))*90,"") -> 2.4449339 | AA8: =IFERROR(INDEX('2025_26'!$M:$M,MATCH($A8,'2025_26'!$A:$A,0))/INDEX('2025_26'!$G:$G,MATCH($A8,'2025_26'!$A:$A,0))*90,"") -> 3.7446198 | AB8: =IFERROR(SUMPRODUCT(S8:U8,{0.2,0.3,0.5})/SUMPRODUCT(--(S8:U8<>""),{0.2,0.3,0.5}),"") -> 0.0096280472 | AC8: =IFERROR(SUMPRODUCT(V8:X8,{0.2,0.3,0.5})/SUMPRODUCT(--(V8:X8<>""),{0.2,0.3,0.5}),"") -> 0.023022614 | AD8: =IFERROR(SUMPRODUCT(Y8:AA8,{0.2,0.3,0.5})/SUMPRODUCT((Y8:AA8<>"")*{0.2,0.3,0.5}),O8) -> 3.2572376 | AE8: =COUNT(S8:U8) -> 3 | AF8: =IF(F8=0,"",E8/F8) -> 75.333333 | AG8: =IF(AND(M8="",AB8=""),0,IF(M8="",AB8,IF(AB8="",M8,M8*AJ8+AB8*(1-AJ8)))) -> 0.050374918 | AH8: =IF(AND(N8="",AC8=""),0,IF(N8="",AC8,IF(AC8="",N8,N8*AJ8+AC8*(1-AJ8)))) -> 0.074678912 | AI8: =IF(AND(O8="",AD8=""),0,IF(O8="",AD8,IF(AD8="",O8,O8*AJ8+AD8*(1-AJ8)))) -> 3.2034519 | AJ8: =IF($E8=0,0,MIN(0.9,$E8/300)) -> 0.75333333 | AK8: =IF(AE8=0,"YES","NO") -> NO | AL8: =IF($H8=0,0,$AG8*$H8/90) -> 0.050374918 | AM8: =IF($H8=0,0,$AH8*$H8/90) -> 0.074678912 | AN8: =AL8 -> 0.050374918 | AO8: =AM8 -> 0.074678912 | AP8: {=AL8*IF($C8="GKP",10,IF($C8="DEF",6,IF($C8="MID",5,4)))} -> 0.25187459 | AQ8: =AM8*3 -> 0.22403673 | AR8: =$G8*2 -> 2 | AS8: =IF($H8=0,0,Player_Analysis!$AM8*$H8/90) -> 0.66666667 | AT8: =IF($H8=0,0,$R8*$H8/90*2/IF(OR($C8="GKP",$C8="DEF"),10,12)) -> 0.92920354 | AU8: =0 -> 0 | AV8: =IF(INDEX(FPL_Raw_Data!K:K,MATCH(A8,FPL_Raw_Data!AA:AA,0))=0,"",INDEX(FPL_Raw_Data!P:P,MATCH(A8,FPL_Raw_Data!AA:AA,0))/INDEX(FPL_Raw_Data!K:K,MATCH(A8,FPL_Raw_Data!AA:AA,0))*90) -> 0 | AW8: =IF(AV8="",0,AV8/3) -> 0 | AX8: =IFERROR(INDEX(TEAM_ANALYSIS!$H$2:$H$21,MATCH($B8,TEAM_ANALYSIS!$A$2:$A$21,0)),0) -> 0.33333333 | AY8: =IF(OR($C8="GKP",$C8="DEF"),-($AX8/2),0) -> 0 | AZ8: =SUM(AP8:AU8)+AW8+AY8 -> 4.0717815 | BA8: =IF($D8=0,0,$AZ8/$D8) -> 0.74032392 | BB8: =IFERROR(Player_Analysis!$Y8,1) -> 1.0430363 | BC8: =BB8*AZ8 -> 4.2470161 | BD8: =BA8*BC8 -> 3.1441676 | BE8: =BC8 -> 4.2470161 | BF8: =IF($BE8="","",_xlfn.RANK.EQ($BE8,$BE$2:$BE$596,0)) -> 140 | BG8: =IF($BE8="","",COUNTIFS($C$2:$C$596,$C8,$BE$2:$BE$596,">"&$BE8)+COUNTIFS($C$2:$C8,$C8,$BE$2:$BE8,$BE8)) -> 69
A9: =Player_Analysis!A9 -> Riccardo Calafiori | B9: =Player_Analysis!C9 -> 1 | C9: =Player_Analysis!B9 -> DEF | D9: =Player_Analysis!E9 -> 5.7 | E9: =Player_Analysis!I9 -> 236 | F9: =Player_Analysis!Z9 -> 3 | G9: =IF(E9=0,0,MIN(1,F9/(E9/90))) -> 1 | H9: =IF($E9=0,0,MIN(90,$G9*90)) -> 90 | I9: =Player_Analysis!AF9 -> 0 | J9: =Player_Analysis!AG9 -> 2 | K9: =Player_Analysis!O9 -> 0.54 | L9: =Player_Analysis!P9 -> 0.58 | M9: =IF(E9=0,"",K9/E9*90) -> 0.2059322 | N9: =IF(E9=0,"",L9/E9*90) -> 0.22118644 | O9: =IF(E9=0,"",Player_Analysis!L9/E9*90) -> 8.3898305 | P9: =IF(E9=0,"",Player_Analysis!Q9/E9*90) -> 0.42711864 | Q9: =IF(E9=0,"",(Player_Analysis!AD9/E9)*90) -> 23.262712 | R9: =IF(E9=0,"",Player_Analysis!AA9/E9*90) -> 3.4322034 | S9: {=IFERROR(INDEX('2023_24'!$O:$O,MATCH($A9,'2023_24'!$A:$A,0)),"")} | T9: =IFERROR(INDEX('2024_25'!$P:$P,MATCH($A9,'2024_25'!$A:$A,0)),"") -> 0.079141104 | U9: =IFERROR(INDEX('2025_26'!$P:$P,MATCH($A9,'2025_26'!$A:$A,0)),"") -> 0.17819682 | V9: =IFERROR(INDEX('2023_24'!$P:$P,MATCH($A9,'2023_24'!$A:$A,0)),"") | W9: =IFERROR(INDEX('2024_25'!$Q:$Q,MATCH($A9,'2024_25'!$A:$A,0)),"") -> 0.063496933 | X9: =IFERROR(INDEX('2025_26'!$Q:$Q,MATCH($A9,'2025_26'!$A:$A,0)),"") -> 0.040306423 | Y9: =IFERROR(INDEX('2023_24'!$M:$M,MATCH($A9,'2023_24'!$A:$A,0))/INDEX('2023_24'!$G:$G,MATCH($A9,'2023_24'!$A:$A,0))*90,"") | Z9: =IFERROR(INDEX('2024_25'!$M:$M,MATCH($A9,'2024_25'!$A:$A,0))/INDEX('2024_25'!$G:$G,MATCH($A9,'2024_25'!$A:$A,0))*90,"") -> 3.5889571 | AA9: =IFERROR(INDEX('2025_26'!$M:$M,MATCH($A9,'2025_26'!$A:$A,0))/INDEX('2025_26'!$G:$G,MATCH($A9,'2025_26'!$A:$A,0))*90,"") -> 5.7807896 | AB9: =IFERROR(SUMPRODUCT(S9:U9,{0.2,0.3,0.5})/SUMPRODUCT(--(S9:U9<>""),{0.2,0.3,0.5}),"") -> 0.14105093 | AC9: =IFERROR(SUMPRODUCT(V9:X9,{0.2,0.3,0.5})/SUMPRODUCT(--(V9:X9<>""),{0.2,0.3,0.5}),"") -> 0.049002864 | AD9: =IFERROR(SUMPRODUCT(Y9:AA9,{0.2,0.3,0.5})/SUMPRODUCT((Y9:AA9<>"")*{0.2,0.3,0.5}),O9) -> 4.9588524 | AE9: =COUNT(S9:U9) -> 2 | AF9: =IF(F9=0,"",E9/F9) -> 78.666667 | AG9: =IF(AND(M9="",AB9=""),0,IF(M9="",AB9,IF(AB9="",M9,M9*AJ9+AB9*(1-AJ9)))) -> 0.19209086 | AH9: =IF(AND(N9="",AC9=""),0,IF(N9="",AC9,IF(AC9="",N9,N9*AJ9+AC9*(1-AJ9)))) -> 0.18445394 | AI9: =IF(AND(O9="",AD9=""),0,IF(O9="",AD9,IF(AD9="",O9,O9*AJ9+AD9*(1-AJ9)))) -> 7.6578885 | AJ9: =IF($E9=0,0,MIN(0.9,$E9/300)) -> 0.78666667 | AK9: =IF(AE9=0,"YES","NO") -> NO | AL9: =IF($H9=0,0,$AG9*$H9/90) -> 0.19209086 | AM9: =IF($H9=0,0,$AH9*$H9/90) -> 0.18445394 | AN9: =AL9 -> 0.19209086 | AO9: =AM9 -> 0.18445394 | AP9: {=AL9*IF($C9="GKP",10,IF($C9="DEF",6,IF($C9="MID",5,4)))} -> 1.1525452 | AQ9: =AM9*3 -> 0.55336183 | AR9: =$G9*2 -> 2 | AS9: =IF($H9=0,0,Player_Analysis!$AM9*$H9/90) -> 2.6666667 | AT9: =IF($H9=0,0,$R9*$H9/90*2/IF(OR($C9="GKP",$C9="DEF"),10,12)) -> 0.68644068 | AU9: =0 -> 0 | AV9: =IF(INDEX(FPL_Raw_Data!K:K,MATCH(A9,FPL_Raw_Data!AA:AA,0))=0,"",INDEX(FPL_Raw_Data!P:P,MATCH(A9,FPL_Raw_Data!AA:AA,0))/INDEX(FPL_Raw_Data!K:K,MATCH(A9,FPL_Raw_Data!AA:AA,0))*90) -> 0 | AW9: =IF(AV9="",0,AV9/3) -> 0 | AX9: =IFERROR(INDEX(TEAM_ANALYSIS!$H$2:$H$21,MATCH($B9,TEAM_ANALYSIS!$A$2:$A$21,0)),0) -> 0.33333333 | AY9: =IF(OR($C9="GKP",$C9="DEF"),-($AX9/2),0) -> -0.16666667 | AZ9: =SUM(AP9:AU9)+AW9+AY9 -> 6.8923477 | BA9: =IF($D9=0,0,$AZ9/$D9) -> 1.2091838 | BB9: =IFERROR(Player_Analysis!$Y9,1) -> 1.1808552 | BC9: =BB9*AZ9 -> 8.1388646 | BD9: =BA9*BC9 -> 9.8413833 | BE9: =BC9 -> 8.1388646 | BF9: =IF($BE9="","",_xlfn.RANK.EQ($BE9,$BE$2:$BE$596,0)) -> 9 | BG9: =IF($BE9="","",COUNTIFS($C$2:$C$596,$C9,$BE$2:$BE$596,">"&$BE9)+COUNTIFS($C$2:$C9,$C9,$BE$2:$BE9,$BE9)) -> 8
A10: =Player_Analysis!A10 -> Piero Hincapié | B10: =Player_Analysis!C10 -> 1 | C10: =Player_Analysis!B10 -> DEF | D10: =Player_Analysis!E10 -> 5.3 | E10: =Player_Analysis!I10 -> 32 | F10: =Player_Analysis!Z10 -> 0 | G10: =IF(E10=0,0,MIN(1,F10/(E10/90))) -> 0 | H10: =IF($E10=0,0,MIN(90,$G10*90)) -> 0 | I10: =Player_Analysis!AF10 -> 0 | J10: =Player_Analysis!AG10 -> 0 | K10: =Player_Analysis!O10 -> 0 | L10: =Player_Analysis!P10 -> 0 | M10: =IF(E10=0,"",K10/E10*90) -> 0 | N10: =IF(E10=0,"",L10/E10*90) -> 0 | O10: =IF(E10=0,"",Player_Analysis!L10/E10*90) -> 5.625 | P10: =IF(E10=0,"",Player_Analysis!Q10/E10*90) -> 0 | Q10: =IF(E10=0,"",(Player_Analysis!AD10/E10)*90) -> 16.875 | R10: =IF(E10=0,"",Player_Analysis!AA10/E10*90) -> 8.4375 | S10: {=IFERROR(INDEX('2023_24'!$O:$O,MATCH($A10,'2023_24'!$A:$A,0)),"")} | T10: =IFERROR(INDEX('2024_25'!$P:$P,MATCH($A10,'2024_25'!$A:$A,0)),"") | U10: =IFERROR(INDEX('2025_26'!$P:$P,MATCH($A10,'2025_26'!$A:$A,0)),"") -> 0.018130946 | V10: =IFERROR(INDEX('2023_24'!$P:$P,MATCH($A10,'2023_24'!$A:$A,0)),"") | W10: =IFERROR(INDEX('2024_25'!$Q:$Q,MATCH($A10,'2024_25'!$A:$A,0)),"") | X10: =IFERROR(INDEX('2025_26'!$Q:$Q,MATCH($A10,'2025_26'!$A:$A,0)),"") -> 0.084107443 | Y10: =IFERROR(INDEX('2023_24'!$M:$M,MATCH($A10,'2023_24'!$A:$A,0))/INDEX('2023_24'!$G:$G,MATCH($A10,'2023_24'!$A:$A,0))*90,"") | Z10: =IFERROR(INDEX('2024_25'!$M:$M,MATCH($A10,'2024_25'!$A:$A,0))/INDEX('2024_25'!$G:$G,MATCH($A10,'2024_25'!$A:$A,0))*90,"") | AA10: =IFERROR(INDEX('2025_26'!$M:$M,MATCH($A10,'2025_26'!$A:$A,0))/INDEX('2025_26'!$G:$G,MATCH($A10,'2025_26'!$A:$A,0))*90,"") -> 4.3816452 | AB10: =IFERROR(SUMPRODUCT(S10:U10,{0.2,0.3,0.5})/SUMPRODUCT(--(S10:U10<>""),{0.2,0.3,0.5}),"") -> 0.018130946 | AC10: =IFERROR(SUMPRODUCT(V10:X10,{0.2,0.3,0.5})/SUMPRODUCT(--(V10:X10<>""),{0.2,0.3,0.5}),"") -> 0.084107443 | AD10: =IFERROR(SUMPRODUCT(Y10:AA10,{0.2,0.3,0.5})/SUMPRODUCT((Y10:AA10<>"")*{0.2,0.3,0.5}),O10) -> 4.3816452 | AE10: =COUNT(S10:U10) -> 1 | AF10: =IF(F10=0,"",E10/F10) | AG10: =IF(AND(M10="",AB10=""),0,IF(M10="",AB10,IF(AB10="",M10,M10*AJ10+AB10*(1-AJ10)))) -> 0.016196978 | AH10: =IF(AND(N10="",AC10=""),0,IF(N10="",AC10,IF(AC10="",N10,N10*AJ10+AC10*(1-AJ10)))) -> 0.075135982 | AI10: =IF(AND(O10="",AD10=""),0,IF(O10="",AD10,IF(AD10="",O10,O10*AJ10+AD10*(1-AJ10)))) -> 4.5142697 | AJ10: =IF($E10=0,0,MIN(0.9,$E10/300)) -> 0.10666667 | AK10: =IF(AE10=0,"YES","NO") -> NO | AL10: =IF($H10=0,0,$AG10*$H10/90) -> 0 | AM10: =IF($H10=0,0,$AH10*$H10/90) -> 0 | AN10: =AL10 -> 0 | AO10: =AM10 -> 0 | AP10: {=AL10*IF($C10="GKP",10,IF($C10="DEF",6,IF($C10="MID",5,4)))} -> 0 | AQ10: =AM10*3 -> 0 | AR10: =$G10*2 -> 0 | AS10: =IF($H10=0,0,Player_Analysis!$AM10*$H10/90) -> 0 | AT10: =IF($H10=0,0,$R10*$H10/90*2/IF(OR($C10="GKP",$C10="DEF"),10,12)) -> 0 | AU10: =0 -> 0 | AV10: =IF(INDEX(FPL_Raw_Data!K:K,MATCH(A10,FPL_Raw_Data!AA:AA,0))=0,"",INDEX(FPL_Raw_Data!P:P,MATCH(A10,FPL_Raw_Data!AA:AA,0))/INDEX(FPL_Raw_Data!K:K,MATCH(A10,FPL_Raw_Data!AA:AA,0))*90) -> 0 | AW10: =IF(AV10="",0,AV10/3) -> 0 | AX10: =IFERROR(INDEX(TEAM_ANALYSIS!$H$2:$H$21,MATCH($B10,TEAM_ANALYSIS!$A$2:$A$21,0)),0) -> 0.33333333 | AY10: =IF(OR($C10="GKP",$C10="DEF"),-($AX10/2),0) -> -0.16666667 | AZ10: =SUM(AP10:AU10)+AW10+AY10 -> -0.16666667 | BA10: =IF($D10=0,0,$AZ10/$D10) -> -0.031446541 | BB10: =IFERROR(Player_Analysis!$Y10,1) -> 1.1808552 | BC10: =BB10*AZ10 -> -0.1968092 | BD10: =BA10*BC10 -> 0.0061889685 | BE10: =BC10 -> -0.1968092 | BF10: =IF($BE10="","",_xlfn.RANK.EQ($BE10,$BE$2:$BE$596,0)) -> 508 | BG10: =IF($BE10="","",COUNTIFS($C$2:$C$596,$C10,$BE$2:$BE$596,">"&$BE10)+COUNTIFS($C$2:$C10,$C10,$BE$2:$BE10,$BE10)) -> 107
A11: =Player_Analysis!A11 -> Benjamin White | B11: =Player_Analysis!C11 -> 1 | C11: =Player_Analysis!B11 -> DEF | D11: =Player_Analysis!E11 -> 5.5 | E11: =Player_Analysis!I11 -> 270 | F11: =Player_Analysis!Z11 -> 3 | G11: =IF(E11=0,0,MIN(1,F11/(E11/90))) -> 1 | H11: =IF($E11=0,0,MIN(90,$G11*90)) -> 90 | I11: =Player_Analysis!AF11 -> 0 | J11: =Player_Analysis!AG11 -> 1 | K11: =Player_Analysis!O11 -> 0.18 | L11: =Player_Analysis!P11 -> 0.29 | M11: =IF(E11=0,"",K11/E11*90) -> 0.06 | N11: =IF(E11=0,"",L11/E11*90) -> 0.096666667 | O11: =IF(E11=0,"",Player_Analysis!L11/E11*90) -> 6.6666667 | P11: =IF(E11=0,"",Player_Analysis!Q11/E11*90) -> 0.15666667 | Q11: =IF(E11=0,"",(Player_Analysis!AD11/E11)*90) -> 24.666667 | R11: =IF(E11=0,"",Player_Analysis!AA11/E11*90) -> 5 | S11: {=IFERROR(INDEX('2023_24'!$O:$O,MATCH($A11,'2023_24'!$A:$A,0)),"")} -> 0.038265819 | T11: =IFERROR(INDEX('2024_25'!$P:$P,MATCH($A11,'2024_25'!$A:$A,0)),"") -> 0.034644351 | U11: =IFERROR(INDEX('2025_26'!$P:$P,MATCH($A11,'2025_26'!$A:$A,0)),"") -> 0.057939914 | V11: =IFERROR(INDEX('2023_24'!$P:$P,MATCH($A11,'2023_24'!$A:$A,0)),"") -> 0.11027787 | W11: =IFERROR(INDEX('2024_25'!$Q:$Q,MATCH($A11,'2024_25'!$A:$A,0)),"") -> 0.09790795 | X11: =IFERROR(INDEX('2025_26'!$Q:$Q,MATCH($A11,'2025_26'!$A:$A,0)),"") -> 0.088841202 | Y11: =IFERROR(INDEX('2023_24'!$M:$M,MATCH($A11,'2023_24'!$A:$A,0))/INDEX('2023_24'!$G:$G,MATCH($A11,'2023_24'!$A:$A,0))*90,"") -> 5.483763 | Z11: =IFERROR(INDEX('2024_25'!$M:$M,MATCH($A11,'2024_25'!$A:$A,0))/INDEX('2024_25'!$G:$G,MATCH($A11,'2024_25'!$A:$A,0))*90,"") -> 3.7656904 | AA11: =IFERROR(INDEX('2025_26'!$M:$M,MATCH($A11,'2025_26'!$A:$A,0))/INDEX('2025_26'!$G:$G,MATCH($A11,'2025_26'!$A:$A,0))*90,"") -> 5.7939914 | AB11: =IFERROR(SUMPRODUCT(S11:U11,{0.2,0.3,0.5})/SUMPRODUCT(--(S11:U11<>""),{0.2,0.3,0.5}),"") -> 0.047016426 | AC11: =IFERROR(SUMPRODUCT(V11:X11,{0.2,0.3,0.5})/SUMPRODUCT(--(V11:X11<>""),{0.2,0.3,0.5}),"") -> 0.09584856 | AD11: =IFERROR(SUMPRODUCT(Y11:AA11,{0.2,0.3,0.5})/SUMPRODUCT((Y11:AA11<>"")*{0.2,0.3,0.5}),O11) -> 5.1234554 | AE11: =COUNT(S11:U11) -> 3 | AF11: =IF(F11=0,"",E11/F11) -> 90 | AG11: =IF(AND(M11="",AB11=""),0,IF(M11="",AB11,IF(AB11="",M11,M11*AJ11+AB11*(1-AJ11)))) -> 0.058701643 | AH11: =IF(AND(N11="",AC11=""),0,IF(N11="",AC11,IF(AC11="",N11,N11*AJ11+AC11*(1-AJ11)))) -> 0.096584856 | AI11: =IF(AND(O11="",AD11=""),0,IF(O11="",AD11,IF(AD11="",O11,O11*AJ11+AD11*(1-AJ11)))) -> 6.5123455 | AJ11: =IF($E11=0,0,MIN(0.9,$E11/300)) -> 0.9 | AK11: =IF(AE11=0,"YES","NO") -> NO | AL11: =IF($H11=0,0,$AG11*$H11/90) -> 0.058701643 | AM11: =IF($H11=0,0,$AH11*$H11/90) -> 0.096584856 | AN11: =AL11 -> 0.058701643 | AO11: =AM11 -> 0.096584856 | AP11: {=AL11*IF($C11="GKP",10,IF($C11="DEF",6,IF($C11="MID",5,4)))} -> 0.35220986 | AQ11: =AM11*3 -> 0.28975457 | AR11: =$G11*2 -> 2 | AS11: =IF($H11=0,0,Player_Analysis!$AM11*$H11/90) -> 2.6666667 | AT11: =IF($H11=0,0,$R11*$H11/90*2/IF(OR($C11="GKP",$C11="DEF"),10,12)) -> 1 | AU11: =0 -> 0 | AV11: =IF(INDEX(FPL_Raw_Data!K:K,MATCH(A11,FPL_Raw_Data!AA:AA,0))=0,"",INDEX(FPL_Raw_Data!P:P,MATCH(A11,FPL_Raw_Data!AA:AA,0))/INDEX(FPL_Raw_Data!K:K,MATCH(A11,FPL_Raw_Data!AA:AA,0))*90) -> 0 | AW11: =IF(AV11="",0,AV11/3) -> 0 | AX11: =IFERROR(INDEX(TEAM_ANALYSIS!$H$2:$H$21,MATCH($B11,TEAM_ANALYSIS!$A$2:$A$21,0)),0) -> 0.33333333 | AY11: =IF(OR($C11="GKP",$C11="DEF"),-($AX11/2),0) -> -0.16666667 | AZ11: =SUM(AP11:AU11)+AW11+AY11 -> 6.1419644 | BA11: =IF($D11=0,0,$AZ11/$D11) -> 1.1167208 | BB11: =IFERROR(Player_Analysis!$Y11,1) -> 1.1808552 | BC11: =BB11*AZ11 -> 7.2527706 | BD11: =BA11*BC11 -> 8.0993198 | BE11: =BC11 -> 7.2527706 | BF11: =IF($BE11="","",_xlfn.RANK.EQ($BE11,$BE$2:$BE$596,0)) -> 17 | BG11: =IF($BE11="","",COUNTIFS($C$2:$C$596,$C11,$BE$2:$BE$596,">"&$BE11)+COUNTIFS($C$2:$C11,$C11,$BE$2:$BE11,$BE11)) -> 9
A12: =Player_Analysis!A12 -> Cristhian Mosquera | B12: =Player_Analysis!C12 -> 1 | C12: =Player_Analysis!B12 -> DEF | D12: =Player_Analysis!E12 -> 5.4 | E12: =Player_Analysis!I12 -> 168 | F12: =Player_Analysis!Z12 -> 2 | G12: =IF(E12=0,0,MIN(1,F12/(E12/90))) -> 1 | H12: =IF($E12=0,0,MIN(90,$G12*90)) -> 90 | I12: =Player_Analysis!AF12 -> 0 | J12: =Player_Analysis!AG12 -> 0 | K12: =Player_Analysis!O12 -> 0 | L12: =Player_Analysis!P12 -> 0.01 | M12: =IF(E12=0,"",K12/E12*90) -> 0 | N12: =IF(E12=0,"",L12/E12*90) -> 0.0053571429 | O12: =IF(E12=0,"",Player_Analysis!L12/E12*90) -> 6.4285714 | P12: =IF(E12=0,"",Player_Analysis!Q12/E12*90) -> 0.0053571429 | Q12: =IF(E12=0,"",(Player_Analysis!AD12/E12)*90) -> 27.857143 | R12: =IF(E12=0,"",Player_Analysis!AA12/E12*90) -> 5.3571429 | S12: {=IFERROR(INDEX('2023_24'!$O:$O,MATCH($A12,'2023_24'!$A:$A,0)),"")} | T12: =IFERROR(INDEX('2024_25'!$P:$P,MATCH($A12,'2024_25'!$A:$A,0)),"") | U12: =IFERROR(INDEX('2025_26'!$P:$P,MATCH($A12,'2025_26'!$A:$A,0)),"") -> 0.009127789 | V12: =IFERROR(INDEX('2023_24'!$P:$P,MATCH($A12,'2023_24'!$A:$A,0)),"") | W12: =IFERROR(INDEX('2024_25'!$Q:$Q,MATCH($A12,'2024_25'!$A:$A,0)),"") | X12: =IFERROR(INDEX('2025_26'!$Q:$Q,MATCH($A12,'2025_26'!$A:$A,0)),"") -> 0.057505071 | Y12: =IFERROR(INDEX('2023_24'!$M:$M,MATCH($A12,'2023_24'!$A:$A,0))/INDEX('2023_24'!$G:$G,MATCH($A12,'2023_24'!$A:$A,0))*90,"") | Z12: =IFERROR(INDEX('2024_25'!$M:$M,MATCH($A12,'2024_25'!$A:$A,0))/INDEX('2024_25'!$G:$G,MATCH($A12,'2024_25'!$A:$A,0))*90,"") | AA12: =IFERROR(INDEX('2025_26'!$M:$M,MATCH($A12,'2025_26'!$A:$A,0))/INDEX('2025_26'!$G:$G,MATCH($A12,'2025_26'!$A:$A,0))*90,"") -> 3.6511156 | AB12: =IFERROR(SUMPRODUCT(S12:U12,{0.2,0.3,0.5})/SUMPRODUCT(--(S12:U12<>""),{0.2,0.3,0.5}),"") -> 0.009127789 | AC12: =IFERROR(SUMPRODUCT(V12:X12,{0.2,0.3,0.5})/SUMPRODUCT(--(V12:X12<>""),{0.2,0.3,0.5}),"") -> 0.057505071 | AD12: =IFERROR(SUMPRODUCT(Y12:AA12,{0.2,0.3,0.5})/SUMPRODUCT((Y12:AA12<>"")*{0.2,0.3,0.5}),O12) -> 3.6511156 | AE12: =COUNT(S12:U12) -> 1 | AF12: =IF(F12=0,"",E12/F12) -> 84 | AG12: =IF(AND(M12="",AB12=""),0,IF(M12="",AB12,IF(AB12="",M12,M12*AJ12+AB12*(1-AJ12)))) -> 0.0040162272 | AH12: =IF(AND(N12="",AC12=""),0,IF(N12="",AC12,IF(AC12="",N12,N12*AJ12+AC12*(1-AJ12)))) -> 0.028302231 | AI12: =IF(AND(O12="",AD12=""),0,IF(O12="",AD12,IF(AD12="",O12,O12*AJ12+AD12*(1-AJ12)))) -> 5.2064909 | AJ12: =IF($E12=0,0,MIN(0.9,$E12/300)) -> 0.56 | AK12: =IF(AE12=0,"YES","NO") -> NO | AL12: =IF($H12=0,0,$AG12*$H12/90) -> 0.0040162272 | AM12: =IF($H12=0,0,$AH12*$H12/90) -> 0.028302231 | AN12: =AL12 -> 0.0040162272 | AO12: =AM12 -> 0.028302231 | AP12: {=AL12*IF($C12="GKP",10,IF($C12="DEF",6,IF($C12="MID",5,4)))} -> 0.024097363 | AQ12: =AM12*3 -> 0.084906694 | AR12: =$G12*2 -> 2 | AS12: =IF($H12=0,0,Player_Analysis!$AM12*$H12/90) -> 4 | AT12: =IF($H12=0,0,$R12*$H12/90*2/IF(OR($C12="GKP",$C12="DEF"),10,12)) -> 1.0714286 | AU12: =0 -> 0 | AV12: =IF(INDEX(FPL_Raw_Data!K:K,MATCH(A12,FPL_Raw_Data!AA:AA,0))=0,"",INDEX(FPL_Raw_Data!P:P,MATCH(A12,FPL_Raw_Data!AA:AA,0))/INDEX(FPL_Raw_Data!K:K,MATCH(A12,FPL_Raw_Data!AA:AA,0))*90) -> 0 | AW12: =IF(AV12="",0,AV12/3) -> 0 | AX12: =IFERROR(INDEX(TEAM_ANALYSIS!$H$2:$H$21,MATCH($B12,TEAM_ANALYSIS!$A$2:$A$21,0)),0) -> 0.33333333 | AY12: =IF(OR($C12="GKP",$C12="DEF"),-($AX12/2),0) -> -0.16666667 | AZ12: =SUM(AP12:AU12)+AW12+AY12 -> 7.013766 | BA12: =IF($D12=0,0,$AZ12/$D12) -> 1.2988455 | BB12: =IFERROR(Player_Analysis!$Y12,1) -> 1.1808552 | BC12: =BB12*AZ12 -> 8.282242 | BD12: =BA12*BC12 -> 10.757353 | BE12: =BC12 -> 8.282242 | BF12: =IF($BE12="","",_xlfn.RANK.EQ($BE12,$BE$2:$BE$596,0)) -> 6 | BG12: =IF($BE12="","",COUNTIFS($C$2:$C$596,$C12,$BE$2:$BE$596,">"&$BE12)+COUNTIFS($C$2:$C12,$C12,$BE$2:$BE12,$BE12)) -> 5
A13: =Player_Analysis!A13 -> Bukayo Saka | B13: =Player_Analysis!C13 -> 1 | C13: =Player_Analysis!B13 -> MID | D13: =Player_Analysis!E13 -> 9.5 | E13: =Player_Analysis!I13 -> 246 | F13: =Player_Analysis!Z13 -> 3 | G13: =IF(E13=0,0,MIN(1,F13/(E13/90))) -> 1 | H13: =IF($E13=0,0,MIN(90,$G13*90)) -> 90 | I13: =Player_Analysis!AF13 -> 2 | J13: =Player_Analysis!AG13 -> 0 | K13: =Player_Analysis!O13 -> 1.5 | L13: =Player_Analysis!P13 -> 0.35 | M13: =IF(E13=0,"",K13/E13*90) -> 0.54878049 | N13: =IF(E13=0,"",L13/E13*90) -> 0.12804878 | O13: =IF(E13=0,"",Player_Analysis!L13/E13*90) -> 8.0487805 | P13: =IF(E13=0,"",Player_Analysis!Q13/E13*90) -> 0.67682927 | Q13: =IF(E13=0,"",(Player_Analysis!AD13/E13)*90) -> 34.756098 | R13: =IF(E13=0,"",Player_Analysis!AA13/E13*90) -> 8.0487805 | S13: {=IFERROR(INDEX('2023_24'!$O:$O,MATCH($A13,'2023_24'!$A:$A,0)),"")} -> 0.47433265 | T13: =IFERROR(INDEX('2024_25'!$P:$P,MATCH($A13,'2024_25'!$A:$A,0)),"") -> 0.35864269 | U13: =IFERROR(INDEX('2025_26'!$P:$P,MATCH($A13,'2025_26'!$A:$A,0)),"") -> 0.30716862 | V13: =IFERROR(INDEX('2023_24'!$P:$P,MATCH($A13,'2023_24'!$A:$A,0)),"") -> 0.33572895 | W13: =IFERROR(INDEX('2024_25'!$Q:$Q,MATCH($A13,'2024_25'!$A:$A,0)),"") -> 0.40614849 | X13: =IFERROR(INDEX('2025_26'!$Q:$Q,MATCH($A13,'2025_26'!$A:$A,0)),"") -> 0.29053201 | Y13: =IFERROR(INDEX('2023_24'!$M:$M,MATCH($A13,'2023_24'!$A:$A,0))/INDEX('2023_24'!$G:$G,MATCH($A13,'2023_24'!$A:$A,0))*90,"") -> 6.9609856 | Z13: =IFERROR(INDEX('2024_25'!$M:$M,MATCH($A13,'2024_25'!$A:$A,0))/INDEX('2024_25'!$G:$G,MATCH($A13,'2024_25'!$A:$A,0))*90,"") -> 6.6299304 | AA13: =IFERROR(INDEX('2025_26'!$M:$M,MATCH($A13,'2025_26'!$A:$A,0))/INDEX('2025_26'!$G:$G,MATCH($A13,'2025_26'!$A:$A,0))*90,"") -> 6.3706041 | AB13: =IFERROR(SUMPRODUCT(S13:U13,{0.2,0.3,0.5})/SUMPRODUCT(--(S13:U13<>""),{0.2,0.3,0.5}),"") -> 0.35604365 | AC13: =IFERROR(SUMPRODUCT(V13:X13,{0.2,0.3,0.5})/SUMPRODUCT(--(V13:X13<>""),{0.2,0.3,0.5}),"") -> 0.33425634 | AD13: =IFERROR(SUMPRODUCT(Y13:AA13,{0.2,0.3,0.5})/SUMPRODUCT((Y13:AA13<>"")*{0.2,0.3,0.5}),O13) -> 6.5664783 | AE13: =COUNT(S13:U13) -> 3 | AF13: =IF(F13=0,"",E13/F13) -> 82 | AG13: =IF(AND(M13="",AB13=""),0,IF(M13="",AB13,IF(AB13="",M13,M13*AJ13+AB13*(1-AJ13)))) -> 0.51408786 | AH13: =IF(AND(N13="",AC13=""),0,IF(N13="",AC13,IF(AC13="",N13,N13*AJ13+AC13*(1-AJ13)))) -> 0.16516614 | AI13: =IF(AND(O13="",AD13=""),0,IF(O13="",AD13,IF(AD13="",O13,O13*AJ13+AD13*(1-AJ13)))) -> 7.7819661 | AJ13: =IF($E13=0,0,MIN(0.9,$E13/300)) -> 0.82 | AK13: =IF(AE13=0,"YES","NO") -> NO | AL13: =IF($H13=0,0,$AG13*$H13/90) -> 0.51408786 | AM13: =IF($H13=0,0,$AH13*$H13/90) -> 0.16516614 | AN13: =AL13 -> 0.51408786 | AO13: =AM13 -> 0.16516614 | AP13: {=AL13*IF($C13="GKP",10,IF($C13="DEF",6,IF($C13="MID",5,4)))} -> 2.5704393 | AQ13: =AM13*3 -> 0.49549843 | AR13: =$G13*2 -> 2 | AS13: =IF($H13=0,0,Player_Analysis!$AM13*$H13/90) -> 0.66666667 | AT13: =IF($H13=0,0,$R13*$H13/90*2/IF(OR($C13="GKP",$C13="DEF"),10,12)) -> 1.3414634 | AU13: =0 -> 0 | AV13: =IF(INDEX(FPL_Raw_Data!K:K,MATCH(A13,FPL_Raw_Data!AA:AA,0))=0,"",INDEX(FPL_Raw_Data!P:P,MATCH(A13,FPL_Raw_Data!AA:AA,0))/INDEX(FPL_Raw_Data!K:K,MATCH(A13,FPL_Raw_Data!AA:AA,0))*90) -> 0 | AW13: =IF(AV13="",0,AV13/3) -> 0 | AX13: =IFERROR(INDEX(TEAM_ANALYSIS!$H$2:$H$21,MATCH($B13,TEAM_ANALYSIS!$A$2:$A$21,0)),0) -> 0.33333333 | AY13: =IF(OR($C13="GKP",$C13="DEF"),-($AX13/2),0) -> 0 | AZ13: =SUM(AP13:AU13)+AW13+AY13 -> 7.0740678 | BA13: =IF($D13=0,0,$AZ13/$D13) -> 0.74463871 | BB13: =IFERROR(Player_Analysis!$Y13,1) -> 1.0430363 | BC13: =BB13*AZ13 -> 7.3785097 | BD13: =BA13*BC13 -> 5.494324 | BE13: =BC13 -> 7.3785097 | BF13: =IF($BE13="","",_xlfn.RANK.EQ($BE13,$BE$2:$BE$596,0)) -> 16 | BG13: =IF($BE13="","",COUNTIFS($C$2:$C$596,$C13,$BE$2:$BE$596,">"&$BE13)+COUNTIFS($C$2:$C13,$C13,$BE$2:$BE13,$BE13)) -> 6
... A596: =Player_Analysis!A596 -> Pedro Porro Sauceda | B596: =Player_Analysis!C596 -> 19 | C596: =Player_Analysis!B596 -> DEF | D596: =Player_Analysis!E596 -> 5.5 | E596: =Player_Analysis!I596 -> 180 | F596: =Player_Analysis!Z596 -> 2 | G596: =IF(E596=0,0,MIN(1,F596/(E596/90))) -> 1 | H596: =IF($E596=0,0,MIN(90,$G596*90)) -> 90 | I596: =Player_Analysis!AF596 -> 0 | J596: =Player_Analysis!AG596 -> 0 | K596: =Player_Analysis!O596 -> 0.36 | L596: =Player_Analysis!P596 -> 0.16 | M596: =IF(E596=0,"",K596/E596*90) -> 0.18 | N596: =IF(E596=0,"",L596/E596*90) -> 0.08 | O596: =IF(E596=0,"",Player_Analysis!L596/E596*90) -> 4 | P596: =IF(E596=0,"",Player_Analysis!Q596/E596*90) -> 0.26 | Q596: =IF(E596=0,"",(Player_Analysis!AD596/E596)*90) -> 14.5 | R596: =IF(E596=0,"",Player_Analysis!AA596/E596*90) -> 4 | S596: {=IFERROR(INDEX('2023_24'!$O:$O,MATCH($A596,'2023_24'!$A:$A,0)),"")} | T596: =IFERROR(INDEX('2024_25'!$P:$P,MATCH($A596,'2024_25'!$A:$A,0)),"") | U596: =IFERROR(INDEX('2025_26'!$P:$P,MATCH($A596,'2025_26'!$A:$A,0)),"") -> 0.033834586 | V596: =IFERROR(INDEX('2023_24'!$P:$P,MATCH($A596,'2023_24'!$A:$A,0)),"") | W596: =IFERROR(INDEX('2024_25'!$Q:$Q,MATCH($A596,'2024_25'!$A:$A,0)),"") | X596: =IFERROR(INDEX('2025_26'!$Q:$Q,MATCH($A596,'2025_26'!$A:$A,0)),"") -> 0.14081633 | Y596: =IFERROR(INDEX('2023_24'!$M:$M,MATCH($A596,'2023_24'!$A:$A,0))/INDEX('2023_24'!$G:$G,MATCH($A596,'2023_24'!$A:$A,0))*90,"") | Z596: =IFERROR(INDEX('2024_25'!$M:$M,MATCH($A596,'2024_25'!$A:$A,0))/INDEX('2024_25'!$G:$G,MATCH($A596,'2024_25'!$A:$A,0))*90,"") | AA596: =IFERROR(INDEX('2025_26'!$M:$M,MATCH($A596,'2025_26'!$A:$A,0))/INDEX('2025_26'!$G:$G,MATCH($A596,'2025_26'!$A:$A,0))*90,"") -> 3.7701396 | AB596: =IFERROR(SUMPRODUCT(S596:U596,{0.2,0.3,0.5})/SUMPRODUCT(--(S596:U596<>""),{0.2,0.3,0.5}),"") -> 0.033834586 | AC596: =IFERROR(SUMPRODUCT(V596:X596,{0.2,0.3,0.5})/SUMPRODUCT(--(V596:X596<>""),{0.2,0.3,0.5}),"") -> 0.14081633 | AD596: =IFERROR(SUMPRODUCT(Y596:AA596,{0.2,0.3,0.5})/SUMPRODUCT((Y596:AA596<>"")*{0.2,0.3,0.5}),O596) -> 3.7701396 | AE596: =COUNT(S596:U596) -> 1 | AF596: =IF(F596=0,"",E596/F596) -> 90 | AG596: =IF(AND(M596="",AB596=""),0,IF(M596="",AB596,IF(AB596="",M596,M596*AJ596+AB596*(1-AJ596)))) -> 0.12153383 | AH596: =IF(AND(N596="",AC596=""),0,IF(N596="",AC596,IF(AC596="",N596,N596*AJ596+AC596*(1-AJ596)))) -> 0.10432653 | AI596: =IF(AND(O596="",AD596=""),0,IF(O596="",AD596,IF(AD596="",O596,O596*AJ596+AD596*(1-AJ596)))) -> 3.9080559 | AJ596: =IF($E596=0,0,MIN(0.9,$E596/300)) -> 0.6 | AK596: =IF(AE596=0,"YES","NO") -> NO | AL596: =IF($H596=0,0,$AG596*$H596/90) -> 0.12153383 | AM596: =IF($H596=0,0,$AH596*$H596/90) -> 0.10432653 | AN596: =AL596 -> 0.12153383 | AO596: =AM596 -> 0.10432653 | AP596: {=AL596*IF($C596="GKP",10,IF($C596="DEF",6,IF($C596="MID",5,4)))} -> 0.72920301 | AQ596: =AM596*3 -> 0.31297959 | AR596: =$G596*2 -> 2 | AS596: =IF($H596=0,0,Player_Analysis!$AM596*$H596/90) -> 2 | AT596: =IF($H596=0,0,$R596*$H596/90*2/IF(OR($C596="GKP",$C596="DEF"),10,12)) -> 0.8 | AU596: =0 -> 0 | AV596: =IF(INDEX(FPL_Raw_Data!K:K,MATCH(A596,FPL_Raw_Data!AA:AA,0))=0,"",INDEX(FPL_Raw_Data!P:P,MATCH(A596,FPL_Raw_Data!AA:AA,0))/INDEX(FPL_Raw_Data!K:K,MATCH(A596,FPL_Raw_Data!AA:AA,0))*90) -> 0 | AW596: =IF(AV596="",0,AV596/3) -> 0 | AX596: =IFERROR(INDEX(TEAM_ANALYSIS!$H$2:$H$21,MATCH($B596,TEAM_ANALYSIS!$A$2:$A$21,0)),0) -> 1.6666667 | AY596: =IF(OR($C596="GKP",$C596="DEF"),-($AX596/2),0) -> -0.83333333 | AZ596: =SUM(AP596:AU596)+AW596+AY596 -> 5.0088493 | BA596: =IF($D596=0,0,$AZ596/$D596) -> 0.91069987 | BB596: =IFERROR(Player_Analysis!$Y596,1) -> 0.97332359 | BC596: =BB596*AZ596 -> 4.8752312 | BD596: =BA596*BC596 -> 4.4398724 | BE596: =BC596 -> 4.8752312 | BF596: =IF($BE596="","",_xlfn.RANK.EQ($BE596,$BE$2:$BE$596,0)) -> 103 | BG596: =IF($BE596="","",COUNTIFS($C$2:$C$596,$C596,$BE$2:$BE$596,">"&$BE596)+COUNTIFS($C$2:$C596,$C596,$BE$2:$BE596,$BE596)) -> 39

Sheet 2023_24
A1: Player | B1: first_name | C1: second_name | D1: team | E1: element_type | F1: now_cost | G1: minutes | H1: starts | I1: goals_scored | J1: assists | K1: expected_goals | L1: expected_assists | M1: total_points | N1: bps | O1: xG_per_90 | P1: xA_per_90
A2: =_xlfn.CONCAT(B2, " ", C2) -> Folarin Balogun | B2: Folarin | C2: Balogun | D2: 1 | E2: 4 | F2: 44 | G2: 0 | H2: 0 | I2: 0 | J2: 0 | K2: 0 | L2: 0 | M2: 0 | N2: 0 | O2: =IFERROR(K2/G2*90,0) -> 0 | P2: =IFERROR(L2/G2*90,0) -> 0
A3: =_xlfn.CONCAT(B3, " ", C3) -> Cédric Alves Soares | B3: Cédric | C3: Alves Soares | D3: 1 | E3: 2 | F3: 38 | G3: 59 | H3: 0 | I3: 0 | J3: 0 | K3: 0 | L3: 0.02 | M3: 3 | N3: 15 | O3: =IFERROR(K3/G3*90,0) -> 0 | P3: =IFERROR(L3/G3*90,0) -> 0.030508475
A4: =_xlfn.CONCAT(B4, " ", C4) -> Mohamed Elneny | B4: Mohamed | C4: Elneny | D4: 1 | E4: 3 | F4: 44 | G4: 25 | H4: 0 | I4: 0 | J4: 1 | K4: 0.08 | L4: 0.01 | M4: 6 | N4: 16 | O4: =IFERROR(K4/G4*90,0) -> 0.288 | P4: =IFERROR(L4/G4*90,0) -> 0.036
A5: =_xlfn.CONCAT(B5, " ", C5) -> Fábio Ferreira Vieira | B5: Fábio | C5: Ferreira Vieira | D5: 1 | E5: 3 | F5: 54 | G5: 290 | H5: 2 | I5: 1 | J5: 3 | K5: 1.25 | L5: 0.64 | M5: 24 | N5: 67 | O5: =IFERROR(K5/G5*90,0) -> 0.38793103 | P5: =IFERROR(L5/G5*90,0) -> 0.19862069
A6: =_xlfn.CONCAT(B6, " ", C6) -> Gabriel dos Santos Magalhães | B6: Gabriel | C6: dos Santos Magalhães | D6: 1 | E6: 2 | F6: 54 | G6: 3042 | H6: 34 | I6: 3 | J6: 1 | K6: 4.48 | L6: 0.65 | M6: 149 | N6: 676 | O6: =IFERROR(K6/G6*90,0) -> 0.13254438 | P6: =IFERROR(L6/G6*90,0) -> 0.019230769
A7: =_xlfn.CONCAT(B7, " ", C7) -> Kai Havertz | B7: Kai | C7: Havertz | D7: 1 | E7: 3 | F7: 76 | G7: 2627 | H7: 30 | I7: 13 | J7: 10 | K7: 12.36 | L7: 3.88 | M7: 180 | N7: 515 | O7: =IFERROR(K7/G7*90,0) -> 0.4234488 | P7: =IFERROR(L7/G7*90,0) -> 0.13292729
A8: =_xlfn.CONCAT(B8, " ", C8) -> Gabriel Fernando de Jesus | B8: Gabriel | C8: Fernando de Jesus | D8: 1 | E8: 4 | F8: 77 | G8: 1470 | H8: 17 | I8: 4 | J8: 7 | K8: 6.27 | L8: 3.26 | M8: 85 | N8: 271 | O8: =IFERROR(K8/G8*90,0) -> 0.38387755 | P8: =IFERROR(L8/G8*90,0) -> 0.19959184
A9: =_xlfn.CONCAT(B9, " ", C9) -> Jorge Luiz Frello Filho | B9: Jorge Luiz | C9: Frello Filho | D9: 1 | E9: 3 | F9: 53 | G9: 913 | H9: 10 | I9: 0 | J9: 2 | K9: 0.1 | L9: 1.77 | M9: 44 | N9: 182 | O9: =IFERROR(K9/G9*90,0) -> 0.0098576123 | P9: =IFERROR(L9/G9*90,0) -> 0.17447974
A10: =_xlfn.CONCAT(B10, " ", C10) -> Jakub Kiwior | B10: Jakub | C10: Kiwior | D10: 1 | E10: 2 | F10: 40 | G10: 942 | H10: 11 | I10: 1 | J10: 3 | K10: 0.74 | L10: 0.6 | M10: 67 | N10: 260 | O10: =IFERROR(K10/G10*90,0) -> 0.070700637 | P10: =IFERROR(L10/G10*90,0) -> 0.057324841
A11: =_xlfn.CONCAT(B11, " ", C11) -> Marcus Oliveira Alencar | B11: Marcus | C11: Oliveira Alencar | D11: 1 | E11: 3 | F11: 45 | G11: 0 | H11: 0 | I11: 0 | J11: 0 | K11: 0 | L11: 0 | M11: 0 | N11: 0 | O11: =IFERROR(K11/G11*90,0) -> 0 | P11: =IFERROR(L11/G11*90,0) -> 0
A12: =_xlfn.CONCAT(B12, " ", C12) -> Gabriel Martinelli Silva | B12: Gabriel | C12: Martinelli Silva | D12: 1 | E12: 3 | F12: 75 | G12: 2010 | H12: 24 | I12: 6 | J12: 5 | K12: 6.36 | L12: 5.18 | M12: 118 | N12: 404 | O12: =IFERROR(K12/G12*90,0) -> 0.28477612 | P12: =IFERROR(L12/G12*90,0) -> 0.2319403
A13: =_xlfn.CONCAT(B13, " ", C13) -> Eddie Nketiah | B13: Eddie | C13: Nketiah | D13: 1 | E13: 4 | F13: 50 | G13: 1065 | H13: 10 | I13: 5 | J13: 4 | K13: 4.65 | L13: 0.53 | M13: 71 | N13: 206 | O13: =IFERROR(K13/G13*90,0) -> 0.39295775 | P13: =IFERROR(L13/G13*90,0) -> 0.044788732
... A866: =_xlfn.CONCAT(B866, " ", C866) -> Temple Ojinnaka | B866: Temple | C866: Ojinnaka | D866: 20 | E866: 3 | F866: 45 | G866: 0 | H866: 0 | I866: 0 | J866: 0 | K866: 0 | L866: 0 | M866: 0 | N866: 0 | O866: =IFERROR(K866/G866*90,0) -> 0 | P866: =IFERROR(L866/G866*90,0) -> 0

Sheet 2024_25
A1: Player | B1: first_name | C1: second_name | D1: team | E1: element_type | F1: now_cost | G1: minutes | H1: starts | I1: goals_scored | J1: assists | K1: expected_goals | L1: expected_assists | M1: total_points | N1: bps | O1: web_name | P1: xG_per_90 | Q1: xA_per_90
A2: =_xlfn.CONCAT(B2, " ", C2) -> Fábio Ferreira Vieira | B2: Fábio | C2: Ferreira Vieira | D2: 1 | E2: 3 | F2: 54 | G2: 0 | H2: 0 | I2: 0 | J2: 0 | K2: 0 | L2: 0 | M2: 0 | N2: 0 | O2: Fábio Vieira | P2: =IFERROR(K2/G2*90,0) -> 0 | Q2: =IFERROR(L2/G2*90,0) -> 0
A3: =_xlfn.CONCAT(B3, " ", C3) -> Gabriel Fernando de Jesus | B3: Gabriel | C3: Fernando de Jesus | D3: 1 | E3: 4 | F3: 65 | G3: 600 | H3: 6 | I3: 3 | J3: 2 | K3: 3.05 | L3: 0.52 | M3: 42 | N3: 152 | O3: G.Jesus | P3: =IFERROR(K3/G3*90,0) -> 0.4575 | Q3: =IFERROR(L3/G3*90,0) -> 0.078
A4: =_xlfn.CONCAT(B4, " ", C4) -> Gabriel dos Santos Magalhães | B4: Gabriel | C4: dos Santos Magalhães | D4: 1 | E4: 2 | F4: 61 | G4: 2363 | H4: 28 | I4: 3 | J4: 2 | K4: 2.7 | L4: 1.21 | M4: 117 | N4: 459 | O4: Gabriel | P4: =IFERROR(K4/G4*90,0) -> 0.10283538 | Q4: =IFERROR(L4/G4*90,0) -> 0.046085485
A5: =_xlfn.CONCAT(B5, " ", C5) -> Kai Havertz | B5: Kai | C5: Havertz | D5: 1 | E5: 4 | F5: 77 | G5: 1872 | H5: 21 | I5: 9 | J5: 3 | K5: 9.53 | L5: 1.65 | M5: 97 | N5: 343 | O5: Havertz | P5: =IFERROR(K5/G5*90,0) -> 0.45817308 | Q5: =IFERROR(L5/G5*90,0) -> 0.079326923
A6: =_xlfn.CONCAT(B6, " ", C6) -> Karl Hein | B6: Karl | C6: Hein | D6: 1 | E6: 1 | F6: 40 | G6: 0 | H6: 0 | I6: 0 | J6: 0 | K6: 0 | L6: 0 | M6: 0 | N6: 0 | O6: Hein | P6: =IFERROR(K6/G6*90,0) -> 0 | Q6: =IFERROR(L6/G6*90,0) -> 0
A7: =_xlfn.CONCAT(B7, " ", C7) -> Jurriën Timber | B7: Jurriën | C7: Timber | D7: 1 | E7: 2 | F7: 55 | G7: 2415 | H7: 27 | I7: 1 | J7: 3 | K7: 1.23 | L7: 1.3 | M7: 114 | N7: 426 | O7: J.Timber | P7: =IFERROR(K7/G7*90,0) -> 0.045838509 | Q7: =IFERROR(L7/G7*90,0) -> 0.048447205
A8: =_xlfn.CONCAT(B8, " ", C8) -> Jorge Luiz Frello Filho | B8: Jorge Luiz | C8: Frello Filho | D8: 1 | E8: 3 | F8: 46 | G8: 701 | H8: 9 | I8: 0 | J8: 0 | K8: 0.06 | L8: 0.59 | M8: 20 | N8: 112 | O8: Jorginho | P8: =IFERROR(K8/G8*90,0) -> 0.007703281 | Q8: =IFERROR(L8/G8*90,0) -> 0.07574893
A9: =_xlfn.CONCAT(B9, " ", C9) -> Jakub Kiwior | B9: Jakub | C9: Kiwior | D9: 1 | E9: 2 | F9: 49 | G9: 1117 | H9: 10 | I9: 1 | J9: 0 | K9: 0.17 | L9: 0.29 | M9: 43 | N9: 178 | O9: Kiwior | P9: =IFERROR(K9/G9*90,0) -> 0.013697404 | Q9: =IFERROR(L9/G9*90,0) -> 0.023366159
A10: =_xlfn.CONCAT(B10, " ", C10) -> Gabriel Martinelli Silva | B10: Gabriel | C10: Martinelli Silva | D10: 1 | E10: 3 | F10: 65 | G10: 2284 | H10: 25 | I10: 8 | J10: 4 | K10: 7.13 | L10: 4.46 | M10: 125 | N10: 422 | O10: Martinelli | P10: =IFERROR(K10/G10*90,0) -> 0.28095447 | Q10: =IFERROR(L10/G10*90,0) -> 0.17574431
A11: =_xlfn.CONCAT(B11, " ", C11) -> Ethan Nwaneri | B11: Ethan | C11: Nwaneri | D11: 1 | E11: 3 | F11: 43 | G11: 882 | H11: 11 | I11: 4 | J11: 2 | K11: 1.19 | L11: 1.78 | M11: 66 | N11: 251 | O11: Nwaneri | P11: =IFERROR(K11/G11*90,0) -> 0.12142857 | Q11: =IFERROR(L11/G11*90,0) -> 0.18163265
A12: =_xlfn.CONCAT(B12, " ", C12) -> Martin Ødegaard | B12: Martin | C12: Ødegaard | D12: 1 | E12: 3 | F12: 82 | G12: 2321 | H12: 26 | I12: 3 | J12: 9 | K12: 4.85 | L12: 6.68 | M12: 116 | N12: 529 | O12: Ødegaard | P12: =IFERROR(K12/G12*90,0) -> 0.18806549 | Q12: =IFERROR(L12/G12*90,0) -> 0.25902628
A13: =_xlfn.CONCAT(B13, " ", C13) -> David Raya Martin | B13: David | C13: Raya Martin | D13: 1 | E13: 1 | F13: 56 | G13: 3420 | H13: 38 | I13: 0 | J13: 0 | K13: 0 | L13: 0.03 | M13: 142 | N13: 555 | O13: Raya | P13: =IFERROR(K13/G13*90,0) -> 0 | Q13: =IFERROR(L13/G13*90,0) -> 0.00078947368
... A805: =_xlfn.CONCAT(B805, " ", C805) -> Mateus Mané | B805: Mateus | C805: Mané | D805: 20 | E805: 4 | F805: 45 | G805: 1 | H805: 0 | I805: 0 | J805: 0 | K805: 0 | L805: 0 | M805: 1 | N805: 3 | O805: Mané | P805: =IFERROR(K805/G805*90,0) -> 0 | Q805: =IFERROR(L805/G805*90,0) -> 0
A806: =_xlfn.CONCAT(B806, " ", C806)
A807: =_xlfn.CONCAT(B807, " ", C807)
A808: =_xlfn.CONCAT(B808, " ", C808)
A809: =_xlfn.CONCAT(B809, " ", C809)
A810: =_xlfn.CONCAT(B810, " ", C810)
A811: =_xlfn.CONCAT(B811, " ", C811)
A812: =_xlfn.CONCAT(B812, " ", C812)
A813: =_xlfn.CONCAT(B813, " ", C813)
A814: =_xlfn.CONCAT(B814, " ", C814)
A815: =_xlfn.CONCAT(B815, " ", C815)
A816: =_xlfn.CONCAT(B816, " ", C816)
A817: =_xlfn.CONCAT(B817, " ", C817)
... A866: =_xlfn.CONCAT(B866, " ", C866)

Sheet 2025_26
A1: Player | B1: first_name | C1: second_name | D1: team | E1: element_type | F1: now_cost | G1: minutes | H1: starts | I1: goals_scored | J1: assists | K1: expected_goals | L1: expected_assists | M1: total_points | N1: bps | O1: defensive_contribution | P1: xG_per_90 | Q1: xA_per_90
A2: =_xlfn.CONCAT(B2, " ", C2) -> David Raya Martín | B2: David | C2: Raya Martín | D2: 1 | E2: 1 | F2: 62 | G2: 3330 | H2: 37 | I2: 0 | J2: 0 | K2: 0 | L2: 0.07 | M2: 162 | N2: 633 | O2: 0 | P2: =IFERROR(K2/G2*90,0) -> 0 | Q2: =IFERROR(L2/G2*90,0) -> 0.0018918919
A3: =_xlfn.CONCAT(B3, " ", C3) -> Kepa Arrizabalaga Revuelta | B3: Kepa | C3: Arrizabalaga Revuelta | D3: 1 | E3: 1 | F3: 40 | G3: 90 | H3: 1 | I3: 0 | J3: 0 | K3: 0 | L3: 0 | M3: 2 | N3: 11 | O3: 0 | P3: =IFERROR(K3/G3*90,0) -> 0 | Q3: =IFERROR(L3/G3*90,0) -> 0
A4: =_xlfn.CONCAT(B4, " ", C4) -> Karl Hein | B4: Karl | C4: Hein | D4: 1 | E4: 1 | F4: 40 | G4: 0 | H4: 0 | I4: 0 | J4: 0 | K4: 0 | L4: 0 | M4: 0 | N4: 0 | O4: 0 | P4: =IFERROR(K4/G4*90,0) -> 0 | Q4: =IFERROR(L4/G4*90,0) -> 0
A5: =_xlfn.CONCAT(B5, " ", C5) -> Tommy Setford | B5: Tommy | C5: Setford | D5: 1 | E5: 1 | F5: 39 | G5: 0 | H5: 0 | I5: 0 | J5: 0 | K5: 0 | L5: 0 | M5: 0 | N5: 0 | O5: 0 | P5: =IFERROR(K5/G5*90,0) -> 0 | Q5: =IFERROR(L5/G5*90,0) -> 0
A6: =_xlfn.CONCAT(B6, " ", C6) -> Gabriel dos Santos Magalhães | B6: Gabriel | C6: dos Santos Magalhães | D6: 1 | E6: 2 | F6: 73 | G6: 2750 | H6: 30 | I6: 3 | J6: 5 | K6: 2.94 | L6: 1.75 | M6: 209 | N6: 724 | O6: 277 | P6: =IFERROR(K6/G6*90,0) -> 0.096218182 | Q6: =IFERROR(L6/G6*90,0) -> 0.057272727
A7: =_xlfn.CONCAT(B7, " ", C7) -> William Saliba | B7: William | C7: Saliba | D7: 1 | E7: 2 | F7: 63 | G7: 2614 | H7: 30 | I7: 1 | J7: 0 | K7: 0.88 | L7: 1.21 | M7: 137 | N7: 581 | O7: 193 | P7: =IFERROR(K7/G7*90,0) -> 0.030298393 | Q7: =IFERROR(L7/G7*90,0) -> 0.041660291
A8: =_xlfn.CONCAT(B8, " ", C8) -> Riccardo Calafiori | B8: Riccardo | C8: Calafiori | D8: 1 | E8: 2 | F8: 56 | G8: 1697 | H8: 22 | I8: 1 | J8: 2 | K8: 3.36 | L8: 0.76 | M8: 109 | N8: 389 | O8: 102 | P8: =IFERROR(K8/G8*90,0) -> 0.17819682 | Q8: =IFERROR(L8/G8*90,0) -> 0.040306423
A9: =_xlfn.CONCAT(B9, " ", C9) -> Jurriën Timber | B9: Jurriën | C9: Timber | D9: 1 | E9: 2 | F9: 60 | G9: 2452 | H9: 28 | I9: 3 | J9: 6 | K9: 4.71 | L9: 1.53 | M9: 149 | N9: 532 | O9: 148 | P9: =IFERROR(K9/G9*90,0) -> 0.17287928 | Q9: =IFERROR(L9/G9*90,0) -> 0.056158238
A10: =_xlfn.CONCAT(B10, " ", C10) -> Jakub Kiwior | B10: Jakub | C10: Kiwior | D10: 1 | E10: 2 | F10: 54 | G10: 0 | H10: 0 | I10: 0 | J10: 0 | K10: 0 | L10: 0 | M10: 0 | N10: 0 | O10: 0 | P10: =IFERROR(K10/G10*90,0) -> 0 | Q10: =IFERROR(L10/G10*90,0) -> 0
A11: =_xlfn.CONCAT(B11, " ", C11) -> Myles Lewis-Skelly | B11: Myles | C11: Lewis-Skelly | D11: 1 | E11: 2 | F11: 50 | G11: 697 | H11: 5 | I11: 0 | J11: 0 | K11: 0.1 | L11: 0.2 | M11: 29 | N11: 110 | O11: 25 | P11: =IFERROR(K11/G11*90,0) -> 0.012912482 | Q11: =IFERROR(L11/G11*90,0) -> 0.025824964
A12: =_xlfn.CONCAT(B12, " ", C12) -> Benjamin White | B12: Benjamin | C12: White | D12: 1 | E12: 2 | F12: 51 | G12: 699 | H12: 9 | I12: 0 | J12: 1 | K12: 0.45 | L12: 0.69 | M12: 45 | N12: 181 | O12: 53 | P12: =IFERROR(K12/G12*90,0) -> 0.057939914 | Q12: =IFERROR(L12/G12*90,0) -> 0.088841202
A13: =_xlfn.CONCAT(B13, " ", C13) -> Brayden Clarke | B13: Brayden | C13: Clarke | D13: 1 | E13: 2 | F13: 37 | G13: 0 | H13: 0 | I13: 0 | J13: 0 | K13: 0 | L13: 0 | M13: 0 | N13: 0 | O13: 0 | P13: =IFERROR(K13/G13*90,0) -> 0 | Q13: =IFERROR(L13/G13*90,0) -> 0
... A842: =_xlfn.CONCAT(B842, " ", C842) -> Josh Gracey | B842: Josh | C842: Gracey | D842: 20 | E842: 1 | F842: 40 | G842: 0 | H842: 0 | I842: 0 | J842: 0 | K842: 0 | L842: 0 | M842: 0 | N842: 0 | O842: 0 | P842: =IFERROR(K842/G842*90,0) -> 0 | Q842: =IFERROR(L842/G842*90,0) -> 0
A843: =_xlfn.CONCAT(B843, " ", C843)
A844: =_xlfn.CONCAT(B844, " ", C844)
A845: =_xlfn.CONCAT(B845, " ", C845)
A846: =_xlfn.CONCAT(B846, " ", C846)
A847: =_xlfn.CONCAT(B847, " ", C847)
A848: =_xlfn.CONCAT(B848, " ", C848)
A849: =_xlfn.CONCAT(B849, " ", C849)
A850: =_xlfn.CONCAT(B850, " ", C850)
A851: =_xlfn.CONCAT(B851, " ", C851)
A852: =_xlfn.CONCAT(B852, " ", C852)
A853: =_xlfn.CONCAT(B853, " ", C853)
A854: =_xlfn.CONCAT(B854, " ", C854)
... A866: =_xlfn.CONCAT(B866, " ", C866)

Sheet MODEL_CONFIG
A1: Historical xG/90 prior | B1: 0.15
A2: Historical xA/90 prior | B2: 0.1
A3: Historical Points/90 prior | B3: 4
A4: Minutes prior | B4: 60
A5: Max xG/90 | B5: 1.5
A6: Max xA/90 | B6: 1
A7: Current season starting weight | B7: 0.2
A8: Historical weight | B8: 0.8

Sheet TEAM_ANALYSIS
A1: Team ID | B1: Team Code | C1: Team Name | D1: Games Played | E1: Goals Scored | F1: Goals Conceded | G1: Goals/Game | H1: Goals Conceded/Game | I1: Clean Sheets | J1: Clean Sheet % | K1: Attacking Score | L1: Defensive Score | M1: Overall Team Score | N1: FPL Attack Home | O1: FPL Attack Away | P1: FPL Defence Home | Q1: FPL Defence Away | R1: FPL Overall Home | S1: FPL Overall Away | T1: Preseason Attack Score | U1: Preseason Defence Score | V1: Preseason Overall Score | W1: Smoothed Goals/Game | X1: Smoothed Goals Conceded/Game | Y1: Attack Strength | Z1: Defence Weakness
A2: =Raw_Teams!B2 -> 1 | B2: =INDEX(Raw_Teams!$D:$D,MATCH(A2,Raw_Teams!$B:$B,0)) -> ARS | C2: =INDEX(Raw_Teams!$C:$C,MATCH(A2,Raw_Teams!$B:$B,0)) -> Arsenal | D2: =COUNTIFS(Fixture_Raw!$B:$B,TRUE,Fixture_Raw!$E:$E,$A2)+COUNTIFS(Fixture_Raw!$B:$B,TRUE,Fixture_Raw!$G:$G,$A2) -> 3 | E2: =SUMIFS(Fixture_Raw!$H:$H,Fixture_Raw!$B:$B,TRUE,Fixture_Raw!$G:$G,$A2)+SUMIFS(Fixture_Raw!$F:$F,Fixture_Raw!$B:$B,TRUE,Fixture_Raw!$E:$E,$A2) -> 6 | F2: =SUMIFS(Fixture_Raw!$F:$F,Fixture_Raw!$B:$B,TRUE,Fixture_Raw!$G:$G,$A2)+SUMIFS(Fixture_Raw!$H:$H,Fixture_Raw!$B:$B,TRUE,Fixture_Raw!$E:$E,$A2) -> 1 | G2: =IFERROR(E2/D2,0) -> 2 | H2: =IFERROR(F2/D2,0) -> 0.33333333 | I2: =COUNTIFS(Fixture_Raw!$B:$B,TRUE,Fixture_Raw!$G:$G,$A2,Fixture_Raw!$F:$F,0)+COUNTIFS(Fixture_Raw!$B:$B,TRUE,Fixture_Raw!$E:$E,$A2,Fixture_Raw!$H:$H,0) -> 2 | J2: =IFERROR(I2/D2,0) -> 0.66666667 | K2: =IFERROR(G2/MAX($G$2:$G$21)*100,0) -> 75 | L2: =IFERROR(MIN($H$2:$H$21)/H2*100,0) -> 0 | M2: =K2*50%+L2*50% -> 37.5 | N2: =IFERROR(INDEX(Raw_Teams!$E:$E,MATCH($A2,Raw_Teams!$A:$A,0)),0) -> 0 | O2: =IFERROR(INDEX(Raw_Teams!$D:$D,MATCH($D2,Raw_Teams!$A:$A,0)),0) -> ARS | P2: =IFERROR(INDEX(Raw_Teams!$G:$G,MATCH($A2,Raw_Teams!$A:$A,0)),0) -> 0 | W2: =IFERROR((E2+AVERAGE($E$2:$E$21))/(D2+1),AVERAGE($E$2:$E$21)) -> 2.5625 | X2: =IFERROR((F2+AVERAGE($F$2:$F$21))/(D2+1),AVERAGE($F$2:$F$21)) -> 1.3125 | Y2: =IFERROR(W2/AVERAGE($W$2:$W$21),1) -> 1.2058824 | Z2: =IFERROR(X2/AVERAGE($X$2:$X$21),1) -> 0.61764706
A3: =Raw_Teams!B3 -> 2 | B3: =INDEX(Raw_Teams!$D:$D,MATCH(A3,Raw_Teams!$B:$B,0)) -> AVL | C3: =INDEX(Raw_Teams!$C:$C,MATCH(A3,Raw_Teams!$B:$B,0)) -> Aston Villa | D3: =COUNTIFS(Fixture_Raw!$B:$B,TRUE,Fixture_Raw!$E:$E,$A3)+COUNTIFS(Fixture_Raw!$B:$B,TRUE,Fixture_Raw!$G:$G,$A3) -> 3 | E3: =SUMIFS(Fixture_Raw!$H:$H,Fixture_Raw!$B:$B,TRUE,Fixture_Raw!$G:$G,$A3)+SUMIFS(Fixture_Raw!$F:$F,Fixture_Raw!$B:$B,TRUE,Fixture_Raw!$E:$E,$A3) -> 0 | F3: =SUMIFS(Fixture_Raw!$F:$F,Fixture_Raw!$B:$B,TRUE,Fixture_Raw!$G:$G,$A3)+SUMIFS(Fixture_Raw!$H:$H,Fixture_Raw!$B:$B,TRUE,Fixture_Raw!$E:$E,$A3) -> 5 | G3: =IFERROR(E3/D3,0) -> 0 | H3: =IFERROR(F3/D3,0) -> 1.6666667 | I3: =COUNTIFS(Fixture_Raw!$B:$B,TRUE,Fixture_Raw!$G:$G,$A3,Fixture_Raw!$F:$F,0)+COUNTIFS(Fixture_Raw!$B:$B,TRUE,Fixture_Raw!$E:$E,$A3,Fixture_Raw!$H:$H,0) -> 1 | J3: =IFERROR(I3/D3,0) -> 0.33333333 | K3: =IFERROR(G3/MAX($G$2:$G$21)*100,0) -> 0 | L3: =IFERROR(MIN($H$2:$H$21)/H3*100,0) -> 0 | M3: =K3*50%+L3*50% -> 0 | N3: =IFERROR(INDEX(Raw_Teams!$E:$E,MATCH($A3,Raw_Teams!$A:$A,0)),0) -> 0 | O3: =IFERROR(INDEX(Raw_Teams!$D:$D,MATCH($D3,Raw_Teams!$A:$A,0)),0) -> ARS | P3: =IFERROR(INDEX(Raw_Teams!$G:$G,MATCH($A3,Raw_Teams!$A:$A,0)),0) -> 0 | W3: =IFERROR((E3+AVERAGE($E$2:$E$21))/(D3+1),AVERAGE($E$2:$E$21)) -> 1.0625 | X3: =IFERROR((F3+AVERAGE($F$2:$F$21))/(D3+1),AVERAGE($F$2:$F$21)) -> 2.3125 | Y3: =IFERROR(W3/AVERAGE($W$2:$W$21),1) -> 0.5 | Z3: =IFERROR(X3/AVERAGE($X$2:$X$21),1) -> 1.0882353
A4: =Raw_Teams!B4 -> 3 | B4: =INDEX(Raw_Teams!$D:$D,MATCH(A4,Raw_Teams!$B:$B,0)) -> BOU | C4: =INDEX(Raw_Teams!$C:$C,MATCH(A4,Raw_Teams!$B:$B,0)) -> Bournemouth | D4: =COUNTIFS(Fixture_Raw!$B:$B,TRUE,Fixture_Raw!$E:$E,$A4)+COUNTIFS(Fixture_Raw!$B:$B,TRUE,Fixture_Raw!$G:$G,$A4) -> 3 | E4: =SUMIFS(Fixture_Raw!$H:$H,Fixture_Raw!$B:$B,TRUE,Fixture_Raw!$G:$G,$A4)+SUMIFS(Fixture_Raw!$F:$F,Fixture_Raw!$B:$B,TRUE,Fixture_Raw!$E:$E,$A4) -> 4 | F4: =SUMIFS(Fixture_Raw!$F:$F,Fixture_Raw!$B:$B,TRUE,Fixture_Raw!$G:$G,$A4)+SUMIFS(Fixture_Raw!$H:$H,Fixture_Raw!$B:$B,TRUE,Fixture_Raw!$E:$E,$A4) -> 5 | G4: =IFERROR(E4/D4,0) -> 1.3333333 | H4: =IFERROR(F4/D4,0) -> 1.6666667 | I4: =COUNTIFS(Fixture_Raw!$B:$B,TRUE,Fixture_Raw!$G:$G,$A4,Fixture_Raw!$F:$F,0)+COUNTIFS(Fixture_Raw!$B:$B,TRUE,Fixture_Raw!$E:$E,$A4,Fixture_Raw!$H:$H,0) -> 0 | J4: =IFERROR(I4/D4,0) -> 0 | K4: =IFERROR(G4/MAX($G$2:$G$21)*100,0) -> 50 | L4: =IFERROR(MIN($H$2:$H$21)/H4*100,0) -> 0 | M4: =K4*50%+L4*50% -> 25 | N4: =IFERROR(INDEX(Raw_Teams!$E:$E,MATCH($A4,Raw_Teams!$A:$A,0)),0) -> 0 | O4: =IFERROR(INDEX(Raw_Teams!$D:$D,MATCH($D4,Raw_Teams!$A:$A,0)),0) -> ARS | P4: =IFERROR(INDEX(Raw_Teams!$G:$G,MATCH($A4,Raw_Teams!$A:$A,0)),0) -> 0 | W4: =IFERROR((E4+AVERAGE($E$2:$E$21))/(D4+1),AVERAGE($E$2:$E$21)) -> 2.0625 | X4: =IFERROR((F4+AVERAGE($F$2:$F$21))/(D4+1),AVERAGE($F$2:$F$21)) -> 2.3125 | Y4: =IFERROR(W4/AVERAGE($W$2:$W$21),1) -> 0.97058824 | Z4: =IFERROR(X4/AVERAGE($X$2:$X$21),1) -> 1.0882353
A5: =Raw_Teams!B5 -> 4 | B5: =INDEX(Raw_Teams!$D:$D,MATCH(A5,Raw_Teams!$B:$B,0)) -> BRE | C5: =INDEX(Raw_Teams!$C:$C,MATCH(A5,Raw_Teams!$B:$B,0)) -> Brentford | D5: =COUNTIFS(Fixture_Raw!$B:$B,TRUE,Fixture_Raw!$E:$E,$A5)+COUNTIFS(Fixture_Raw!$B:$B,TRUE,Fixture_Raw!$G:$G,$A5) -> 3 | E5: =SUMIFS(Fixture_Raw!$H:$H,Fixture_Raw!$B:$B,TRUE,Fixture_Raw!$G:$G,$A5)+SUMIFS(Fixture_Raw!$F:$F,Fixture_Raw!$B:$B,TRUE,Fixture_Raw!$E:$E,$A5) -> 5 | F5: =SUMIFS(Fixture_Raw!$F:$F,Fixture_Raw!$B:$B,TRUE,Fixture_Raw!$G:$G,$A5)+SUMIFS(Fixture_Raw!$H:$H,Fixture_Raw!$B:$B,TRUE,Fixture_Raw!$E:$E,$A5) -> 2 | G5: =IFERROR(E5/D5,0) -> 1.6666667 | H5: =IFERROR(F5/D5,0) -> 0.66666667 | I5: =COUNTIFS(Fixture_Raw!$B:$B,TRUE,Fixture_Raw!$G:$G,$A5,Fixture_Raw!$F:$F,0)+COUNTIFS(Fixture_Raw!$B:$B,TRUE,Fixture_Raw!$E:$E,$A5,Fixture_Raw!$H:$H,0) -> 1 | J5: =IFERROR(I5/D5,0) -> 0.33333333 | K5: =IFERROR(G5/MAX($G$2:$G$21)*100,0) -> 62.5 | L5: =IFERROR(MIN($H$2:$H$21)/H5*100,0) -> 0 | M5: =K5*50%+L5*50% -> 31.25 | N5: =IFERROR(INDEX(Raw_Teams!$E:$E,MATCH($A5,Raw_Teams!$A:$A,0)),0) -> 0 | O5: =IFERROR(INDEX(Raw_Teams!$D:$D,MATCH($D5,Raw_Teams!$A:$A,0)),0) -> ARS | P5: =IFERROR(INDEX(Raw_Teams!$G:$G,MATCH($A5,Raw_Teams!$A:$A,0)),0) -> 0 | W5: =IFERROR((E5+AVERAGE($E$2:$E$21))/(D5+1),AVERAGE($E$2:$E$21)) -> 2.3125 | X5: =IFERROR((F5+AVERAGE($F$2:$F$21))/(D5+1),AVERAGE($F$2:$F$21)) -> 1.5625 | Y5: =IFERROR(W5/AVERAGE($W$2:$W$21),1) -> 1.0882353 | Z5: =IFERROR(X5/AVERAGE($X$2:$X$21),1) -> 0.73529412
A6: =Raw_Teams!B6 -> 5 | B6: =INDEX(Raw_Teams!$D:$D,MATCH(A6,Raw_Teams!$B:$B,0)) -> BHA | C6: =INDEX(Raw_Teams!$C:$C,MATCH(A6,Raw_Teams!$B:$B,0)) -> Brighton | D6: =COUNTIFS(Fixture_Raw!$B:$B,TRUE,Fixture_Raw!$E:$E,$A6)+COUNTIFS(Fixture_Raw!$B:$B,TRUE,Fixture_Raw!$G:$G,$A6) -> 3 | E6: =SUMIFS(Fixture_Raw!$H:$H,Fixture_Raw!$B:$B,TRUE,Fixture_Raw!$G:$G,$A6)+SUMIFS(Fixture_Raw!$F:$F,Fixture_Raw!$B:$B,TRUE,Fixture_Raw!$E:$E,$A6) -> 8 | F6: =SUMIFS(Fixture_Raw!$F:$F,Fixture_Raw!$B:$B,TRUE,Fixture_Raw!$G:$G,$A6)+SUMIFS(Fixture_Raw!$H:$H,Fixture_Raw!$B:$B,TRUE,Fixture_Raw!$E:$E,$A6) -> 5 | G6: =IFERROR(E6/D6,0) -> 2.6666667 | H6: =IFERROR(F6/D6,0) -> 1.6666667 | I6: =COUNTIFS(Fixture_Raw!$B:$B,TRUE,Fixture_Raw!$G:$G,$A6,Fixture_Raw!$F:$F,0)+COUNTIFS(Fixture_Raw!$B:$B,TRUE,Fixture_Raw!$E:$E,$A6,Fixture_Raw!$H:$H,0) -> 1 | J6: =IFERROR(I6/D6,0) -> 0.33333333 | K6: =IFERROR(G6/MAX($G$2:$G$21)*100,0) -> 100 | L6: =IFERROR(MIN($H$2:$H$21)/H6*100,0) -> 0 | M6: =K6*50%+L6*50% -> 50 | N6: =IFERROR(INDEX(Raw_Teams!$E:$E,MATCH($A6,Raw_Teams!$A:$A,0)),0) -> 0 | O6: =IFERROR(INDEX(Raw_Teams!$D:$D,MATCH($D6,Raw_Teams!$A:$A,0)),0) -> ARS | P6: =IFERROR(INDEX(Raw_Teams!$G:$G,MATCH($A6,Raw_Teams!$A:$A,0)),0) -> 0 | W6: =IFERROR((E6+AVERAGE($E$2:$E$21))/(D6+1),AVERAGE($E$2:$E$21)) -> 3.0625 | X6: =IFERROR((F6+AVERAGE($F$2:$F$21))/(D6+1),AVERAGE($F$2:$F$21)) -> 2.3125 | Y6: =IFERROR(W6/AVERAGE($W$2:$W$21),1) -> 1.4411765 | Z6: =IFERROR(X6/AVERAGE($X$2:$X$21),1) -> 1.0882353
A7: =Raw_Teams!B7 -> 6 | B7: =INDEX(Raw_Teams!$D:$D,MATCH(A7,Raw_Teams!$B:$B,0)) -> CHE | C7: =INDEX(Raw_Teams!$C:$C,MATCH(A7,Raw_Teams!$B:$B,0)) -> Chelsea | D7: =COUNTIFS(Fixture_Raw!$B:$B,TRUE,Fixture_Raw!$E:$E,$A7)+COUNTIFS(Fixture_Raw!$B:$B,TRUE,Fixture_Raw!$G:$G,$A7) -> 3 | E7: =SUMIFS(Fixture_Raw!$H:$H,Fixture_Raw!$B:$B,TRUE,Fixture_Raw!$G:$G,$A7)+SUMIFS(Fixture_Raw!$F:$F,Fixture_Raw!$B:$B,TRUE,Fixture_Raw!$E:$E,$A7) -> 8 | F7: =SUMIFS(Fixture_Raw!$F:$F,Fixture_Raw!$B:$B,TRUE,Fixture_Raw!$G:$G,$A7)+SUMIFS(Fixture_Raw!$H:$H,Fixture_Raw!$B:$B,TRUE,Fixture_Raw!$E:$E,$A7) -> 7 | G7: =IFERROR(E7/D7,0) -> 2.6666667 | H7: =IFERROR(F7/D7,0) -> 2.3333333 | I7: =COUNTIFS(Fixture_Raw!$B:$B,TRUE,Fixture_Raw!$G:$G,$A7,Fixture_Raw!$F:$F,0)+COUNTIFS(Fixture_Raw!$B:$B,TRUE,Fixture_Raw!$E:$E,$A7,Fixture_Raw!$H:$H,0) -> 0 | J7: =IFERROR(I7/D7,0) -> 0 | K7: =IFERROR(G7/MAX($G$2:$G$21)*100,0) -> 100 | L7: =IFERROR(MIN($H$2:$H$21)/H7*100,0) -> 0 | M7: =K7*50%+L7*50% -> 50 | N7: =IFERROR(INDEX(Raw_Teams!$E:$E,MATCH($A7,Raw_Teams!$A:$A,0)),0) -> 0 | O7: =IFERROR(INDEX(Raw_Teams!$D:$D,MATCH($D7,Raw_Teams!$A:$A,0)),0) -> ARS | P7: =IFERROR(INDEX(Raw_Teams!$G:$G,MATCH($A7,Raw_Teams!$A:$A,0)),0) -> 0 | W7: =IFERROR((E7+AVERAGE($E$2:$E$21))/(D7+1),AVERAGE($E$2:$E$21)) -> 3.0625 | X7: =IFERROR((F7+AVERAGE($F$2:$F$21))/(D7+1),AVERAGE($F$2:$F$21)) -> 2.8125 | Y7: =IFERROR(W7/AVERAGE($W$2:$W$21),1) -> 1.4411765 | Z7: =IFERROR(X7/AVERAGE($X$2:$X$21),1) -> 1.3235294
A8: =Raw_Teams!B8 -> 7 | B8: =INDEX(Raw_Teams!$D:$D,MATCH(A8,Raw_Teams!$B:$B,0)) -> COV | C8: =INDEX(Raw_Teams!$C:$C,MATCH(A8,Raw_Teams!$B:$B,0)) -> Coventry City | D8: =COUNTIFS(Fixture_Raw!$B:$B,TRUE,Fixture_Raw!$E:$E,$A8)+COUNTIFS(Fixture_Raw!$B:$B,TRUE,Fixture_Raw!$G:$G,$A8) -> 3 | E8: =SUMIFS(Fixture_Raw!$H:$H,Fixture_Raw!$B:$B,TRUE,Fixture_Raw!$G:$G,$A8)+SUMIFS(Fixture_Raw!$F:$F,Fixture_Raw!$B:$B,TRUE,Fixture_Raw!$E:$E,$A8) -> 0 | F8: =SUMIFS(Fixture_Raw!$F:$F,Fixture_Raw!$B:$B,TRUE,Fixture_Raw!$G:$G,$A8)+SUMIFS(Fixture_Raw!$H:$H,Fixture_Raw!$B:$B,TRUE,Fixture_Raw!$E:$E,$A8) -> 5 | G8: =IFERROR(E8/D8,0) -> 0 | H8: =IFERROR(F8/D8,0) -> 1.6666667 | I8: =COUNTIFS(Fixture_Raw!$B:$B,TRUE,Fixture_Raw!$G:$G,$A8,Fixture_Raw!$F:$F,0)+COUNTIFS(Fixture_Raw!$B:$B,TRUE,Fixture_Raw!$E:$E,$A8,Fixture_Raw!$H:$H,0) -> 0 | J8: =IFERROR(I8/D8,0) -> 0 | K8: =IFERROR(G8/MAX($G$2:$G$21)*100,0) -> 0 | L8: =IFERROR(MIN($H$2:$H$21)/H8*100,0) -> 0 | M8: =K8*50%+L8*50% -> 0 | N8: =IFERROR(INDEX(Raw_Teams!$E:$E,MATCH($A8,Raw_Teams!$A:$A,0)),0) -> 0 | O8: =IFERROR(INDEX(Raw_Teams!$D:$D,MATCH($D8,Raw_Teams!$A:$A,0)),0) -> ARS | P8: =IFERROR(INDEX(Raw_Teams!$G:$G,MATCH($A8,Raw_Teams!$A:$A,0)),0) -> 0 | W8: =IFERROR((E8+AVERAGE($E$2:$E$21))/(D8+1),AVERAGE($E$2:$E$21)) -> 1.0625 | X8: =IFERROR((F8+AVERAGE($F$2:$F$21))/(D8+1),AVERAGE($F$2:$F$21)) -> 2.3125 | Y8: =IFERROR(W8/AVERAGE($W$2:$W$21),1) -> 0.5 | Z8: =IFERROR(X8/AVERAGE($X$2:$X$21),1) -> 1.0882353
